Workbook

Sheet Kas Fisik Bahan Baku
A1: LAPORAN BELANJA BAHAN BAKU
A2: KOPERASI GOTONG ROYONG SEJAHTERA NUSANTARA
A3: MEI 2026
A6: TANGGAL | B6: NO | C6: NAMA TOKO | D6: NAMA BARANG | E6: SATUAN | F6: QTY | G6: HARGA | H6: SUBTOTAL | I6: TOTAL | J6: ADMIN
A7: 24 Mei 2026 | H7: TOTAL | I7: =sum(I8:I42) -> 10990000 | J7: =sum(J8:J42) -> 20000
C8: RICHARD TANTAMA | D8: KNOOR CHICK POWDER | E8: KG | F8: 6 | G8: =H8/F8 -> 94000 | H8: 564000 | I8: =H8 -> 564000 | K8: v
C9: DINAWATI | D9: BAMER KULIT | E9: KG | F9: 9 | G9: 36000 | H9: =F9*G9 -> 324000
D10: BAMER KUPAS | E10: KG | F10: 3 | G10: 40000 | H10: =F10*G10 -> 120000
D11: BAPUT KUPAS | E11: KG | F11: 8 | G11: 30000 | H11: =F11*G11 -> 240000 | I11: =SUM(H9:H11) -> 684000 | K11: v
C12: PT. BERKAT SINERGI TERPADU | D12: BOMBAY CAMBRIDGE 50/60 CRB | E12: KARUNG | F12: 20 | G12: =H12/F12 -> 19000 | H12: 380000 | I12: =H12 -> 380000 | K12: v
C13: AMMIRUDIN | D13: KOL | E13: KG | F13: 60 | G13: 7500 | H13: =F13*G13 -> 450000 | I13: =H13 -> 450000 | K13: v
C14: SRI WATI | D14: BUNCIS | E14: KG | F14: 80 | G14: 20000 | H14: =F14*G14 -> 1600000
D15: CABE MERAH | E15: KG | F15: 6 | G15: 70000 | H15: =F15*G15 -> 420000
D16: RAWIT MERAH | E16: KG | F16: 5 | G16: 90000 | H16: =F16*G16 -> 450000
D17: DAUN BAWANG | E17: KG | F17: 4 | G17: 15000 | H17: =F17*G17 -> 60000
D18: JAHE | E18: KG | F18: 2 | G18: 20000 | H18: =F18*G18 -> 40000
D19: CESIM | E19: KG | F19: 20 | G19: 6000 | H19: =F19*G19 -> 120000
D20: TIMUN | E20: KG | F20: 105 | G20: 8000 | H20: =F20*G20 -> 840000
D21: WORTEL | E21: KG | F21: 142 | G21: 12000 | H21: =F21*G21 -> 1704000
D22: PAKCOY | E22: KG | F22: 90 | G22: 10000 | H22: =F22*G22 -> 900000 | I22: =SUM(H14:H22) -> 6134000 | K22: v
C23: RUSDIANTO | D23: LAOS | E23: KG | F23: 2 | G23: =H23/F23 -> 12000 | H23: 24000
D24: SEREH | E24: KG | F24: 2 | G24: =H24/F24 -> 10000 | H24: 20000
D25: KUNIR | E25: KG | F25: 1 | G25: =H25/F25 -> 12000 | H25: 12000
D26: SALAM | E26: KG | F26: 1 | G26: =H26/F26 -> 14000 | H26: 14000 | I26: =SUM(H23:H26) -> 70000 | K26: v
C27: ADE SETIAWAN | D27: TOMAT | E27: KG | F27: 30 | G27: 12000 | H27: =F27*G27 -> 360000 | I27: =H27 -> 360000 | K27: v
C28: H.ZAENAL | D28: GULA PUTIH | E28: KG | F28: 20 | G28: 18500 | H28: =F28*G28 -> 370000
D29: KECAP INGGRIS | E29: KG | F29: 1 | G29: 47000 | H29: =F29*G29 -> 47000
D30: BANGO 1.5 | E30: BOTOL | F30: 4 | G30: 48000 | H30: =F30*G30 -> 192000
D31: KEMIRI | E31: PCS | F31: 2 | G31: 43000 | H31: =F31*G31 -> 86000
D32: LADA HITAM | E32: KG | F32: 0.25 | G32: =H32/F32 -> 180000 | H32: 45000
D33: ROYCO | E33: KG | F33: 3 | G33: 42000 | H33: =F33*G33 -> 126000
D34: SAOS TOMAT | E34: DRIGEN | F34: 1 | G34: 95000 | H34: =F34*G34 -> 95000
D35: SAOS CILLI | E35: DRIGEN | F35: 1 | G35: 115000 | H35: =F35*G35 -> 115000
D36: SAOS TIRAM | E36: BOTOL | F36: 6 | G36: 52000 | H36: =F36*G36 -> 312000
D37: TERASI 1/2 KG | E37: PCS | F37: 2 | G37: 6000 | H37: =F37*G37 -> 12000
D38: TERIGU | E38: SAK | F38: 2 | G38: 225000 | H38: =F38*G38 -> 450000
D39: MAYZENA | E39: KG | F39: 2 | G39: 24000 | H39: =F39*G39 -> 48000
D40: GARAM | E40: BAL | F40: 1 | G40: 70000 | H40: =F40*G40 -> 70000
D41: KECAP BANGO | E41: DRIGEN | F41: 2 | G41: 190000 | H41: =F41*G41 -> 380000 | I41: =SUM(H28:H41) -> 2348000 | K41: v
D42: ADMIN | F42: 8 | G42: 2500 | H42: =F42*G42 -> 20000 | J42: =H42 -> 20000
A43: 25 Mei 2026 | H43: TOTAL | I43: =sum(I44:I105) -> 71663250 | J43: =sum(J44:J105) -> 35000
C44: Yahman Gunadi | D44: Tempe Tegalsari | E44: Papan | F44: 46 | G44: 12000 | H44: =F44*G44 -> 552000
D45: Tempe Tegalsari | E45: Papan | F45: 60 | G45: 12000 | H45: =F45*G45 -> 720000
D46: Tahu Pong Tegalsari | E46: Pcs | F46: 1424 | G46: 750 | H46: =F46*G46 -> 1068000
D47: Tahu Mentah Putih | E47: Pcs | F47: 1424 | G47: 500 | H47: =F47*G47 -> 712000
D48: Tahu Mentah Putih | E48: Pcs | F48: 1424 | G48: 500 | H48: =F48*G48 -> 712000 | I48: =sum(H44:H48) -> 3764000 | K48: v
C49: Sri Yatun | D49: KURANG TF BAWANG PUTIH | E49: KG | F49: 4 | G49: 28000 | H49: =F49*G49 -> 112000 | I49: =H49 -> 112000 | K49: v
C50: BANUROJA | D50: BERAS | E50: KG | F50: 1075 | G50: 14500 | H50: =F50*G50 -> 15587500 | I50: =H50 -> 15587500 | K50: v
C51: RICHARD | D51: SINARMAS CURAH (MARGARIN) | E51: KG | F51: 2 | G51: 24000 | H51: =F51*G51 -> 48000
D52: KNOOR CHIC POWDER | E52: KG | F52: 2 | G52: 94500 | H52: =F52*G52 -> 189000
D53: SAJIKU TEPUNG 900GR | E53: PCS | F53: 16 | G53: =H53/F53 -> 22500 | H53: 360000
D54: SAJIKU TEPUNG 900GR | E54: PCS | F54: 14 | G54: =H54/F54 -> 22700 | H54: 317800 | I54: =SUM(H51:H54) -> 914800 | K54: v
C55: DINAWATI DEWI | D55: BAMER KULIT | E55: KG | F55: 11 | G55: 34000 | H55: =F55*G55 -> 374000
D56: BAMER KUPAS | E56: KG | F56: 11 | G56: 40000 | H56: =F56*G56 -> 440000
D57: BAPUT KUPAS | E57: KG | F57: 8 | G57: 30000 | H57: =F57*G57 -> 240000 | I57: =SUM(H55:H57) -> 1054000 | K57: v
C58: RUSDIANTO | D58: DAUN JERUK | E58: KG | F58: 0.25 | G58: 40000 | H58: =F58*G58 -> 10000
D59: SALAM | E59: KG | F59: 0.25 | G59: 28000 | H59: =F59*G59 -> 7000
D60: LIMAU | E60: KG | H60: 18000
D61: KENCUR | E61: KG | F61: 1 | G61: 35000 | H61: =F61*G61 -> 35000
D62: KUNIR | E62: KG | F62: 6 | G62: =H62/F62 -> 11666.667 | H62: 70000
D63: LENGKUAS | E63: KG | F63: 6.5 | G63: =H63/F63 -> 12000 | H63: 78000
D64: SEREH | E64: KG | F64: 3 | G64: 11000 | H64: =F64*G64 -> 33000 | I64: =SUM(H58:H64) -> 251000 | K64: v
C65: SRI WATI | D65: WORTEL | E65: KG | F65: 160 | G65: 12000 | H65: =F65*G65 -> 1920000
D66: DAUN BAWANG | E66: KG | F66: 6 | G66: 15000 | H66: =F66*G66 -> 90000
D67: PECAY | E67: KG | F67: 80 | G67: 12000 | H67: =F67*G67 -> 960000
D68: CABE MERAH | E68: KG | F68: 5 | G68: 70000 | H68: =F68*G68 -> 350000
D69: KENTANG | E69: KG | F69: 2 | G69: 18000 | H69: =F69*G69 -> 36000
D70: KACANG PANJANG | E70: KG | F70: 25 | G70: 15000 | H70: =F70*G70 -> 375000
D71: WALUH | E71: KG | F71: 67 | G71: 9000 | H71: =F71*G71 -> 603000
D72: TIMUN | E72: KG | F72: 125 | G72: 9000 | H72: =F72*G72 -> 1125000
D73: KELAPA PARUD | E73: KG | F73: 9 | G73: 22000 | H73: =F73*G73 -> 198000 | I73: =SUM(H65:H73) -> 5657000 | K73: v
C74: AMMIRUDIN | D74: KOL | E74: KG | F74: 40 | G74: 8000 | H74: =F74*G74 -> 320000 | I74: =H74 -> 320000 | K74: v
C75: H.ZAENAL | D75: ASEM | E75: PACK | F75: 2 | G75: 20000 | H75: =F75*G75 -> 40000
D76: TEPUNG TAPIOK | E76: KG | F76: 3 | G76: 13000 | H76: =F76*G76 -> 39000
D77: TEPUNG BERAS | E77: KG | F77: 2 | G77: 16500 | H77: =F77*G77 -> 33000
D78: KECAP BANGO | E78: DRIGEN | F78: 2 | G78: 190000 | H78: =F78*G78 -> 380000
D79: MINYAK WIJEN | E79: BOTOL | F79: 1 | G79: 48000 | H79: =F79*G79 -> 48000
D80: LADA BUBUK | E80: KG | F80: 1 | G80: 140000 | H80: =F80*G80 -> 140000
D81: GULA MERAH | E81: KG | F81: 10 | G81: 16000 | H81: =F81*G81 -> 160000
D82: GULA PUTIH | E82: KG | F82: 13 | G82: 18500 | H82: =F82*G82 -> 240500
D83: SINTI 100GR | E83: PCS | F83: 20 | G83: 5200 | H83: =F83*G83 -> 104000
D84: BANGO 1,5 | E84: KG | F84: 1 | G84: 48000 | H84: =F84*G84 -> 48000
D85: KEMIRI | E85: KG | F85: 6 | G85: 43000 | H85: =F85*G85 -> 258000
D86: KETUMBAR | E86: KG | F86: 1 | G86: 30000 | H86: =F86*G86 -> 30000
D87: LADA BUBUK | E87: KG | F87: 1 | G87: 140000 | H87: =F87*G87 -> 140000
... D92: TERIGU SEGITIGA | E92: KG | F92: 14 | G92: 11500 | H92: =F92*G92 -> 161000
D93: BAWANG PUTIH SUPER | E93: KG | F93: 20 | G93: 28000 | H93: =F93*G93 -> 560000 | I93: =sum(H75:H93) -> 2795500 | K93: v
C94: H.ZAENAL | D94: CABE BUBUK | E94: KG | F94: 1 | G94: 85000 | H94: =F94*G94 -> 85000
D95: DRIGEN SAOS TOMAT | E95: DRIGEN | F95: 1 | G95: 95000 | H95: =F95*G95 -> 95000 | I95: =sum(H94:H95) -> 180000 | K95: v
C96: DWINANTO | D96: Tempe Kalikoa | E96: Papan | F96: 90 | G96: 12000 | H96: =F96*G96 -> 1080000
D97: Kacang Giling | E97: Kg | F97: 22 | G97: 55000 | H97: =F97*G97 -> 1210000 | I97: =SUM(H96:H97) -> 2290000 | K97: v
C98: APIPAH | D98: Bandeng Presto | E98: Ekor | F98: 2550 | G98: 3500 | H98: =F98*G98 -> 8925000 | I98: =H98 -> 8925000 | K98: v
C99: PANDI | D99: Daging Ayam Potong Binawan | E99: Kg | F99: 210 | G99: 33500 | H99: =F99*G99 -> 7035000
D100: Daging Ayam Fillet tanpa kulit Werkudara | E100: Kg | F100: 117.4 | G100: 46500 | H100: =F100*G100 -> 5459100
D101: Daging Ayam Potong Bakung 2 | E101: Kg | F101: 215 | G101: 33500 | H101: =F101*G101 -> 7202500 | I101: =SUM(H99:H101) -> 19696600 | K101: v
C102: UD. ANIK | D102: TELUR KALIKOA | E102: KG | F102: 135 | G102: 25500 | H102: =F102*G102 -> 3442500
D103: TELUR BAKUNG 01 | E103: KG | F103: 135 | G103: 25500 | H103: =F103*G103 -> 3442500
D104: TELUR WERKUDARA | F104: 126.7 | G104: 25500 | H104: =F104*G104 -> 3230850 | I104: =SUM(H102:H104) -> 10115850 | K104: v
D105: ADMIN | F105: 14 | G105: 2500 | H105: =F105*G105 -> 35000 | J105: =H105 -> 35000
A106: 26 Mei 2026 | H106: TOTAL | I106: =sum(I107:I112) -> 16250000 | J106: =sum(J107:J159) -> 32500
...

Sheet Kas Fisik Oprasional
A1: LAPORAN BELANJA OPERASIONAL
A2: KOPERASI GOTONG ROYONG SEJAHTERA NUSANTARA
A3: MEI 2026
A6: TANGGAL | B6: NO | C6: NAMA TOKO | D6: NAMA BARANG | E6: SATUAN | F6: QTY | G6: HARGA | H6: SUBTOTAL | I6: TOTAL | J6: ADMIN
A7: 24 Mei 2026 | H7: TOTAL | I7: =sum(I8:I17) -> 1547500 | J7: =sum(J8:J17) -> 5000
C8: TK JAYA | D8: HIT SEMPROT BESAR | E8: BOTOL | F8: 5 | G8: 32500 | H8: =F8*G8 -> 162500
D9: TISU MUKA PASEO | E9: PACK | F9: 10 | G9: 9000 | H9: =F9*G9 -> 90000
D10: WIPOL BOTOL BESAR | E10: BOTOL | F10: 15 | G10: 20000 | H10: =F10*G10 -> 300000
D11: KIT SABUN MOTOR | E11: PACK | F11: 1 | G11: 15000 | H11: =F11*G11 -> 15000
D12: SOKLIN PEL SEREH | E12: DRIGEN | F12: 3 | G12: 53000 | H12: =F12*G12 -> 159000 | I12: =sum(H8:H12) -> 726500 | K12: v
C13: TK ANYAR | D13: STIK ESKRIM | E13: PACK | F13: 8 | G13: 16000 | H13: =F13*G13 -> 128000
D14: PLASTIK PP 10X25 02 | E14: PACK | F14: 11 | G14: 11000 | H14: =F14*G14 -> 121000
D15: PLASTIK ES 15X35 | E15: PACK | F15: 4 | G15: 13000 | H15: =F15*G15 -> 52000
D16: CUP SAMBAL 35 ML | E16: PACK | F16: 40 | G16: 13000 | H16: =F16*G16 -> 520000 | I16: =sum(H13:H16) -> 821000 | K16: v
D17: ADMIN | F17: 2 | G17: 2500 | H17: =F17*G17 -> 5000 | J17: =H17 -> 5000
A18: 25 Mei 2026 | H18: TOTAL | I18: =sum(I19:I34) -> 4838400 | J18: =sum(J19:J34) -> 12500
C19: TK SINAR JAYA | D19: ALAT KUPAS WORTEL | E19: PCS | F19: 8 | G19: 6000 | H19: =F19*G19 -> 48000
D20: ALAT KOCOKAN TELOR | E20: PCS | F20: 1 | G20: 20000 | H20: =F20*G20 -> 20000
D21: LAP MICROFIBER ISI 10 KLEANER | E21: PCS | F21: 5 | G21: 96700 | H21: =F21*G21 -> 483500
D22: LAP KANEBO | E22: PCS | F22: 4 | G22: 10000 | H22: =F22*G22 -> 40000
D23: PAYUNG | E23: PCS | F23: 5 | G23: 25500 | H23: =F23*G23 -> 127500 | I23: =sum(H19:H23) -> 719000 | K23: v
C24: TK SANITAS | D24: KAPORIT BUBUK (15 kg) | E24: EMBER | F24: 1 | G24: 470000 | H24: =F24*G24 -> 470000 | I24: =H24 -> 470000 | K24: v
C25: TK EKA KNMN | D25: PLASTIK HDPLONG | E25: PACK | F25: 10.3 | G25: 48000 | H25: =F25*G25 -> 494400
D26: THINWAL KOTAK 500 ML (500 PCS) | E26: KARDUS | F26: 2 | G26: 505000 | H26: =F26*G26 -> 1010000
D27: THINWAL KOTAK 500 ML | E27: PACK | F27: 14 | G27: 26500 | H27: =F27*G27 -> 371000
D28: PLASTIK ES 12X25 (4 PACK) | E28: IKAT | F28: 20 | G28: 39500 | H28: =F28*G28 -> 790000
D29: PLASTIK ES 10X26 | E29: IKAT | F29: 5 | G29: 39500 | H29: =F29*G29 -> 197500
D30: STIK ES KRIM | E30: PACK | F30: 5 | G30: 15000 | H30: =F30*G30 -> 75000
D31: PLASTIK PP 40X60 RAMAYANA | E31: PACK | F31: 1 | G31: 43000 | H31: =F31*G31 -> 43000 | I31: =sum(H25:H31) -> 2980900 | K31: v
C32: TK SAMUDRA | D32: SARUNG TANGAN KAIN | E32: LUSIN | F32: 1 | G32: 28500 | H32: =F32*G32 -> 28500 | I32: =H32 -> 28500 | K32: v
C33: TK SEMARANG | D33: JENGKOK PLASTIK LION STAR | E33: PCS | F33: 16 | G33: 40000 | H33: =F33*G33 -> 640000 | I33: =H33 -> 640000 | K33: v
D34: ADMIN | F34: 5 | G34: 2500 | H34: =F34*G34 -> 12500 | J34: =H34 -> 12500
A35: 28 Mei 2026 | H35: TOTAL | I35: =sum(I36:I42) -> 3678000 | J35: =sum(J36:J51) -> 7500
C36: RIZKI FADILLAH | D36: GAS 50KG TEGALSARI | E36: TABUNG | F36: 1 | G36: 1125000 | H36: =F36*G36 -> 1125000
C37: RIZKI FADILLAH | D37: GAS 50KG BAKUNG 01 | E37: TABUNG | F37: 2 | G37: 1125000 | H37: =F37*G37 -> 2250000 | I37: =sum(H36:H37) -> 3375000 | K37: v
C38: NUR AISYAH | D38: SESER IKAN 30 CM | F38: 1 | G38: 30000
D39: SESER IKAN 15 CM | F39: 1 | G39: 15000
D40: EMBER 69CM | F40: 4 | G40: 180000
D41: GELAS PLASTIK HAWAI | F41: 12 | G41: 78000 | H41: =SUM(G38:G41) -> 303000 | I41: =H41 -> 303000 | K41: v
D42: ADMIN | F42: 2 | G42: 2500 | H42: =F42*G42 -> 5000 | J42: =H42 -> 5000
A43: 29 Mei 2026 | H43: TOTAL | I43: =sum(I44:I53) -> 14010000 | J43: =sum(J44:J53) -> 2500
C44: RIZKI FADLILAH | D44: GAS 50KG BAKUNG 02 | E44: TABUNG | F44: 2 | G44: 1125000 | H44: =F44*G44 -> 2250000
D45: GAS 50KG TEGALSARI | E45: TABUNG | F45: 1 | G45: 1125000 | H45: =F45*G45 -> 1125000
D46: GAS 50KG BINAWAN | E46: TABUNG | F46: 1 | G46: 1125000 | H46: =F46*G46 -> 1125000
D47: GAS 50KG BAKUNG 02 | E47: TABUNG | F47: 1 | G47: 1125000 | H47: =F47*G47 -> 1125000
D48: GAS 50KG BINAWAN | E48: TABUNG | F48: 2 | G48: 1125000 | H48: =F48*G48 -> 2250000
D49: GAS 50KG WERKUDARA | E49: TABUNG | F49: 2 | G49: 1125000 | H49: =F49*G49 -> 2250000
D50: GAS 12KG WERKUDARA | E50: TABUNG | F50: 2 | G50: 255000 | H50: =F50*G50 -> 510000
D51: GAS 50KG TEGALSARI | E51: TABUNG | F51: 1 | G51: 1125000 | H51: =F51*G51 -> 1125000
D52: GAS 50KG BAKUNG 01 | E52: TABUNG | F52: 2 | G52: 1125000 | H52: =F52*G52 -> 2250000 | I52: =SUM(H44:H52) -> 14010000 | K52: v
D53: ADMIN | F53: 1 | G53: 2500 | H53: =F53*G53 -> 2500 | J53: =H53 -> 2500
A54: 1 JUNI 2026 | H54: TOTAL | I54: =sum(I55:I68) -> 13604500 | J54: =sum(J55:J68) -> 10000
C55: RIZKI FADLILAH | D55: GAS 50KG TEGALSARI 29 MEI | E55: TABUNG | F55: 1 | G55: 1125000 | H55: =G55*F55 -> 1125000
D56: GAS 50KG BAKUNG 02 29 MEI | E56: TABUNG | F56: 2 | G56: 1125000 | H56: =G56*F56 -> 2250000
D57: GAS 50KG KALIKOA 30 MEI | E57: TABUNG | F57: 3 | G57: 1125000 | H57: =G57*F57 -> 3375000
D58: GAS 50KG BINAWAN 30 MEI | E58: TABUNG | F58: 2 | G58: 1125000 | H58: =G58*F58 -> 2250000 | I58: =SUM(H55:H58) -> 9000000 | K58: v
C59: EKA MAJU | D59: KLIR SAUCE 25ML (40) | E59: PAK | F59: 27 | G59: 9000 | H59: =G59*F59 -> 243000
D60: ALUMUNIUM FOIL 45CM (24) | E60: ROLL | F60: 5 | G60: 28500 | H60: =G60*F60 -> 142500
D61: KERTAS ROTI | E61: LEMBAR | F61: 5 | G61: 2000 | H61: =F61*G61 -> 10000 | I61: =SUM(H59:H61) -> 395500
C62: TOKO ANYAR | D62: 200ML | E62: DUS | F62: 5 | G62: 290000 | H62: =F62*G62 -> 1450000
D63: 200ML | E63: DUS | F63: 2 | G63: 14500 | H63: =F63*G63 -> 29000
D64: P 02 | E64: KG | F64: 5 | G64: 42000 | H64: =F64*G64 -> 210000
D65: OX 100 | E65: DUS | F65: 1 | G65: 1000000 | H65: =F65*G65 -> 1000000
D66: PELASTIK ES | E66: PACK | F66: 90 | G66: 12500 | H66: =F66*G66 -> 1125000 | I66: =SUM(H62:H66) -> 3814000
C67: JUANITA | D67: PLESTER HANSAPLAS ISI 100 | E67: PACK | F67: 10 | G67: 39500 | H67: =F67*G67 -> 395000 | I67: =H67 -> 395000
D68: ADMIN | F68: 4 | G68: 2500 | H68: =F68*G68 -> 10000 | J68: =H68 -> 10000
A69: 2 Juni 2026 | H69: TOTAL | I69: =SUM(I70:I94) -> 4464020 | J69: =SUM(J70:J94) -> 17500
C70: CV. CARMELIA | D70: SARUNG TANGAN NITRIL M BIRU | E70: PACK | F70: 5 | G70: =H70/F70 -> 85000 | H70: 425000 | I70: =H70 -> 425000
C71: SAMUDRA | D71: SARUNG TANGAN SB | E71: LUSIN | F71: 1 | G71: 28500 | H71: =F71*G71 -> 28500 | I71: =H71 -> 28500
C72: TOKO SEMARANG | D72: IRUS LUBANG 6.5 | E72: PCS | F72: 2 | G72: 25000 | H72: =F72*G72 -> 50000
D73: IRUS SS SML | E73: PCS | F73: 2 | G73: 12500 | H73: =F73*G73 -> 25000
D74: PEMANTIK API GAS TEMBAK | E74: PCS | F74: 2 | G74: 25000 | H74: =F74*G74 -> 50000
D75: LAP SERBET KAIN KOTAK HAND APPLE | E75: PCS | F75: 12 | G75: 5000 | H75: =F75*G75 -> 60000 | I75: =SUM(H72:H75) -> 185000
C76: EKA MAJU | D76: PLASTIK PLONG MIX PACKING | E76: KG | F76: 7.74 | G76: 48000 | H76: =F76*G76 -> 371520
D77: PELASTIK SAMPAH 90X120 (50) | E77: BALL | F77: 1 | G77: 450000 | H77: =F77*G77 -> 450000
D78: PELASTIK SAMPAH 60X100 | E78: IKAT | F78: 1 | G78: 47500 | H78: =F78*G78 -> 47500
D79: KERESEK HD MINO PUTIH UK 2 | E79: PACK | F79: 2 | G79: 15500 | H79: =F79*G79 -> 31000
D80: KERESEK ANIMA 35 HITAM 6 | E80: PACK | F80: 2 | G80: 11000 | H80: =F80*G80 -> 22000 | I80: =SUM(H76:H80) -> 922020
C81: SINAR JAYA | D81: SUSHI ROLL CYPRUS | E81: PCS | F81: 10 | G81: 27000 | H81: =F81*G81 -> 270000 | I81: =H81 -> 270000
D82: HIT SEMPROT BESAR | E82: PCS | F82: 7 | G82: 32500 | H82: =F82*G82 -> 227500
D83: GAYUNG MANDI | E83: PCS | F83: 5 | G83: 10000 | H83: =F83*G83 -> 50000
D84: KARBOL SHUNTON BULAT | E84: PCS | F84: 16 | G84: 27000 | H84: =F84*G84 -> 432000
D85: SABUN KIT CUCI MOBIL | E85: PCS | F85: 1 | G85: 15000 | H85: =F85*G85 -> 15000
D86: PEACE KARBOL SEREH | E86: PCS | F86: 2 | G86: 107000 | H86: =F86*G86 -> 214000
D87: SO KLIN APEL DRIGEN | E87: PCS | F87: 2 | G87: 57000 | H87: =F87*G87 -> 114000
D88: KOPI GOODDAY MOCCACINO | E88: DUS | F88: 1 | G88: 230000 | H88: =F88*G88 -> 230000
D89: KOPI GOODDAY FREEZE | E89: DUS | F89: 1 | G89: 302000 | H89: =F89*G89 -> 302000
D90: MIE SEDAP GORENG | E90: DUS | F90: 1 | G90: 124000 | H90: =F90*G90 -> 124000
D91: KOPI KAPAL API SPECIAL | E91: DUS | F91: 1 | G91: 225000 | H91: =F91*G91 -> 225000
D92: MAP TULANG PLASTIK A4 | E92: PCS | F92: 2 | G92: 35000 | H92: =F92*G92 -> 70000 | I92: =SUM(H82:H92) -> 2003500
C93: ASIYAH | D93: SABUN CUCI SUNLIGHT | F93: 6 | G93: 105000 | H93: =F93*G93 -> 630000 | I93: =H93 -> 630000
D94: ADMIN | F94: 7 | G94: 2500 | H94: =F94*G94 -> 17500 | J94: =H94 -> 17500
A95: 3 Juni 2026 | H95: TOTAL | I95: =SUM(I96:I103) -> 2466000 | J95: =SUM(J96:J103) -> 7500
C96: EKA MAJU | D96: PLASTIK ES UK 12X25 | E96: IKAT | F96: 10 | G96: 39500 | H96: =F96*G96 -> 395000
D97: KLIR BOWL 200ML (20) | E97: DUS | F97: 5 | G97: 270000 | H97: =F97*G97 -> 1350000
D98: SPOND | E98: PCS | F98: 24 | G98: 2000 | H98: =F98*G98 -> 48000 | I98: =SUM(H96:H98) -> 1793000
C99: EKA MAJU | D99: KLIR SAUCE 25ML(40) | E99: DUS | F99: 1 | G99: 305000 | H99: =F99*G99 -> 305000
D100: KLIR SAUCE 25ML(40) | E100: PAK | F100: 12 | G100: 9000 | H100: =F100*G100 -> 108000 | I100: =SUM(H99:H100) -> 413000
C101: SANITAS | D101: TAWAS | E101: KG | F101: 5 | G101: 10000 | H101: =F101*G101 -> 50000
D102: PENGURAI IPAL BIO L 500GR | E102: PCS | F102: 5 | G102: 42000 | H102: =F102*G102 -> 210000 | I102: =SUM(H101:H102) -> 260000
...

Sheet list Reimburse
A1: LIST REIMBURSE
A2: KOPERASI GOTONG ROYONG SEJAHTERA NUSANTARA
A3: MEI 2026
A6: TANGGAL | B6: NO | C6: NAMA TOKO | D6: NAMA BARANG | E6: SATUAN | F6: QTY | G6: HARGA | H6: SUBTOTAL | I6: TOTAL | J6: ADMIN | K6: =I7+I10+I12+I15+I32+I37+I45+I48+I57+I70+I72+I83+I86+I89+I94+I99 -> 8308150
A7: 25 Mei 2026 | H7: TOTAL | I7: =sum(I8:I9) -> 264000 | J7: =sum(J8:J9) -> 2500
C8: FIA BINAWAN | D8: AYAM | E8: Kg | F8: 8 | G8: 33000 | H8: =F8*G8 -> 264000 | I8: =H8 -> 264000 | K8: v
D9: ADMIN | F9: 1 | G9: 2500 | H9: =F9*G9 -> 2500 | J9: =H9 -> 2500
A10: 28 Mei 2026 | H10: TOTAL | I10: =sum(I11) -> 105000 | J10: =sum(J11) -> 0
A11: 25 Mei | C11: WERKUDARA | D11: GULA | E11: KG | F11: 6 | G11: 17500 | H11: =F11*G11 -> 105000 | I11: =H11 -> 105000 | K11: v
A12: 31 Mei 2026 | H12: TOTAL | I12: =SUM(I13:I14) -> 90000 | J12: =SUM(J13:J14) -> 0
A13: 25 Mei | C13: GUNADI KALIKOA | D13: BAWANG BOMBAY | E13: KG | F13: 3.45 | G13: 30000 | H13: =F13*G13 -> 103500
H14: -13500 | I14: =SUM(H13:H14) -> 90000 | K14: v
A15: 1 Juni 2026 | H15: TOTAL | I15: =SUM(I16:I31) -> 1517600 | J15: =SUM(J16:J31) -> 0
C16: FIA BINAWAN | D16: BAWANG MERAH | E16: KG | F16: 1 | G16: 56000 | H16: =F16*G16 -> 56000
D17: GULA PASIR | E17: KG | F17: 1 | G17: 22000 | H17: =F17*G17 -> 22000 | I17: =SUM(H16:H17) -> 78000 | K17: v
C18: BAKUNG 2 | D18: PARKIR | E18: PCS | F18: 1 | G18: 3000 | H18: =F18*G18 -> 3000
D19: TEFLON | E19: PCS | F19: 4 | G19: 164000 | H19: =F19*G19 -> 656000 | I19: =SUM(H18:H19) -> 659000 | K19: v
A20: 23 Mei | C20: ULVI KALIKOA | D20: BERAS | F20: 1 | G20: 16000 | H20: =F20*G20 -> 16000
A21: 26 mei | D21: GARAM | F21: 1 | G21: 20000 | H21: =F21*G21 -> 20000
A22: 26 mei | D22: PECAY | F22: =H22/G22 -> 3.3333333 | G22: 12000 | H22: 40000
A23: 26 mei | D23: WORTEL | F23: 5 | G23: 16000 | H23: =F23*G23 -> 80000
A24: 29 Mei | D24: BERAS PREMIUM | E24: KG | F24: 10 | G24: 15500 | H24: =F24*G24 -> 155000
A25: 29 Mei | D25: GARAM | E25: PCS | F25: 2 | G25: 3000 | H25: =F25*G25 -> 6000
A26: 29 MEI | D26: MC LEWIS TOMATO | E26: DRIGEN | F26: 2 | G26: 75500 | H26: =F26*G26 -> 151000 | I26: =SUM(H20:H26) -> 468000 | K26: V
D27: TAHU | E27: PCS | F27: 200 | G27: 700 | H27: =F27*G27 -> 140000 | I27: =H27 -> 140000 | K27: V
A28: 25 Mei | C28: HASBI BAKUNG 1 | D28: PLASTIK | E28: PCS | F28: 1 | G28: 500 | H28: =F28*G28 -> 500
D29: KECAP SEDAP | E29: PCS | F29: 4 | G29: 26900 | H29: =F29*G29 -> 107600
D30: BANGO 700 | E30: PCS | F30: 3 | G30: 26900 | H30: =F30*G30 -> 80700
D31: DISKON | G31: -16200 | H31: =G31 -> -16200 | I31: =SUM(H28:H31) -> 172600 | K31: V
A32: 5 Juni 2026 | H32: TOTAL | I32: =SUM(I33:I36) -> 682500 | J32: =SUM(J33:J36) -> 0
C33: TEGALSARI | D33: TELUR 03 JUNI | E33: KG | F33: 10 | G33: 25500 | H33: =F33*G33 -> 255000
D34: TELUR 03 JUNI | E34: KG | F34: 5 | G34: 25500 | H34: =F34*G34 -> 127500
D35: TELUR 04 JUNI | E35: KG | F35: 12 | G35: 25500 | H35: =F35*G35 -> 306000
D36: DISKON | H36: -6000 | I36: =SUM(H33:H36) -> 682500 | K36: v
A37: 7 Juni 2026 | H37: TOTAL | I37: =SUM(I38:I44) -> 302600 | J37: =SUM(J38:J44) -> 0
C38: ULVI KALIKOA | D38: TELUR 03 JUNI | E38: KG | F38: 3 | G38: =H38/F38 -> 27000 | H38: 81000
D39: NORI 04 JUNI | E39: PCS | F39: 3 | G39: 16700 | H39: =F39*G39 -> 50100
D40: NORI 04 JUNI | E40: PCS | F40: 2 | G40: 17500 | H40: =F40*G40 -> 35000
D41: PLASTIK | E41: PCS | F41: 1 | G41: 500 | H41: =F41*G41 -> 500
D42: DELMONTE TOMAT 04 JUNI | E42: KG | F42: 1 | G42: 17500 | H42: =F42*G42 -> 17500
D43: MC LEWIS MAYO 04 JUNI | E43: POUCH | F43: 3 | G43: 24000 | H43: =F43*G43 -> 72000
D44: ROTI WIJEN 05 JUNI | E44: PCS | F44: 3 | G44: 15500 | H44: =F44*G44 -> 46500 | I44: =SUM(H38:H44) -> 302600 | K44: v
A45: 09 Juni 2026 | H45: TOTAL | I45: =sum(I46:I47) -> 131500 | J45: =sum(J46:J47) -> 0
A46: 08 JUNI | C46: CINTAMI WERKUDARA | D46: WORTEL | E46: KG | F46: 3 | G46: 15000 | H46: =F46*G46 -> 45000
A47: 09 JUNI | D47: KECAP BANGO 700GR | E47: POUCH | F47: 4 | G47: =H47/F47 -> 21625 | H47: 86500 | I47: =SUM(H46:H47) -> 131500 | K47: v
A48: 10 Juni 2026 | H48: TOTAL | I48: =SUM(I49:I56) -> 1074050 | J48: =SUM(J49:J56) -> 0
A49: 08 JUNI | C49: FIA BINAWAN | D49: KUNCI BIRU TEPUNG | E49: KG | F49: 4 | G49: 15500 | H49: =F49*G49 -> 62000
D50: MINYAK | E50: LITER | F50: 2.5 | G50: 23200 | H50: =F50*G50 -> 58000
D51: TERIGU | E51: KG | F51: 3 | G51: 13000 | H51: =F51*G51 -> 39000
D52: AYAM | E52: KG | F52: 2 | G52: 24000 | H52: =F52*G52 -> 48000
D53: PARSLEY SAYUR | E53: KG | F53: 3 | G53: 12950 | H53: =F53*G53 -> 38850
D54: PLASTIK | E54: PCS | F54: 1 | G54: 200 | H54: =F54*G54 -> 200 | I54: =SUM(H49:H54) -> 246050 | K54: v
C55: KHUSNUL TEGALSARI | D55: TELUR | E55: KG | F55: 3 | G55: 26000 | H55: =F55*G55 -> 78000 | I55: =H55 -> 78000
C56: HASBI BAKUNG 1 | D56: DAGING SAPI | E56: KG | F56: 5 | G56: 150000 | H56: =F56*G56 -> 750000 | I56: =H56 -> 750000
A57: 11 Juni 2026 | H57: TOTAL | I57: =SUM(I58:I69) -> 1230000 | J57: =SUM(J58:J69) -> 0
C58: KHUSNUL TEGALSARI | D58: CABE MERAH | E58: KG | F58: 2 | G58: 60000 | H58: =F58*G58 -> 120000
D59: PP 10X20X02 | E59: PACK | F59: 7 | G59: =H59/F59 -> 11571.429 | H59: 81000
D60: PP 10X20X02 | E60: KG | F60: 2 | G60: =H60/F60 -> 45000 | H60: 90000 | I60: =SUM(H58:H60) -> 291000 | J60: v
A61: 09 JUNI | C61: CINTAMI WEERKUDARA | D61: KEJU PROCHIZ SPREADY 2KG | E61: KG | F61: 4 | G61: 116000 | H61: =F61*G61 -> 464000
A62: 09 JUNI | D62: SEMANGKA | E62: KG | F62: =H62/G62 -> 7.4666667 | G62: 15000 | H62: 112000
A63: 09 JUNI | D63: KEJU OLES 2KG | E63: PACK | F63: 1 | G63: 116000 | H63: =F63*G63 -> 116000
A64: 09 JUNI | D64: DELMONTE SAOS TOMAT | E64: PACK | F64: 13 | G64: 6000 | H64: =F64*G64 -> 78000
A65: 10 JUNI | D65: KECAP BANGO 950GR | E65: PCS | F65: 3 | G65: 34500 | H65: =F65*G65 -> 103500
A66: 10 JUNI | D66: KP | E66: PCS | F66: 1 | G66: 500 | H66: =F66*G66 -> 500
A67: 10 JUNI | D67: KECAP BANGO 950GR | E67: PCS | F67: 3 | G67: 26500 | H67: =F67*G67 -> 79500
A68: 10 JUNI | D68: DIS | H68: -15000
A69: 10 JUNI | D69: KP | F69: 1 | H69: 500 | I69: =SUM(H61:H69) -> 939000 | J69: v
A70: 12 Juni 2026 | H70: TOTAL | I70: =SUM(I71) -> 515000 | J70: =SUM(J73:J133) -> 0
C71: FIA BINAWAN | D71: MINYAK KITA | E71: DUS | F71: 2 | G71: =H71/F71 -> 257500 | H71: 515000 | I71: =H71 -> 515000 | K71: v
A72: 13 Juni 2026 | H72: TOTAL | I72: =sum(I73:I82) -> 648000 | J72: =SUM(J75:J135) -> 0
A73: 09 JUNI | C73: ULVI KALIKOA | D73: TELUR | E73: KG | F73: 5 | G73: =H73/F73 -> 29000 | H73: 145000
A74: 10 JUNI | D74: MINYAK KUNCI MAS | E74: LT | F74: 1 | G74: 43000 | H74: =G74*F74 -> 43000
A75: 10 JUNI | D75: TROPICAL MINYAK 1LT | E75: LT | F75: 2 | G75: 23900 | H75: =G75*F75 -> 47800
D76: KP | H76: 500
D77: DISKON | H77: -1300
A78: 11 JUNI | D78: SEMANGKA | E78: KG | F78: 7.2 | G78: 15000 | H78: =F78*G78 -> 108000
A79: 12 JUNI | D79: AYAM DADA FILLET | E79: KG | F79: 3 | G79: 29000 | H79: =F79*G79 -> 87000 | I79: =SUM(H73:H79) -> 430000 | K79: v
A80: 10 JUNI | C80: KHUSNUL TEGALSARI | D80: TELUR AYAM | E80: KG | F80: 5 | G80: 25000 | H80: =F80*G80 -> 125000
A81: 11 JUNI | D81: GARAM | E81: KG | F81: 5 | G81: 5000 | H81: =F81*G81 -> 25000
A82: 11 JUNI | D82: TEMPE | E82: PAPAN | F82: 17 | G82: 4000 | H82: =F82*G82 -> 68000 | I82: =SUM(H80:H82) -> 218000 | K82: v
A83: 15 Juni 2026 | H83: TOTAL | I83: =SUM((I84:I85)) -> 157000 | J83: =SUM((J84:J85)) -> 0
C84: KHUSNUL TEGALSARI | D84: KENTANG | E84: KG | F84: 1 | G84: 32000 | H84: =F84*G84 -> 32000
D85: TELUR | E85: KG | F85: 5 | G85: 25000 | H85: =F85*G85 -> 125000 | I85: =SUM(H84:H85) -> 157000
A86: 16 Juni 2026 | H86: TOTAL | I86: =sum(I87:I88) -> 279000
C87: ULVI KALIKOA | D87: WJ EDAMAME 1KG | E87: KG | F87: 5 | G87: 39000 | H87: =F87*G87 -> 195000
D88: MINYAK MASKU 2L | E88: POUCH | F88: 2 | G88: 42000 | H88: =F88*G88 -> 84000 | I88: =sum(H87:H88) -> 279000
A89: 17 Juni 2026 | H89: TOTAL | I89: =SUM(I90:I93) -> 71000 | J89: =SUM(J92:J152) -> 0
C90: KHUSNUL TEGALSARI | D90: GULA 1KG | E90: KG | F90: 2 | G90: 17500 | H90: =G90*F90 -> 35000
D91: KECAP 700G | E91: POUCH | F91: 1 | G91: 26500 | H91: =G91*F91 -> 26500
D92: KL | F92: 1 | G92: 500 | H92: =G92*F92 -> 500
D93: AYAM POTONG | E93: GR | F93: 300 | G93: 30 | H93: =G93*F93 -> 9000 | I93: =SUM(H90:H93) -> 71000
A94: 18 Juni 2026 | H94: TOTAL | I94: =sum(I95:I98) -> 156900 | J94: =sum(J95:J98) -> 0
A95: 17 JUNI | C95: CHINTAMI WERKUDARA | D95: JERUK | E95: KG | F95: =H95/G95 -> 1.2727273 | G95: 22000 | H95: 28000
D96: FORTUNE MINYAK 2L | E96: LT | F96: 1 | G96: 42800 | H96: =G96*F96 -> 42800
D97: FORTUNE MINYAK 2L | E97: LT | F97: 2 | G97: 42800 | H97: =G97*F97 -> 85600
D98: KL | F98: 1 | G98: 500 | H98: =F98*G98 -> 500 | I98: =SUM(H95:H98) -> 156900
A99: 19 Juni 2026 | H99: TOTAL | I99: =SUM(I100:I106) -> 1084000 | J99: =SUM(J100:J106) -> 0
C100: FIA BINAWAN | D100: CABE MERAH | E100: KG | F100: 3 | G100: 30000 | H100: =F100*G100 -> 90000
D101: TOMAT MERAH | E101: KG | F101: 3 | G101: 12000 | H101: =F101*G101 -> 36000
D102: TOMAT HIJAU | E102: KG | F102: 3 | G102: 10000 | H102: =F102*G102 -> 30000
...

Sheet Hutang Suplier
A1: TANGGAL | B1: NO | C1: NAMA TOKO | D1: NAMA BARANG | E1: SATUAN | F1: QTY | G1: HARGA | H1: Disc | I1: SUBTOTAL | J1: TOTAL | K1: Pengecekan Invoice | L1: REKENING
A2: 20-21 April | C2: Fandy Sumantri | D2: Bahan Baku Beras Dan Minyak | F2: 1 | G2: 31445000 | I2: =F2*G2 -> 31445000 | J2: =I2 -> 31445000 | K2: SUDAH APPROVE
A3: 46139 | C3: Widia | D3: Semangka | F3: 225 | G3: 18500 | I3: =F3*G3 -> 4162500
C4: Widia | D4: Santang | F4: 26 | G4: 315000 | I4: =F4*G4 -> 8190000
C5: Widia | D5: Ambon Super | F5: 1946 | G5: 1800 | I5: =F5*G5 -> 3502800 | J5: =SUM(I3:I5) -> 15855300 | K5: SUDAH APPROVE
A6: 46140 | C6: Jaena | D6: Ayam Potong | F6: 200 | G6: 34000 | I6: =F6*G6 -> 6800000
C7: Jaena | D7: Ayam Fillet | F7: 90 | G7: 45000 | I7: =F7*G7 -> 4050000
C8: Jaena | D8: Ayam Fillet | F8: 10 | G8: 45000 | I8: =F8*G8 -> 450000
A9: 46141 | C9: Jaena | D9: Filet tanpa kulit | F9: 120 | G9: 47000 | I9: =F9*G9 -> 5640000
C10: Jaena | D10: Ayam Potong | F10: 135 | G10: 35000 | I10: =F10*G10 -> 4725000
A11: 01 Mei | C11: Jaena | D11: Ayam Utuh | F11: 165 | G11: 35000 | I11: =F11*G11 -> 5775000 | J11: =SUM(I6:I11) -> 27440000 | K11: SUDAH APPROVE
A12: 46138 | C12: Jaena | D12: tempe tegalsari | F12: 85 | G12: 12000 | I12: =F12*G12 -> 1020000
A13: 46139 | C13: Jaena | D13: tahu tegalsari | F13: 1540 | G13: 750 | I13: =F13*G13 -> 1155000
A14: 46140 | C14: Jaena | D14: tempe tegalsari | F14: 85 | G14: 12000 | I14: =F14*G14 -> 1020000
A15: 46141 | C15: Jaena | D15: Tahu Tegalsari | F15: 1790 | G15: 500 | I15: =F15*G15 -> 895000 | J15: =SUM(I12:I15) -> 4090000 | K15: SUDAH APPROVE
A16: 26-29 April | C16: Ishma | D16: tahu bakung, binawan, werkudara | F16: 1 | G16: 13542000 | I16: =F16*G16 -> 13542000 | J16: =I16 -> 13542000 | K16: SUDAH APPROVE
A17: 46140 | C17: Ishma | D17: Tempe bakung 1 | F17: 120 | G17: 12000 | I17: =F17*G17 -> 1440000
A18: 46141 | C18: Ishma | D18: Tempe bakung 2 | F18: 65 | G18: 12000 | I18: =F18*G18 -> 780000 | J18: =SUM(I17:I18) -> 2220000 | K18: SUDAH APPROVE
A20: 1 Mei 2026 | C20: Dwinanto Basarah | D20: Tempe Kalikoa | F20: 53 | G20: 12000 | I20: =G20*F20 -> 636000
A21: 04 Mei | C21: Dwinanto Basarah | D21: Tempe Werkudara | F21: 81 | G21: 12000 | I21: =G21*F21 -> 972000
C22: Dwinanto Basarah | D22: Tempe Kalikoa | F22: 85 | G22: 12000 | I22: =G22*F22 -> 1020000 | J22: =SUM(I20:I22) -> 2628000 | K22: SUDAH APPROVE
A24: 46141 | C24: Rizki Fadillah | D24: Gas Werkudara | F24: 1 | G24: 1125000 | I24: =G24*F24 -> 1125000 | J24: =I24 -> 1125000 | K24: SUDAH APPROVE
A26: 46141 | C26: Yudi | D26: Ayam Fillet Tegalsari | F26: 109 | G26: 52500 | I26: =G26*F26 -> 5722500 | J26: =I26 -> 5722500 | K26: SUDAH APPROVE | L26: 782002200300 RADEN YUDI PRAMANTO CIMB Niaga
A27: 03 Mei | C27: Yudi | D27: Ayam Potong Tegalsari | F27: 179 | G27: 36500 | I27: =G27*F27 -> 6533500 | J27: =SUM(I26:I27) -> 12256000 | K27: SUDAH APPROVE
A28: 46138 | C28: Riski Fadilah | D28: Pisang Kalikoa | F28: 1700 | G28: 1550 | I28: =F28*G28 -> 2635000 | L28: RIZKY FADILLAH
A29: 46139 | C29: Riski Fadilah | D29: Jeruk Medan Tegalsari | F29: 156 | G29: 29500 | I29: =F29*G29 -> 4602000 | L29: 7257935757
A30: 46140 | C30: Riski Fadilah | D30: Jeruk Medan Werkudara | F30: 138.3 | G30: 29500 | I30: =F30*G30 -> 4079850
A31: 46138 | C31: Riski Fadilah | D31: Semangka Tegalsari | F31: 127 | G31: 13500 | I31: =F31*G31 -> 1714500
A32: 46139 | C32: Riski Fadilah | D32: Buah Naga Werkudara | F32: 220.5 | G32: 21000 | I32: =F32*G32 -> 4630500
A33: 46140 | C33: Riski Fadilah | D33: Pisang Kalikoa | F33: 1680 | G33: 1550 | I33: =F33*G33 -> 2604000
A34: 46140 | C34: Riski Fadilah | D34: Sunkis Tegalsari | F34: 98 | G34: 34000 | I34: =F34*G34 -> 3332000 | J34: =SUM(I28:I34) -> 23597850 | K34: SUDAH APPROVE
A35: 46139 | C35: Riski Fadilah | D35: Jeruk Medan Kalikoa | F35: 140 | G35: 29500 | I35: =F35*G35 -> 4130000
A36: 46139 | C36: Riski Fadilah | D36: Pisang Binawan | F36: 400 | G36: 1550 | I36: =F36*G36 -> 620000
A37: 46141 | C37: Riski Fadilah | D37: Anggur Tegalsari | F37: 45 | G37: 84000 | I37: =F37*G37 -> 3780000
C38: Riski Fadilah | D38: Jeruk Kino | F38: 140 | G38: 33500 | I38: =F38*G38 -> 4690000
C39: Riski Fadilah | D39: Pisang | F39: 1390 | G39: 1550 | I39: =F39*G39 -> 2154500
A40: 1 Mei | C40: Riski Fadilah | D40: Anggur Kalikoa | F40: 18 | G40: 84000 | I40: =F40*G40 -> 1512000
A41: 46141 | C41: Riski Fadilah | D41: Jambu Kalikoa | F41: 175 | G41: 12000 | I41: =F41*G41 -> 2100000
A42: 1 Mei | C42: Riski Fadilah | D42: Jeruk Medan Binawan | F42: 107 | G42: 29500 | I42: =F42*G42 -> 3156500 | J42: =SUM(I35:I42) -> 22143000 | K42: SUDAH APPROVE
A43: 04 Mei | C43: Syahrudin | D43: Tempe Bakung 2 | F43: 90 | G43: 12000 | I43: =G43*F43 -> 1080000 | J43: =I43 -> 1080000 | K43: SUDAH APPROVE
A45: 03 Mei | C45: Jaena | D45: Daging ayam fillet werkudara | F45: 115 | G45: 45000 | I45: =G45*F45 -> 5175000
C46: Jaena | D46: fillet kalikoa | F46: 60 | G46: 45000 | I46: =G46*F46 -> 2700000
C47: Jaena | D47: ayam poton bakung 2 | F47: 240 | G47: 35000 | I47: =G47*F47 -> 8400000 | J47: =SUM(I45:I47) -> 16275000 | K47: SUDAH APPROVE
A49: 46141 | C49: Siti Khumaedah | D49: Beras Bakung | F49: 25 | G49: 375000 | I49: =G49*F49 -> 9375000 | J49: =I49 -> 9375000 | K49: SUDAH APPROVE | L49: 7745291091 Siti khumaedah
A51: 01 Mei | C51: Widia | D51: Semangka | F51: 59 | G51: 18500 | I51: =G51*F51 -> 1091500
A52: 03 Mei | C52: Widia | D52: Melon Madu | F52: 236 | G52: 19500 | I52: =G52*F52 -> 4602000
C53: Widia | D53: Semingka no biji | F53: 367 | G53: 18500 | I53: =G53*F53 -> 6789500
C54: Widia | D54: ambon super | F54: 4920 | G54: 1800 | I54: =G54*F54 -> 8856000
A55: 04 Mei | C55: Widia | D55: Melon Madu | F55: 268.85 | G55: 19500 | I55: =G55*F55 -> 5242575
C56: Widia | D56: Jeruk Wogam | F56: 38 | G56: 230000 | I56: =G56*F56 -> 8740000
C57: Widia | D57: Ambon Super | F57: 2100 | G57: 1800 | I57: =G57*F57 -> 3780000
C58: Widia | D58: Jeruk Malang | F58: 267.5 | G58: 25500 | I58: =G58*F58 -> 6821250
A59: 05 Mei | C59: Widia | D59: Jeruk Malang | F59: 300 | G59: 25500 | I59: =G59*F59 -> 7650000
C60: Widia | D60: Semingka no biji | F60: 231 | G60: 18000 | I60: =G60*F60 -> 4158000
C61: Widia | D61: Semingka no biji | F61: 235 | G61: 18000 | I61: =G61*F61 -> 4230000
C62: Widia | D62: Semingka no biji | F62: 250 | G62: 18000 | I62: =G62*F62 -> 4500000 | J62: =SUM(I51:I62) -> 66460825 | K62: SUDAH APPROVE
A64: 46131 | B64: . | C64: Riski Fadillah | D64: Gas Kalikoa 50Kg | E64: Tabung | F64: 2 | G64: 1125000 | I64: =F64*G64 -> 2250000
A65: 46132 | B65: . | C65: Riski Fadillah | D65: Gas Bakung 2 50kg | E65: Tabung | F65: 1 | G65: 1125000 | I65: =F65*G65 -> 1125000
A66: 46132 | B66: . | C66: Riski Fadillah | D66: Gas Tegalsari 50Kg | E66: Tabung | F66: 1 | G66: 1125000 | I66: =F66*G66 -> 1125000
A67: 46133 | B67: . | C67: Riski Fadillah | D67: Gas Bakung 1 50Kg | E67: Tabung | F67: 2 | G67: 1125000 | I67: =F67*G67 -> 2250000
A68: 46133 | B68: . | C68: Riski Fadillah | D68: Gas Bakung 2 50Kg | E68: Tabung | F68: 1 | G68: 1125000 | I68: =F68*G68 -> 1125000
B69: . | C69: Riski Fadillah | D69: Gas Bakung 2 12Kg | E69: Tabung | F69: 1 | G69: 255000 | I69: =F69*G69 -> 255000
A70: 46133 | B70: . | C70: Riski Fadillah | D70: Gas Binawan 50Kg | E70: Tabung | F70: 2 | G70: 1125000 | I70: =F70*G70 -> 2250000
B71: . | C71: Riski Fadillah | D71: Gas Tegalsari 12Kg | E71: Tabung | F71: 2 | G71: 255000 | I71: =F71*G71 -> 510000
A72: 46134 | C72: Riski Fadillah | D72: Gas Bakung 2 50Kg | E72: Tabung | F72: 2 | G72: 1125000 | I72: =F72*G72 -> 2250000
A73: 46134 | B73: . | C73: Riski Fadillah | D73: Gas Tegalsari 50Kg | E73: Tabung | F73: 2 | G73: 1125000 | I73: =F73*G73 -> 2250000
A74: 46135 | B74: . | C74: Riski Fadillah | D74: Gas Bakung 1 50Kg | E74: Tabung | F74: 2 | G74: 1125000 | I74: =F74*G74 -> 2250000
A75: 46135 | B75: . | C75: Riski Fadillah | D75: Gas Bakung 2 50Kg | E75: Tabung | F75: 2 | G75: 1125000 | I75: =F75*G75 -> 2250000
A76: 46135 | B76: . | C76: Riski Fadillah | D76: Gas Binawan 50Kg | E76: Tabung | F76: 2 | G76: 1125000 | I76: =F76*G76 -> 2250000
A77: 46137 | B77: . | C77: Riski Fadillah | D77: Gas Bakung 1 50Kg | E77: Tabung | F77: 2 | G77: 1125000 | I77: =F77*G77 -> 2250000
B78: . | C78: Riski Fadillah | D78: Gas Bakung 2 50kg | E78: Tabung | F78: 2 | G78: 1125000 | I78: =F78*G78 -> 2250000
B79: . | C79: Riski Fadillah | D79: Gas Binawan 50Kg | E79: Tabung | F79: 1 | G79: 1125000 | I79: =F79*G79 -> 1125000
B80: . | C80: Riski Fadillah | D80: Gas Tegalsari 50Kg | E80: Tabung | F80: 1 | G80: 1125000 | I80: =F80*G80 -> 1125000
B81: . | C81: Riski Fadillah | D81: Gas Tegalsari 12Kg | E81: Tabung | F81: 1 | G81: 255000 | I81: =F81*G81 -> 255000 | J81: =sum(I64:I81) -> 29145000 | K81: SUDAH APPROVE
A83: 46135 | B83: . | C83: Riski Fadillah | D83: Gas Werkudara 50Kg | E83: Tabung | F83: 3 | G83: 1125000 | I83: =F83*G83 -> 3375000
B84: . | C84: Riski Fadillah | D84: Gas Werkudara 12Kg | E84: Tabung | F84: 1 | G84: 255000 | I84: =F84*G84 -> 255000 | J84: =sum(I83:I84) -> 3630000 | K84: SUDAH APPROVE | L84: revisi invoice dapur 12kg binawan
A86: 3 Mei | C86: Wahid Hidayat | D86: Tahu Putih Bakung 1 | E86: Pcs | F86: 2800 | G86: 500 | I86: =F86*G86 -> 1400000 | L86: SEABANK WAHID HIDAYAT 901730792357
A87: 5 Mei | C87: Wahid Hidayat | D87: Tahu Putih Bakung 2 | E87: Pcs | F87: 2275 | G87: 500 | I87: =F87*G87 -> 1137500 | J87: =sum(I86:I87) -> 2537500 | K87: SUDAH APPROVE
A89: 5 Mei | C89: Pandi | D89: Daging Ayam Fillet Werkudara | E89: Kg | F89: 102 | G89: 46500 | I89: =F89*G89 -> 4743000 | L89: BRI PANDI 413301001051502
C90: Pandi | D90: Daging Ayam Potong Binawan | E90: Kg | F90: 220 | G90: 36500 | I90: =F90*G90 -> 8030000 | J90: =sum(I89:I90) -> 12773000 | K90: SUDAH APPROVE
A93: 05 Mei | C93: Dwinanto Basarah | D93: Tempe Binawan | E93: Papan | F93: 105 | G93: 12000 | I93: =G93*F93 -> 1260000
C94: Dwinanto Basarah | D94: Tempe Werkudara | F94: 90 | G94: 12000 | I94: =G94*F94 -> 1080000
C95: Dwinanto Basarah | D95: Tempe Kalikoa | F95: 85 | G95: 12000 | I95: =G95*F95 -> 1020000
A96: 08 Mei | C96: Dwinanto Basarah | D96: Tempe Werkudara | F96: 14 | G96: 12000 | I96: =G96*F96 -> 168000 | J96: =SUM(I93:I96) -> 3528000 | K96: SUDAH APPROVE
A98: 4 Mei | D98: Daging Ayam Potog | F98: 197.45 | G98: 35200 | I98: =F98*G98 -> 6950240
D99: Daging Ayam Fillet | F99: 120 | G99: 45200 | I99: =F99*G99 -> 5424000
D100: Daging Ayam Potong | F100: 275 | G100: 35200 | I100: =F100*G100 -> 9680000 | J100: =sum(I98:I100) -> 22054240 | K100: SUDAH APPROVE
A102: 6 MEI | D102: Daging ayam fillet Bakung 2 | F102: 100 | G102: 48500 | I102: =F102*G102 -> 4850000
D103: Daging Ayam Filet Bakung 1 | F103: 120 | G103: 48500 | I103: =F103*G103 -> 5820000 | J103: =sum(I102:I103) -> 10670000 | K103: SUDAH APPROVE
A105: 7 Mei | D105: Tahu Putih Bakung 1 | F105: 2700 | G105: 500 | I105: =F105*G105 -> 1350000
A106: 6 Mei | D106: Tahu Putih Bakung 1 | F106: 2800 | G106: 500 | I106: =F106*G106 -> 1400000 | J106: =sum(I105:I106) -> 2750000 | K106: SUDAH APPROVE
A108: 6 Mei | D108: Melon Madu | E108: Kg | F108: 220 | G108: 19500 | I108: =F108*G108 -> 4290000
D109: Wogam 70 | E109: Box | F109: 39 | G109: 260000 | I109: =F109*G109 -> 10140000
D110: Apel Fuji | E110: Kg | F110: 13 | G110: 590000 | I110: =F110*G110 -> 7670000
D111: Semangka non biji | E111: Kg | F111: 150 | G111: 18500 | I111: =F111*G111 -> 2775000 | J111: =sum(I108:I111) -> 24875000 | K111: SUDAH APPROVE
A113: 7 Mei | D113: Salak Super Werkudara | E113: Kg | F113: 146.7 | G113: 13500 | I113: =F113*G113 -> 1980450
D114: Semangka non biji Binawan | E114: Kg | F114: 260 | G114: 18500 | I114: =F114*G114 -> 4810000
D115: Semangka non biji Bakung 1 | E115: Kg | F115: 250 | G115: 18500 | I115: =F115*G115 -> 4625000
D116: Melon Madu Bakung 2 | E116: Kg | F116: 250 | G116: 19500 | I116: =F116*G116 -> 4875000 | J116: =sum(I113:I116) -> 16290450 | K116: SUDAH APPROVE
A118: 8 Mei | D118: Apel fuji | E118: Dus | F118: 2 | G118: 575000 | I118: =F118*G118 -> 1150000 | J118: =I118 -> 1150000 | K118: SUDAH APPROVE
...

Sheet Kas Besar
A1: LAPORAN BELANJA BAHAN BAKU
A2: KOPERASI GOTONG ROYONG SEJAHTERA NUSANTARA
A3: MEI 2026
A5: TANGGAL | B5: PENERIMA | C5: TOTAL | D5: ITEM | E5: QTY | F5: SATUAN | G5: HARGA SATUAN | H5: TOTAL | I5: KETERANGAN
A6: 01 JUNI 2026 | H6: =SUM(H7) -> 2000000
B7: LISMA | D7: PETTY CASH | E7: 1 | G7: 2000000 | H7: =E7*G7 -> 2000000
A8: 02 JUNI 2026 | H8: =SUM(H9) -> 500000
B9: LISMA | D9: TOKEN LISTRIK | E9: 1 | G9: 500000 | H9: =G9 -> 500000
A10: 05 JUNI 2026 | H10: =SUM(H11:H16) -> 36700000
B11: BAMBANG SETIAWAN | D11: PENGAJUAN BIAYA SEWA MOBIL SPPG 24 MEI-6 JUNI 2026 | E11: 3 | F11: UNIT | G11: 2700000 | H11: =G11*E11 -> 8100000
E12: 8 | F12: UNIT | G12: 2400000 | H12: =G12*E12 -> 19200000
E13: 1 | F13: UNIT | G13: 2000000 | H13: =G13*E13 -> 2000000
D14: PENGAJUAN BIATA KOORDINASI WILAYAH | E14: 1 | G14: 3000000 | H14: =G14*E14 -> 3000000
D15: PENGAJUAN BIAYA SEWA MOBIL OPRASIONAL KOPRASI 24 MEI- 6 JUNI 2026 | E15: 1 | F15: UNIT | G15: 2400000 | H15: =G15*E15 -> 2400000
E16: 1 | F16: UNIT | G16: 2000000 | H16: =G16*E16 -> 2000000
A17: 16 JUNI 2026 | H17: =SUM(H18:H23) -> 67500000
B18: LISMA | D18: PETTYCASH | E18: 1 | G18: 1000000 | H18: =G18 -> 1000000
D19: TOKEN LISTRIK | E19: 1 | G19: 500000 | H19: =G19 -> 500000
A20: 19 JUNI 2026 | H20: =SUM(H21:H26) -> 36700000
B21: BAMBANG SETIAWAN | D21: PENGAJUAN BIAYA SEWA MOBIL SPPG 7-20 JUNI 2026 | E21: 3 | F21: UNIT | G21: 2700000 | H21: =G21*E21 -> 8100000
E22: 8 | F22: UNIT | G22: 2400000 | H22: =G22*E22 -> 19200000
E23: 1 | F23: UNIT | G23: 2000000 | H23: =G23*E23 -> 2000000
D24: PENGAJUAN BIATA KOORDINASI WILAYAH 7-20 JUNI 2026 | E24: 1 | G24: 3000000 | H24: =G24*E24 -> 3000000
D25: PENGAJUAN BIAYA SEWA MOBIL OPRASIONAL KOPRASI 7- 20 JUNI 2026 | E25: 1 | F25: UNIT | G25: 2400000 | H25: =G25*E25 -> 2400000
E26: 1 | F26: UNIT | G26: 2000000 | H26: =G26*E26 -> 2000000
E27: 3 | G27: 2500 | H27: =E27*G27 -> 7500 | I27: =H27 -> 7500
A28: JUNI 2026 | H28: =SUM(H29:H34) -> 0

Sheet Daftar Harga
A1: 💰 DAFTAR HARGA REFERENSI (Sumber: Rekap Mei 2026) — BISA DIEDIT
A2: ⚠️ Harga BIRU = input manual. Ubah di sini → otomatis update semua invoice.
A3: No | B3: Nama Barang | C3: Satuan | D3: Harga Beli (Rp) | E3: Harga Jual (Rp) | F3: Margin (Rp) | G3: Margin (%)
A4: 1 | B4: Anggur | C4: Kg | D4: 90000 | E4: 92000 | F4: =IF(AND(D4<>"",E4<>""),E4-D4,"") -> 2000 | G4: =IF(AND(D4<>"",E4<>"",D4<>0),(E4-D4)/D4,"") -> 0.022222222
A5: 2 | B5: Apel | C5: Pcs | D5: 26000 | E5: 30000 | F5: =IF(AND(D5<>"",E5<>""),E5-D5,"") -> 4000 | G5: =IF(AND(D5<>"",E5<>"",D5<>0),(E5-D5)/D5,"") -> 0.15384615
A6: 3 | B6: Asam Jawa | C6: Kg | F6: =IF(AND(D6<>"",E6<>""),E6-D6,"") | G6: =IF(AND(D6<>"",E6<>"",D6<>0),(E6-D6)/D6,"")
A7: 4 | B7: Ayam Dada Fillet | C7: Kg | D7: 46500 | E7: 52000 | F7: =IF(AND(D7<>"",E7<>""),E7-D7,"") -> 5500 | G7: =IF(AND(D7<>"",E7<>"",D7<>0),(E7-D7)/D7,"") -> 0.11827957
A8: 5 | B8: Ayam Fillet | C8: Kg | D8: 48000 | E8: 54000 | F8: =IF(AND(D8<>"",E8<>""),E8-D8,"") -> 6000 | G8: =IF(AND(D8<>"",E8<>"",D8<>0),(E8-D8)/D8,"") -> 0.125
A9: 6 | B9: Ayam Potong | C9: Kg | D9: 36500 | E9: 38000 | F9: =IF(AND(D9<>"",E9<>""),E9-D9,"") -> 1500 | G9: =IF(AND(D9<>"",E9<>"",D9<>0),(E9-D9)/D9,"") -> 0.04109589
A10: 7 | B10: Ayam Potong Sayap | C10: Kg | D10: 36500 | E10: 38000 | F10: =IF(AND(D10<>"",E10<>""),E10-D10,"") -> 1500 | G10: =IF(AND(D10<>"",E10<>"",D10<>0),(E10-D10)/D10,"") -> 0.04109589
A11: 8 | B11: Bandeng presto | C11: Pcs | F11: =IF(AND(D11<>"",E11<>""),E11-D11,"") | G11: =IF(AND(D11<>"",E11<>"",D11<>0),(E11-D11)/D11,"")
A12: 9 | B12: Bawang Bombay | C12: Kg | D12: 30000 | E12: 40000 | F12: =IF(AND(D12<>"",E12<>""),E12-D12,"") -> 10000 | G12: =IF(AND(D12<>"",E12<>"",D12<>0),(E12-D12)/D12,"") -> 0.33333333
A13: 10 | B13: Bawang merah | C13: Kg | D13: 28000 | E13: 30000 | F13: =IF(AND(D13<>"",E13<>""),E13-D13,"") -> 2000 | G13: =IF(AND(D13<>"",E13<>"",D13<>0),(E13-D13)/D13,"") -> 0.071428571
A14: 11 | B14: Bawang merah kupas | C14: Kg | D14: 40000 | E14: 45000 | F14: =IF(AND(D14<>"",E14<>""),E14-D14,"") -> 5000 | G14: =IF(AND(D14<>"",E14<>"",D14<>0),(E14-D14)/D14,"") -> 0.125
A15: 12 | B15: Bawang putih | C15: Kg | D15: 33000 | E15: 36000 | F15: =IF(AND(D15<>"",E15<>""),E15-D15,"") -> 3000 | G15: =IF(AND(D15<>"",E15<>"",D15<>0),(E15-D15)/D15,"") -> 0.090909091
A16: 13 | B16: Bawang putih kupas | C16: Kg | D16: 33000 | E16: 45000 | F16: =IF(AND(D16<>"",E16<>""),E16-D16,"") -> 12000 | G16: =IF(AND(D16<>"",E16<>"",D16<>0),(E16-D16)/D16,"") -> 0.36363636
A17: 14 | B17: Beras | C17: Kg | D17: 15500 | E17: 15500 | F17: =IF(AND(D17<>"",E17<>""),E17-D17,"") -> 0 | G17: =IF(AND(D17<>"",E17<>"",D17<>0),(E17-D17)/D17,"") -> 0
A18: 15 | B18: Blimbing | C18: Kg | F18: =IF(AND(D18<>"",E18<>""),E18-D18,"") | G18: =IF(AND(D18<>"",E18<>"",D18<>0),(E18-D18)/D18,"")
A19: 16 | B19: Buah pir | C19: Pcs | D19: 22500 | E19: 23500 | F19: =IF(AND(D19<>"",E19<>""),E19-D19,"") -> 1000 | G19: =IF(AND(D19<>"",E19<>"",D19<>0),(E19-D19)/D19,"") -> 0.044444444
A20: 17 | B20: Buah Plum | C20: Dus | D20: 22500 | E20: 23500 | F20: =IF(AND(D20<>"",E20<>""),E20-D20,"") -> 1000 | G20: =IF(AND(D20<>"",E20<>"",D20<>0),(E20-D20)/D20,"") -> 0.044444444
A21: 18 | B21: Bubuk Gochugaru | C21: Kg | D21: 170000 | E21: 180000 | F21: =IF(AND(D21<>"",E21<>""),E21-D21,"") -> 10000 | G21: =IF(AND(D21<>"",E21<>"",D21<>0),(E21-D21)/D21,"") -> 0.058823529
A22: 19 | B22: Bubuk Ngohiong | C22: Kg | D22: 170000 | E22: 180000 | F22: =IF(AND(D22<>"",E22<>""),E22-D22,"") -> 10000 | G22: =IF(AND(D22<>"",E22<>"",D22<>0),(E22-D22)/D22,"") -> 0.058823529
A23: 20 | B23: Bubuk Paprika | C23: Kg | D23: 170000 | E23: 180000 | F23: =IF(AND(D23<>"",E23<>""),E23-D23,"") -> 10000 | G23: =IF(AND(D23<>"",E23<>"",D23<>0),(E23-D23)/D23,"") -> 0.058823529
A24: 21 | B24: Buncis | C24: Kg | D24: 13000 | E24: 16000 | F24: =IF(AND(D24<>"",E24<>""),E24-D24,"") -> 3000 | G24: =IF(AND(D24<>"",E24<>"",D24<>0),(E24-D24)/D24,"") -> 0.23076923
A25: 22 | B25: Cabai merah | C25: Kg | D25: 47000 | E25: 52000 | F25: =IF(AND(D25<>"",E25<>""),E25-D25,"") -> 5000 | G25: =IF(AND(D25<>"",E25<>"",D25<>0),(E25-D25)/D25,"") -> 0.10638298
A26: 23 | B26: Cabai merah besar | C26: Kg | D26: 47000 | E26: 52000 | F26: =IF(AND(D26<>"",E26<>""),E26-D26,"") -> 5000 | G26: =IF(AND(D26<>"",E26<>"",D26<>0),(E26-D26)/D26,"") -> 0.10638298
A27: 24 | B27: Cabai rawit merah | C27: Kg | D27: 80000 | E27: 90000 | F27: =IF(AND(D27<>"",E27<>""),E27-D27,"") -> 10000 | G27: =IF(AND(D27<>"",E27<>"",D27<>0),(E27-D27)/D27,"") -> 0.125
A28: 25 | B28: Daging Ayam Giling | C28: Kg | D28: 52000 | E28: 65000 | F28: =IF(AND(D28<>"",E28<>""),E28-D28,"") -> 13000 | G28: =IF(AND(D28<>"",E28<>"",D28<>0),(E28-D28)/D28,"") -> 0.25
A29: 26 | B29: Daun bawang | C29: Kg | D29: 10000 | E29: 12000 | F29: =IF(AND(D29<>"",E29<>""),E29-D29,"") -> 2000 | G29: =IF(AND(D29<>"",E29<>"",D29<>0),(E29-D29)/D29,"") -> 0.2
A30: 27 | B30: Daun jeruk | C30: Kg | D30: 27000 | E30: 35000 | F30: =IF(AND(D30<>"",E30<>""),E30-D30,"") -> 8000 | G30: =IF(AND(D30<>"",E30<>"",D30<>0),(E30-D30)/D30,"") -> 0.2962963
... A32: 29 | B32: Daun Salam | C32: Kg | D32: 21600 | E32: 15000 | F32: =IF(AND(D32<>"",E32<>""),E32-D32,"") -> -6600 | G32: =IF(AND(D32<>"",E32<>"",D32<>0),(E32-D32)/D32,"") -> -0.30555556
A33: 30 | B33: Edamame | C33: Kg | F33: =IF(AND(D33<>"",E33<>""),E33-D33,"") | G33: =IF(AND(D33<>"",E33<>"",D33<>0),(E33-D33)/D33,"")
A34: 31 | B34: Garam | C34: Kg | D34: 9000 | E34: 10500 | F34: =IF(AND(D34<>"",E34<>""),E34-D34,"") -> 1500 | G34: =IF(AND(D34<>"",E34<>"",D34<>0),(E34-D34)/D34,"") -> 0.16666667
A35: 32 | B35: Gula merah | C35: Kg | D35: 17000 | E35: 22000 | F35: =IF(AND(D35<>"",E35<>""),E35-D35,"") -> 5000 | G35: =IF(AND(D35<>"",E35<>"",D35<>0),(E35-D35)/D35,"") -> 0.29411765
A36: 33 | B36: Gula pasir | C36: Kg | D36: 19000 | E36: 20000 | F36: =IF(AND(D36<>"",E36<>""),E36-D36,"") -> 1000 | G36: =IF(AND(D36<>"",E36<>"",D36<>0),(E36-D36)/D36,"") -> 0.052631579
A37: 34 | B37: Ikan Tongkol | C37: Kg | D37: 6500 | E37: 14000 | F37: =IF(AND(D37<>"",E37<>""),E37-D37,"") -> 7500 | G37: =IF(AND(D37<>"",E37<>"",D37<>0),(E37-D37)/D37,"") -> 1.1538462
A38: 35 | B38: Jagung pipil | C38: Kg | D38: 24000 | E38: 24000 | F38: =IF(AND(D38<>"",E38<>""),E38-D38,"") -> 0 | G38: =IF(AND(D38<>"",E38<>"",D38<>0),(E38-D38)/D38,"") -> 0
A39: 36 | B39: Jahe | C39: Kg | D39: 20000 | E39: 260000 | F39: =IF(AND(D39<>"",E39<>""),E39-D39,"") -> 240000 | G39: =IF(AND(D39<>"",E39<>"",D39<>0),(E39-D39)/D39,"") -> 12
A40: 37 | B40: Jeruk | C40: Pcs | D40: 29000 | E40: 32000 | F40: =IF(AND(D40<>"",E40<>""),E40-D40,"") -> 3000 | G40: =IF(AND(D40<>"",E40<>"",D40<>0),(E40-D40)/D40,"") -> 0.10344828
A41: 38 | B41: Jeruk Limau | C41: Kg | D41: 29000 | E41: 32000 | F41: =IF(AND(D41<>"",E41<>""),E41-D41,"") -> 3000 | G41: =IF(AND(D41<>"",E41<>"",D41<>0),(E41-D41)/D41,"") -> 0.10344828
A42: 39 | B42: Jeruk Malang | C42: Kg | D42: 27500 | E42: 29000 | F42: =IF(AND(D42<>"",E42<>""),E42-D42,"") -> 1500 | G42: =IF(AND(D42<>"",E42<>"",D42<>0),(E42-D42)/D42,"") -> 0.054545455
A43: 40 | B43: Jeruk Medan | C43: Kg | D43: 28000 | E43: 30500 | F43: =IF(AND(D43<>"",E43<>""),E43-D43,"") -> 2500 | G43: =IF(AND(D43<>"",E43<>"",D43<>0),(E43-D43)/D43,"") -> 0.089285714
A44: 41 | B44: Jinten | C44: Kg | E44: 100000 | F44: =IF(AND(D44<>"",E44<>""),E44-D44,"") | G44: =IF(AND(D44<>"",E44<>"",D44<>0),(E44-D44)/D44,"")
A45: 42 | B45: Kacang panjang | C45: Kg | D45: 10000 | E45: 14000 | F45: =IF(AND(D45<>"",E45<>""),E45-D45,"") -> 4000 | G45: =IF(AND(D45<>"",E45<>"",D45<>0),(E45-D45)/D45,"") -> 0.4
A46: 43 | B46: Kacang Sambal | C46: Kg | D46: 10000 | E46: 14000 | F46: =IF(AND(D46<>"",E46<>""),E46-D46,"") -> 4000 | G46: =IF(AND(D46<>"",E46<>"",D46<>0),(E46-D46)/D46,"") -> 0.4
A47: 44 | B47: Kacang tanah giling | C47: Kg | D47: 35000 | E47: 40000 | F47: =IF(AND(D47<>"",E47<>""),E47-D47,"") -> 5000 | G47: =IF(AND(D47<>"",E47<>"",D47<>0),(E47-D47)/D47,"") -> 0.14285714
A48: 45 | B48: Kaldu jamur | C48: Kg | D48: 120000 | E48: 180000 | F48: =IF(AND(D48<>"",E48<>""),E48-D48,"") -> 60000 | G48: =IF(AND(D48<>"",E48<>"",D48<>0),(E48-D48)/D48,"") -> 0.5
A49: 46 | B49: Kecap Inggris | C49: Botol | D49: 47000 | E49: 55000 | F49: =IF(AND(D49<>"",E49<>""),E49-D49,"") -> 8000 | G49: =IF(AND(D49<>"",E49<>"",D49<>0),(E49-D49)/D49,"") -> 0.17021277
A50: 47 | B50: Kecap manis | C50: Dirigen | D50: 190000 | E50: 215000 | F50: =IF(AND(D50<>"",E50<>""),E50-D50,"") -> 25000 | G50: =IF(AND(D50<>"",E50<>"",D50<>0),(E50-D50)/D50,"") -> 0.13157895
A51: 48 | B51: Keju Slice | C51: Pcs | F51: =IF(AND(D51<>"",E51<>""),E51-D51,"") | G51: =IF(AND(D51<>"",E51<>"",D51<>0),(E51-D51)/D51,"")
A52: 49 | B52: Kelapa parut | C52: Kg | D52: 22000 | E52: 30000 | F52: =IF(AND(D52<>"",E52<>""),E52-D52,"") -> 8000 | G52: =IF(AND(D52<>"",E52<>"",D52<>0),(E52-D52)/D52,"") -> 0.36363636
A53: 50 | B53: Kelengkeng | C53: Kg | E53: 63000 | F53: =IF(AND(D53<>"",E53<>""),E53-D53,"") | G53: =IF(AND(D53<>"",E53<>"",D53<>0),(E53-D53)/D53,"")
A54: 51 | B54: Kemiri | C54: Kg | D54: 45000 | E54: 55000 | F54: =IF(AND(D54<>"",E54<>""),E54-D54,"") -> 10000 | G54: =IF(AND(D54<>"",E54<>"",D54<>0),(E54-D54)/D54,"") -> 0.22222222
A55: 52 | B55: Kencur | C55: Kg | F55: =IF(AND(D55<>"",E55<>""),E55-D55,"") | G55: =IF(AND(D55<>"",E55<>"",D55<>0),(E55-D55)/D55,"")
A56: 53 | B56: Ketumbar | C56: Kg | D56: 30000 | E56: 40000 | F56: =IF(AND(D56<>"",E56<>""),E56-D56,"") -> 10000 | G56: =IF(AND(D56<>"",E56<>"",D56<>0),(E56-D56)/D56,"") -> 0.33333333
A57: 54 | B57: Knorr | C57: Kg | D57: 95000 | E57: 100000 | F57: =IF(AND(D57<>"",E57<>""),E57-D57,"") -> 5000 | G57: =IF(AND(D57<>"",E57<>"",D57<>0),(E57-D57)/D57,"") -> 0.052631579
A58: 55 | B58: Kol | C58: Kg | D58: 6500 | E58: 14000 | F58: =IF(AND(D58<>"",E58<>""),E58-D58,"") -> 7500 | G58: =IF(AND(D58<>"",E58<>"",D58<>0),(E58-D58)/D58,"") -> 1.1538462
A59: 56 | B59: Kulit Kebab | C59: Pcs | D59: 25000 | E59: 32500 | F59: =IF(AND(D59<>"",E59<>""),E59-D59,"") -> 7500 | G59: =IF(AND(D59<>"",E59<>"",D59<>0),(E59-D59)/D59,"") -> 0.3
A60: 57 | B60: Kunyit | C60: Kg | D60: 12000 | E60: 15000 | F60: =IF(AND(D60<>"",E60<>""),E60-D60,"") -> 3000 | G60: =IF(AND(D60<>"",E60<>"",D60<>0),(E60-D60)/D60,"") -> 0.25
A61: 58 | B61: Labu Siam | C61: Kg | D61: 9000 | E61: 12000 | F61: =IF(AND(D61<>"",E61<>""),E61-D61,"") -> 3000 | G61: =IF(AND(D61<>"",E61<>"",D61<>0),(E61-D61)/D61,"") -> 0.33333333
A62: 59 | B62: Lada | C62: Kg | D62: 170000 | E62: 180000 | F62: =IF(AND(D62<>"",E62<>""),E62-D62,"") -> 10000 | G62: =IF(AND(D62<>"",E62<>"",D62<>0),(E62-D62)/D62,"") -> 0.058823529
A63: 60 | B63: Lada hitam | C63: Kg | D63: 170000 | E63: 180000 | F63: =IF(AND(D63<>"",E63<>""),E63-D63,"") -> 10000 | G63: =IF(AND(D63<>"",E63<>"",D63<>0),(E63-D63)/D63,"") -> 0.058823529
A64: 61 | B64: Lada putih bubuk | C64: Kg | D64: 140000 | E64: 180000 | F64: =IF(AND(D64<>"",E64<>""),E64-D64,"") -> 40000 | G64: =IF(AND(D64<>"",E64<>"",D64<>0),(E64-D64)/D64,"") -> 0.28571429
A65: 62 | B65: Lengkuas | C65: Kg | D65: 16000 | E65: 15000 | F65: =IF(AND(D65<>"",E65<>""),E65-D65,"") -> -1000 | G65: =IF(AND(D65<>"",E65<>"",D65<>0),(E65-D65)/D65,"") -> -0.0625
A66: 63 | B66: Margarin | C66: Kg | D66: 24000 | E66: 26000 | F66: =IF(AND(D66<>"",E66<>""),E66-D66,"") -> 2000 | G66: =IF(AND(D66<>"",E66<>"",D66<>0),(E66-D66)/D66,"") -> 0.083333333
A67: 64 | B67: Mayonaise | C67: Kg | F67: =IF(AND(D67<>"",E67<>""),E67-D67,"") | G67: =IF(AND(D67<>"",E67<>"",D67<>0),(E67-D67)/D67,"")
A68: 65 | B68: Mentega | C68: Kg | F68: =IF(AND(D68<>"",E68<>""),E68-D68,"") | G68: =IF(AND(D68<>"",E68<>"",D68<>0),(E68-D68)/D68,"")
A69: 66 | B69: Minyak | C69: Liter | D69: 205000 | E69: 270000 | F69: =IF(AND(D69<>"",E69<>""),E69-D69,"") -> 65000 | G69: =IF(AND(D69<>"",E69<>"",D69<>0),(E69-D69)/D69,"") -> 0.31707317
A70: 67 | B70: Minyak wijen | C70: Botol | D70: 47000 | E70: 55000 | F70: =IF(AND(D70<>"",E70<>""),E70-D70,"") -> 8000 | G70: =IF(AND(D70<>"",E70<>"",D70<>0),(E70-D70)/D70,"") -> 0.17021277
A71: 68 | B71: Pisang | C71: Pcs | D71: 1900 | E71: 2000 | F71: =IF(AND(D71<>"",E71<>""),E71-D71,"") -> 100 | G71: =IF(AND(D71<>"",E71<>"",D71<>0),(E71-D71)/D71,"") -> 0.052631579
A72: 69 | B72: Roti Burger | C72: Pcs | F72: =IF(AND(D72<>"",E72<>""),E72-D72,"") | G72: =IF(AND(D72<>"",E72<>"",D72<>0),(E72-D72)/D72,"")
A73: 70 | B73: Roti Tawar | C73: Pack | F73: =IF(AND(D73<>"",E73<>""),E73-D73,"") | G73: =IF(AND(D73<>"",E73<>"",D73<>0),(E73-D73)/D73,"")
A74: 71 | B74: Royko | C74: Kg | D74: 42000 | E74: 46000 | F74: =IF(AND(D74<>"",E74<>""),E74-D74,"") -> 4000 | G74: =IF(AND(D74<>"",E74<>"",D74<>0),(E74-D74)/D74,"") -> 0.095238095
A75: 72 | B75: Saus BBQ | C75: Kg | E75: 32500 | F75: =IF(AND(D75<>"",E75<>""),E75-D75,"") | G75: =IF(AND(D75<>"",E75<>"",D75<>0),(E75-D75)/D75,"")
A76: 73 | B76: Saus Bulgogi | C76: Botol | D76: 115000 | E76: 125000 | F76: =IF(AND(D76<>"",E76<>""),E76-D76,"") -> 10000 | G76: =IF(AND(D76<>"",E76<>"",D76<>0),(E76-D76)/D76,"") -> 0.086956522
A77: 74 | B77: Saus Pedas | C77: Dirigen | D77: 135000 | E77: 155000 | F77: =IF(AND(D77<>"",E77<>""),E77-D77,"") -> 20000 | G77: =IF(AND(D77<>"",E77<>"",D77<>0),(E77-D77)/D77,"") -> 0.14814815
A78: 75 | B78: Saus Sambal Sachet | C78: Dus | D78: 115000 | E78: 125000 | F78: =IF(AND(D78<>"",E78<>""),E78-D78,"") -> 10000 | G78: =IF(AND(D78<>"",E78<>"",D78<>0),(E78-D78)/D78,"") -> 0.086956522
A79: 76 | B79: Saus tiram | C79: Botol | D79: 52000 | E79: 57000 | F79: =IF(AND(D79<>"",E79<>""),E79-D79,"") -> 5000 | G79: =IF(AND(D79<>"",E79<>"",D79<>0),(E79-D79)/D79,"") -> 0.096153846
A80: 77 | B80: Saus tomat | C80: Dirigen | D80: 95000 | E80: 100000 | F80: =IF(AND(D80<>"",E80<>""),E80-D80,"") -> 5000 | G80: =IF(AND(D80<>"",E80<>"",D80<>0),(E80-D80)/D80,"") -> 0.052631579
A81: 78 | B81: Saus Tomat Sachet | C81: Pcs | D81: 5750 | E81: 7500 | F81: =IF(AND(D81<>"",E81<>""),E81-D81,"") -> 1750 | G81: =IF(AND(D81<>"",E81<>"",D81<>0),(E81-D81)/D81,"") -> 0.30434783
A82: 79 | B82: Sawi hijau | C82: Kg | D82: 9000 | E82: 12000 | F82: =IF(AND(D82<>"",E82<>""),E82-D82,"") -> 3000 | G82: =IF(AND(D82<>"",E82<>"",D82<>0),(E82-D82)/D82,"") -> 0.33333333
A83: 80 | B83: Sawi putih | C83: Kg | D83: 9000 | E83: 15000 | F83: =IF(AND(D83<>"",E83<>""),E83-D83,"") -> 6000 | G83: =IF(AND(D83<>"",E83<>"",D83<>0),(E83-D83)/D83,"") -> 0.66666667
A84: 81 | B84: Selada | C84: Kg | D84: 34000 | E84: 37000 | F84: =IF(AND(D84<>"",E84<>""),E84-D84,"") -> 3000 | G84: =IF(AND(D84<>"",E84<>"",D84<>0),(E84-D84)/D84,"") -> 0.088235294
A85: 82 | B85: Semangka | C85: Kg | D85: 18500 | E85: 21500 | F85: =IF(AND(D85<>"",E85<>""),E85-D85,"") -> 3000 | G85: =IF(AND(D85<>"",E85<>"",D85<>0),(E85-D85)/D85,"") -> 0.16216216
A86: 83 | B86: Sereh | C86: Kg | D86: 12000 | E86: 15000 | F86: =IF(AND(D86<>"",E86<>""),E86-D86,"") -> 3000 | G86: =IF(AND(D86<>"",E86<>"",D86<>0),(E86-D86)/D86,"") -> 0.25
A87: 84 | B87: Susu UHT | C87: Pcs | D87: 3264 | E87: 3700 | F87: =IF(AND(D87<>"",E87<>""),E87-D87,"") -> 436 | G87: =IF(AND(D87<>"",E87<>"",D87<>0),(E87-D87)/D87,"") -> 0.13357843
... A93: 90 | B93: Tempe | C93: Papan | D93: 12000 | E93: 14000 | F93: =IF(AND(D93<>"",E93<>""),E93-D93,"") -> 2000 | G93: =IF(AND(D93<>"",E93<>"",D93<>0),(E93-D93)/D93,"") -> 0.16666667
A94: 91 | B94: Tepung Cakra | C94: Kg | E94: 14000 | F94: =IF(AND(D94<>"",E94<>""),E94-D94,"") | G94: =IF(AND(D94<>"",E94<>"",D94<>0),(E94-D94)/D94,"")
A95: 92 | B95: Tepung Serbaguna | C95: Kg | D95: 23000 | E95: 26500 | F95: =IF(AND(D95<>"",E95<>""),E95-D95,"") -> 3500 | G95: =IF(AND(D95<>"",E95<>"",D95<>0),(E95-D95)/D95,"") -> 0.15217391
A96: 93 | B96: Tepung Tapioka | C96: Kg | D96: 12000 | E96: 14000 | F96: =IF(AND(D96<>"",E96<>""),E96-D96,"") -> 2000 | G96: =IF(AND(D96<>"",E96<>"",D96<>0),(E96-D96)/D96,"") -> 0.16666667
A97: 94 | B97: Tepung Terigu | C97: Kg | D97: 11500 | E97: 300000 | F97: =IF(AND(D97<>"",E97<>""),E97-D97,"") -> 288500 | G97: =IF(AND(D97<>"",E97<>"",D97<>0),(E97-D97)/D97,"") -> 25.086957
A98: 95 | B98: Terasi | C98: Kg | D98: 7000 | E98: 15000 | F98: =IF(AND(D98<>"",E98<>""),E98-D98,"") -> 8000 | G98: =IF(AND(D98<>"",E98<>"",D98<>0),(E98-D98)/D98,"") -> 1.1428571
A99: 96 | B99: Timun | C99: Kg | D99: 8000 | E99: 13000 | F99: =IF(AND(D99<>"",E99<>""),E99-D99,"") -> 5000 | G99: =IF(AND(D99<>"",E99<>"",D99<>0),(E99-D99)/D99,"") -> 0.625
A100: 97 | B100: Tomat | C100: Kg | D100: 14000 | E100: 18000 | F100: =IF(AND(D100<>"",E100<>""),E100-D100,"") -> 4000 | G100: =IF(AND(D100<>"",E100<>"",D100<>0),(E100-D100)/D100,"") -> 0.28571429
A101: 98 | B101: Wortel | C101: Kg | D101: 9000 | E101: 14000 | F101: =IF(AND(D101<>"",E101<>""),E101-D101,"") -> 5000 | G101: =IF(AND(D101<>"",E101<>"",D101<>0),(E101-D101)/D101,"") -> 0.55555556

Sheet Invoice B01
A1: 🧾 DRAFT INVOICE — BAKUNG 01
A2: Periode: Mei-Juni 2026 | 🟢 Hijau = linked Daftar Harga | 🔵 Biru = input manual (isi setelah nota datang)
A3: Kolom G (Harga Beli Nota) dikosongkan — isi saat barang tiba. Margin: pakai Nota jika ada, fallback ke Estimasi.
A4: 📅 Sunday, 24 May 2026
A5: No | B5: Nama Barang | C5: Satuan | D5: Qty | E5: 📊 ESTIMASI | G5: 🧾 REALISASI BELI | I5: 💰 PENJUALAN | K5: 📈 MARGIN | M5: Keterangan
A6: No | B6: Nama Barang | C6: Satuan | D6: Qty | E6: Est. Harga Beli (Rp) | F6: Total Estimasi (Rp) | G6: Harga Beli Nota (Rp) | H6: Total Beli Nota (Rp) | I6: Harga Jual (Rp) | J6: Total Jual (Rp) | K6: Margin (Rp) | L6: Margin (%) | M6: Keterangan
A7: 1 | B7: Bandeng presto | C7: Pcs | D7: 2550 | E7: ='Daftar Harga'!D11 | F7: =IF(E7<>"",D7*E7,"") | G7: 3500 | H7: =IF(G7<>"",D7*G7,"") -> 8925000 | I7: 3800 | J7: =IF(I7<>"",D7*I7,"") -> 9690000 | K7: =IF(J7<>"",IF(H7<>"",J7-H7,IF(F7<>"",J7-F7,"")),"") -> 765000 | L7: =IF(K7<>"",IF(H7<>"",IF(H7<>0,K7/H7,""),IF(F7<>"",IF(F7<>0,K7/F7,""),"")),"") -> 0.085714286
A8: 2 | B8: Bawang merah kupas | C8: Kg | D8: 3 | E8: ='Daftar Harga'!D14 -> 40000 | F8: =IF(E8<>"",D8*E8,"") -> 120000 | G8: 40000 | H8: =IF(G8<>"",D8*G8,"") -> 120000 | I8: 45000 | J8: =IF(I8<>"",D8*I8,"") -> 135000 | K8: =IF(J8<>"",IF(H8<>"",J8-H8,IF(F8<>"",J8-F8,"")),"") -> 15000 | L8: =IF(K8<>"",IF(H8<>"",IF(H8<>0,K8/H8,""),IF(F8<>"",IF(F8<>0,K8/F8,""),"")),"") -> 0.125
A9: 3 | B9: Bawang putih kupas | C9: Kg | D9: 3 | E9: ='Daftar Harga'!D16 -> 33000 | F9: =IF(E9<>"",D9*E9,"") -> 99000 | G9: 30000 | H9: =IF(G9<>"",D9*G9,"") -> 90000 | I9: 44000 | J9: =IF(I9<>"",D9*I9,"") -> 132000 | K9: =IF(J9<>"",IF(H9<>"",J9-H9,IF(F9<>"",J9-F9,"")),"") -> 42000 | L9: =IF(K9<>"",IF(H9<>"",IF(H9<>0,K9/H9,""),IF(F9<>"",IF(F9<>0,K9/F9,""),"")),"") -> 0.46666667
A10: 4 | B10: Beras | C10: Kg | D10: 100 | E10: ='Daftar Harga'!D17 -> 15500 | F10: =IF(E10<>"",D10*E10,"") -> 1550000 | G10: 14500 | H10: =IF(G10<>"",D10*G10,"") -> 1450000 | I10: 15500 | J10: =IF(I10<>"",D10*I10,"") -> 1550000 | K10: =IF(J10<>"",IF(H10<>"",J10-H10,IF(F10<>"",J10-F10,"")),"") -> 100000 | L10: =IF(K10<>"",IF(H10<>"",IF(H10<>0,K10/H10,""),IF(F10<>"",IF(F10<>0,K10/F10,""),"")),"") -> 0.068965517
A11: 5 | B11: Gula pasir | C11: Kg | D11: 5 | E11: ='Daftar Harga'!D36 -> 19000 | F11: =IF(E11<>"",D11*E11,"") -> 95000 | G11: 18500 | H11: =IF(G11<>"",D11*G11,"") -> 92500 | I11: 20000 | J11: =IF(I11<>"",D11*I11,"") -> 100000 | K11: =IF(J11<>"",IF(H11<>"",J11-H11,IF(F11<>"",J11-F11,"")),"") -> 7500 | L11: =IF(K11<>"",IF(H11<>"",IF(H11<>0,K11/H11,""),IF(F11<>"",IF(F11<>0,K11/F11,""),"")),"") -> 0.081081081
A12: 6 | B12: Knorr | C12: Kg | D12: 5 | E12: ='Daftar Harga'!D57 -> 95000 | F12: =IF(E12<>"",D12*E12,"") -> 475000 | G12: 94000 | H12: =IF(G12<>"",D12*G12,"") -> 470000 | I12: 105000 | J12: =IF(I12<>"",D12*I12,"") -> 525000 | K12: =IF(J12<>"",IF(H12<>"",J12-H12,IF(F12<>"",J12-F12,"")),"") -> 55000 | L12: =IF(K12<>"",IF(H12<>"",IF(H12<>0,K12/H12,""),IF(F12<>"",IF(F12<>0,K12/F12,""),"")),"") -> 0.11702128
A13: 7 | B13: Kol | C13: Kg | D13: 60 | E13: ='Daftar Harga'!D58 -> 6500 | F13: =IF(E13<>"",D13*E13,"") -> 390000 | G13: 7500 | H13: =IF(G13<>"",D13*G13,"") -> 450000 | I13: 12000 | J13: =IF(I13<>"",D13*I13,"") -> 720000 | K13: =IF(J13<>"",IF(H13<>"",J13-H13,IF(F13<>"",J13-F13,"")),"") -> 270000 | L13: =IF(K13<>"",IF(H13<>"",IF(H13<>0,K13/H13,""),IF(F13<>"",IF(F13<>0,K13/F13,""),"")),"") -> 0.6
A14: 8 | B14: Kunyit | C14: Kg | D14: 1 | E14: ='Daftar Harga'!D60 -> 12000 | F14: =IF(E14<>"",D14*E14,"") -> 12000 | G14: 12000 | H14: =IF(G14<>"",D14*G14,"") -> 12000 | I14: 16000 | J14: =IF(I14<>"",D14*I14,"") -> 16000 | K14: =IF(J14<>"",IF(H14<>"",J14-H14,IF(F14<>"",J14-F14,"")),"") -> 4000 | L14: =IF(K14<>"",IF(H14<>"",IF(H14<>0,K14/H14,""),IF(F14<>"",IF(F14<>0,K14/F14,""),"")),"") -> 0.33333333
A15: 9 | B15: Minyak | C15: Liter | D15: 60 | E15: ='Daftar Harga'!D69 -> 205000 | F15: =IF(E15<>"",D15*E15,"") -> 12300000 | G15: 22000 | H15: =IF(G15<>"",D15*G15,"") -> 1320000 | I15: 23000 | J15: =IF(I15<>"",D15*I15,"") -> 1380000 | K15: =IF(J15<>"",IF(H15<>"",J15-H15,IF(F15<>"",J15-F15,"")),"") -> 60000 | L15: =IF(K15<>"",IF(H15<>"",IF(H15<>0,K15/H15,""),IF(F15<>"",IF(F15<>0,K15/F15,""),"")),"") -> 0.045454545
A16: 10 | B16: Tahu | C16: Pcs | D16: 2600 | E16: ='Daftar Harga'!D71 -> 1900 | F16: =IF(E16<>"",D16*E16,"") -> 4940000 | G16: 480 | H16: =IF(G16<>"",D16*G16,"") -> 1248000 | I16: 700 | J16: =IF(I16<>"",D16*I16,"") -> 1820000 | K16: =IF(J16<>"",IF(H16<>"",J16-H16,IF(F16<>"",J16-F16,"")),"") -> 572000 | L16: =IF(K16<>"",IF(H16<>"",IF(H16<>0,K16/H16,""),IF(F16<>"",IF(F16<>0,K16/F16,""),"")),"") -> 0.45833333
A17: 11 | B17: Sawi hijau | C17: Kg | D17: 20 | E17: ='Daftar Harga'!D82 -> 9000 | F17: =IF(E17<>"",D17*E17,"") -> 180000 | G17: 6000 | H17: =IF(G17<>"",D17*G17,"") -> 120000 | I17: 12000 | J17: =IF(I17<>"",D17*I17,"") -> 240000 | K17: =IF(J17<>"",IF(H17<>"",J17-H17,IF(F17<>"",J17-F17,"")),"") -> 120000 | L17: =IF(K17<>"",IF(H17<>"",IF(H17<>0,K17/H17,""),IF(F17<>"",IF(F17<>0,K17/F17,""),"")),"") -> 1
A18: 12 | B18: Wortel | C18: Kg | D18: 30 | E18: ='Daftar Harga'!D101 -> 9000 | F18: =IF(E18<>"",D18*E18,"") -> 270000 | G18: 12000 | H18: =IF(G18<>"",D18*G18,"") -> 360000 | I18: 14000 | J18: =IF(I18<>"",D18*I18,"") -> 420000 | K18: =IF(J18<>"",IF(H18<>"",J18-H18,IF(F18<>"",J18-F18,"")),"") -> 60000 | L18: =IF(K18<>"",IF(H18<>"",IF(H18<>0,K18/H18,""),IF(F18<>"",IF(F18<>0,K18/F18,""),"")),"") -> 0.16666667
A19: 13 | B19: Semangka | C19: Kg | D19: 220 | E19: ='Daftar Harga'!D102 | F19: =IF(E19<>"",D19*E19,"") | G19: 18500 | H19: =IF(G19<>"",D19*G19,"") -> 4070000 | I19: 20500 | J19: =IF(I19<>"",D19*I19,"") -> 4510000 | K19: =IF(J19<>"",IF(H19<>"",J19-H19,IF(F19<>"",J19-F19,"")),"") -> 440000 | L19: =IF(K19<>"",IF(H19<>"",IF(H19<>0,K19/H19,""),IF(F19<>"",IF(F19<>0,K19/F19,""),"")),"") -> 0.10810811
A20: 14 | B20: Apel | C20: Box | D20: 7 | E20: ='Daftar Harga'!D103 | F20: =IF(E20<>"",D20*E20,"") | G20: 590000 | H20: =IF(G20<>"",D20*G20,"") -> 4130000 | I20: 605000 | J20: =IF(I20<>"",D20*I20,"") -> 4235000 | K20: =IF(J20<>"",IF(H20<>"",J20-H20,IF(F20<>"",J20-F20,"")),"") -> 105000 | L20: =IF(K20<>"",IF(H20<>"",IF(H20<>0,K20/H20,""),IF(F20<>"",IF(F20<>0,K20/F20,""),"")),"") -> 0.025423729
A21: SUBTOTAL 24 May 2026 | F21: =SUMIF(F7:F20,"<>",F7:F20) -> 20431000 | H21: =SUMIF(H7:H20,"<>",H7:H20) -> 22857500 | J21: =SUMIF(J7:J20,"<>",J7:J20) -> 25473000 | K21: =IF(J21<>"",IF(H21<>"",J21-H21,IF(F21<>"",J21-F21,"")),"") -> 2615500 | L21: =IF(K21<>"",IF(H21<>"",IF(H21<>0,K21/H21,""),IF(F21<>"",IF(F21<>0,K21/F21,""),"")),"") -> 0.11442634
A23: 📅 Monday, 25 May 2026
A24: No | B24: Nama Barang | C24: Satuan | D24: Qty | E24: 📊 ESTIMASI | G24: 🧾 REALISASI BELI | I24: 💰 PENJUALAN | K24: 📈 MARGIN | M24: Keterangan
A25: No | B25: Nama Barang | C25: Satuan | D25: Qty | E25: Est. Harga Beli (Rp) | F25: Total Estimasi (Rp) | G25: Harga Beli Nota (Rp) | H25: Total Beli Nota (Rp) | I25: Harga Jual (Rp) | J25: Total Jual (Rp) | K25: Margin (Rp) | L25: Margin (%) | M25: Keterangan
A26: 1 | B26: Ayam Potong | C26: Kg | D26: 265 | E26: ='Daftar Harga'!D9 -> 36500 | F26: =IF(E26<>"",D26*E26,"") -> 9672500 | G26: 34000 | H26: =IF(G26<>"",D26*G26,"") -> 9010000 | I26: 38000 | J26: =IF(I26<>"",D26*I26,"") -> 10070000 | K26: =IF(J26<>"",IF(H26<>"",J26-H26,IF(F26<>"",J26-F26,"")),"") -> 1060000 | L26: =IF(K26<>"",IF(H26<>"",IF(H26<>0,K26/H26,""),IF(F26<>"",IF(F26<>0,K26/F26,""),"")),"") -> 0.11764706
A27: 2 | B27: Bawang merah kupas | C27: Kg | D27: 3 | E27: ='Daftar Harga'!D14 -> 40000 | F27: =IF(E27<>"",D27*E27,"") -> 120000 | G27: 40000 | H27: =IF(G27<>"",D27*G27,"") -> 120000 | I27: 45000 | J27: =IF(I27<>"",D27*I27,"") -> 135000 | K27: =IF(J27<>"",IF(H27<>"",J27-H27,IF(F27<>"",J27-F27,"")),"") -> 15000 | L27: =IF(K27<>"",IF(H27<>"",IF(H27<>0,K27/H27,""),IF(F27<>"",IF(F27<>0,K27/F27,""),"")),"") -> 0.125
A28: 3 | B28: Bawang putih kupas | C28: Kg | D28: 3 | E28: ='Daftar Harga'!D16 -> 33000 | F28: =IF(E28<>"",D28*E28,"") -> 99000 | G28: 30000 | H28: =IF(G28<>"",D28*G28,"") -> 90000 | I28: 40000 | J28: =IF(I28<>"",D28*I28,"") -> 120000 | K28: =IF(J28<>"",IF(H28<>"",J28-H28,IF(F28<>"",J28-F28,"")),"") -> 30000 | L28: =IF(K28<>"",IF(H28<>"",IF(H28<>0,K28/H28,""),IF(F28<>"",IF(F28<>0,K28/F28,""),"")),"") -> 0.33333333
A29: 4 | B29: Beras | C29: Kg | D29: 125 | E29: ='Daftar Harga'!D17 -> 15500 | F29: =IF(E29<>"",D29*E29,"") -> 1937500 | G29: 14500 | H29: =IF(G29<>"",D29*G29,"") -> 1812500 | I29: 15500 | J29: =IF(I29<>"",D29*I29,"") -> 1937500 | K29: =IF(J29<>"",IF(H29<>"",J29-H29,IF(F29<>"",J29-F29,"")),"") -> 125000 | L29: =IF(K29<>"",IF(H29<>"",IF(H29<>0,K29/H29,""),IF(F29<>"",IF(F29<>0,K29/F29,""),"")),"") -> 0.068965517
A30: 5 | B30: Blimbing | C30: Kg | D30: 67 | E30: ='Daftar Harga'!D18 | F30: =IF(E30<>"",D30*E30,"") | G30: 15000 | H30: =IF(G30<>"",D30*G30,"") -> 1005000 | I30: 20000 | J30: =IF(I30<>"",D30*I30,"") -> 1340000 | K30: =IF(J30<>"",IF(H30<>"",J30-H30,IF(F30<>"",J30-F30,"")),"") -> 335000 | L30: =IF(K30<>"",IF(H30<>"",IF(H30<>0,K30/H30,""),IF(F30<>"",IF(F30<>0,K30/F30,""),"")),"") -> 0.33333333
A31: 6 | B31: Gula pasir | C31: Kg | D31: 10 | E31: ='Daftar Harga'!D36 -> 19000 | F31: =IF(E31<>"",D31*E31,"") -> 190000 | G31: 18500 | H31: =IF(G31<>"",D31*G31,"") -> 185000 | I31: 20000 | J31: =IF(I31<>"",D31*I31,"") -> 200000 | K31: =IF(J31<>"",IF(H31<>"",J31-H31,IF(F31<>"",J31-F31,"")),"") -> 15000 | L31: =IF(K31<>"",IF(H31<>"",IF(H31<>0,K31/H31,""),IF(F31<>"",IF(F31<>0,K31/F31,""),"")),"") -> 0.081081081
A32: 7 | B32: Knorr | C32: Kg | D32: 2 | E32: ='Daftar Harga'!D57 -> 95000 | F32: =IF(E32<>"",D32*E32,"") -> 190000 | G32: 94500 | H32: =IF(G32<>"",D32*G32,"") -> 189000 | I32: 110000 | J32: =IF(I32<>"",D32*I32,"") -> 220000 | K32: =IF(J32<>"",IF(H32<>"",J32-H32,IF(F32<>"",J32-F32,"")),"") -> 31000 | L32: =IF(K32<>"",IF(H32<>"",IF(H32<>0,K32/H32,""),IF(F32<>"",IF(F32<>0,K32/F32,""),"")),"") -> 0.16402116
A33: 8 | B33: Kunyit | C33: Kg | D33: 2 | E33: ='Daftar Harga'!D60 -> 12000 | F33: =IF(E33<>"",D33*E33,"") -> 24000 | G33: 11667 | H33: =IF(G33<>"",D33*G33,"") -> 23334 | I33: 15000 | J33: =IF(I33<>"",D33*I33,"") -> 30000 | K33: =IF(J33<>"",IF(H33<>"",J33-H33,IF(F33<>"",J33-F33,"")),"") -> 6666 | L33: =IF(K33<>"",IF(H33<>"",IF(H33<>0,K33/H33,""),IF(F33<>"",IF(F33<>0,K33/F33,""),"")),"") -> 0.28567755
A34: 9 | B34: Minyak | C34: Liter | D34: 50 | E34: ='Daftar Harga'!D69 -> 205000 | F34: =IF(E34<>"",D34*E34,"") -> 10250000 | G34: 22000 | H34: =IF(G34<>"",D34*G34,"") -> 1100000 | I34: 25000 | J34: =IF(I34<>"",D34*I34,"") -> 1250000 | K34: =IF(J34<>"",IF(H34<>"",J34-H34,IF(F34<>"",J34-F34,"")),"") -> 150000 | L34: =IF(K34<>"",IF(H34<>"",IF(H34<>0,K34/H34,""),IF(F34<>"",IF(F34<>0,K34/F34,""),"")),"") -> 0.13636364
A35: 10 | B35: Semangka | C35: Kg | D35: 230 | E35: ='Daftar Harga'!D85 -> 18500 | F35: =IF(E35<>"",D35*E35,"") -> 4255000 | G35: 18500 | H35: =IF(G35<>"",D35*G35,"") -> 4255000 | I35: 21500 | J35: =IF(I35<>"",D35*I35,"") -> 4945000 | K35: =IF(J35<>"",IF(H35<>"",J35-H35,IF(F35<>"",J35-F35,"")),"") -> 690000 | L35: =IF(K35<>"",IF(H35<>"",IF(H35<>0,K35/H35,""),IF(F35<>"",IF(F35<>0,K35/F35,""),"")),"") -> 0.16216216
A36: 11 | B36: Tempe | C36: Papan | D36: 130 | E36: ='Daftar Harga'!D93 -> 12000 | F36: =IF(E36<>"",D36*E36,"") -> 1560000 | G36: 12000 | H36: =IF(G36<>"",D36*G36,"") -> 1560000 | I36: 14000 | J36: =IF(I36<>"",D36*I36,"") -> 1820000 | K36: =IF(J36<>"",IF(H36<>"",J36-H36,IF(F36<>"",J36-F36,"")),"") -> 260000 | L36: =IF(K36<>"",IF(H36<>"",IF(H36<>0,K36/H36,""),IF(F36<>"",IF(F36<>0,K36/F36,""),"")),"") -> 0.16666667
A37: 12 | B37: Tepung Serbaguna | C37: Kg | D37: 30 | E37: ='Daftar Harga'!D95 -> 23000 | F37: =IF(E37<>"",D37*E37,"") -> 690000 | G37: 22500 | H37: =IF(G37<>"",D37*G37,"") -> 675000 | I37: 26500 | J37: =IF(I37<>"",D37*I37,"") -> 795000 | K37: =IF(J37<>"",IF(H37<>"",J37-H37,IF(F37<>"",J37-F37,"")),"") -> 120000 | L37: =IF(K37<>"",IF(H37<>"",IF(H37<>0,K37/H37,""),IF(F37<>"",IF(F37<>0,K37/F37,""),"")),"") -> 0.17777778
A38: 13 | B38: Timun | C38: Kg | D38: 90 | E38: ='Daftar Harga'!D99 -> 8000 | F38: =IF(E38<>"",D38*E38,"") -> 720000 | G38: 9000 | H38: =IF(G38<>"",D38*G38,"") -> 810000 | I38: 13000 | J38: =IF(I38<>"",D38*I38,"") -> 1170000 | K38: =IF(J38<>"",IF(H38<>"",J38-H38,IF(F38<>"",J38-F38,"")),"") -> 360000 | L38: =IF(K38<>"",IF(H38<>"",IF(H38<>0,K38/H38,""),IF(F38<>"",IF(F38<>0,K38/F38,""),"")),"") -> 0.44444444
A39: 14 | B39: Wortel | C39: Kg | D39: 30 | E39: ='Daftar Harga'!D101 -> 9000 | F39: =IF(E39<>"",D39*E39,"") -> 270000 | G39: 12000 | H39: =IF(G39<>"",D39*G39,"") -> 360000 | I39: 14000 | J39: =IF(I39<>"",D39*I39,"") -> 420000 | K39: =IF(J39<>"",IF(H39<>"",J39-H39,IF(F39<>"",J39-F39,"")),"") -> 60000 | L39: =IF(K39<>"",IF(H39<>"",IF(H39<>0,K39/H39,""),IF(F39<>"",IF(F39<>0,K39/F39,""),"")),"") -> 0.16666667
A40: 15 | B40: Kecap Sedap 720Ml | C40: Pcs | D40: 4 | F40: =IF(E40<>"",D40*E40,"") | G40: 26900 | H40: =IF(G40<>"",D40*G40,"") -> 107600 | I40: 30000 | J40: =IF(I40<>"",D40*I40,"") -> 120000 | K40: =IF(J40<>"",IF(H40<>"",J40-H40,IF(F40<>"",J40-F40,"")),"") -> 12400 | L40: =IF(K40<>"",IF(H40<>"",IF(H40<>0,K40/H40,""),IF(F40<>"",IF(F40<>0,K40/F40,""),"")),"") -> 0.11524164
A41: 16 | B41: Kecap Bango 700 Gr | C41: Pcs | D41: 3 | F41: =IF(E41<>"",D41*E41,"") | G41: 26900 | H41: =IF(G41<>"",D41*G41,"") -> 80700 | I41: 30000 | J41: =IF(I41<>"",D41*I41,"") -> 90000 | K41: =IF(J41<>"",IF(H41<>"",J41-H41,IF(F41<>"",J41-F41,"")),"") -> 9300 | L41: =IF(K41<>"",IF(H41<>"",IF(H41<>0,K41/H41,""),IF(F41<>"",IF(F41<>0,K41/F41,""),"")),"") -> 0.11524164
A42: SUBTOTAL 25 May 2026 | F42: =SUMIF(F26:F41,"<>",F26:F41) -> 29978000 | H42: =SUMIF(H26:H41,"<>",H26:H41) -> 21383134 | J42: =SUMIF(J26:J41,"<>",J26:J41) -> 24662500 | K42: =IF(J42<>"",IF(H42<>"",J42-H42,IF(F42<>"",J42-F42,"")),"") -> 3279366 | L42: =IF(K42<>"",IF(H42<>"",IF(H42<>0,K42/H42,""),IF(F42<>"",IF(F42<>0,K42/F42,""),"")),"") -> 0.15336227
A44: 📅 Thursday, 28 May 2026
A45: No | B45: Nama Barang | C45: Satuan | D45: Qty | E45: 📊 ESTIMASI | G45: 🧾 REALISASI BELI | I45: 💰 PENJUALAN | K45: 📈 MARGIN | M45: Keterangan
A46: No | B46: Nama Barang | C46: Satuan | D46: Qty | E46: Est. Harga Beli (Rp) | F46: Total Estimasi (Rp) | G46: Harga Beli Nota (Rp) | H46: Total Beli Nota (Rp) | I46: Harga Jual (Rp) | J46: Total Jual (Rp) | K46: Margin (Rp) | L46: Margin (%) | M46: Keterangan
A47: 1 | B47: Ayam Dada Fillet | C47: Kg | D47: 110 | E47: ='Daftar Harga'!D7 -> 46500 | F47: =IF(E47<>"",D47*E47,"") -> 5115000 | G47: 46500 | H47: =IF(G47<>"",D47*G47,"") -> 5115000 | I47: 48500 | J47: =IF(I47<>"",D47*I47,"") -> 5335000 | K47: =IF(J47<>"",IF(H47<>"",J47-H47,IF(F47<>"",J47-F47,"")),"") -> 220000 | L47: =IF(K47<>"",IF(H47<>"",IF(H47<>0,K47/H47,""),IF(F47<>"",IF(F47<>0,K47/F47,""),"")),"") -> 0.043010753
A48: 2 | B48: Bawang putih kupas | C48: Kg | D48: 2 | E48: ='Daftar Harga'!D16 -> 33000 | F48: =IF(E48<>"",D48*E48,"") -> 66000 | G48: 30000 | H48: =IF(G48<>"",D48*G48,"") -> 60000 | I48: 40000 | J48: =IF(I48<>"",D48*I48,"") -> 80000 | K48: =IF(J48<>"",IF(H48<>"",J48-H48,IF(F48<>"",J48-F48,"")),"") -> 20000 | L48: =IF(K48<>"",IF(H48<>"",IF(H48<>0,K48/H48,""),IF(F48<>"",IF(F48<>0,K48/F48,""),"")),"") -> 0.33333333
A49: 3 | B49: Edamame | C49: Kg | D49: 116.85 | E49: ='Daftar Harga'!D33 | F49: =IF(E49<>"",D49*E49,"") | G49: 34000 | H49: =IF(G49<>"",D49*G49,"") -> 3972900 | I49: 36000 | J49: =IF(I49<>"",D49*I49,"") -> 4206600 | K49: =IF(J49<>"",IF(H49<>"",J49-H49,IF(F49<>"",J49-F49,"")),"") -> 233700 | L49: =IF(K49<>"",IF(H49<>"",IF(H49<>0,K49/H49,""),IF(F49<>"",IF(F49<>0,K49/F49,""),"")),"") -> 0.058823529
A50: 4 | B50: Minyak | C50: Liter | D50: 50 | E50: ='Daftar Harga'!D69 -> 205000 | F50: =IF(E50<>"",D50*E50,"") -> 10250000 | G50: 22000 | H50: =IF(G50<>"",D50*G50,"") -> 1100000 | I50: 23000 | J50: =IF(I50<>"",D50*I50,"") -> 1150000 | K50: =IF(J50<>"",IF(H50<>"",J50-H50,IF(F50<>"",J50-F50,"")),"") -> 50000 | L50: =IF(K50<>"",IF(H50<>"",IF(H50<>0,K50/H50,""),IF(F50<>"",IF(F50<>0,K50/F50,""),"")),"") -> 0.045454545
A51: 5 | B51: Roti Burger | C51: Pcs | D51: 2550 | E51: ='Daftar Harga'!D72 | F51: =IF(E51<>"",D51*E51,"") | G51: 2000 | H51: =IF(G51<>"",D51*G51,"") -> 5100000 | I51: 2200 | J51: =IF(I51<>"",D51*I51,"") -> 5610000 | K51: =IF(J51<>"",IF(H51<>"",J51-H51,IF(F51<>"",J51-F51,"")),"") -> 510000 | L51: =IF(K51<>"",IF(H51<>"",IF(H51<>0,K51/H51,""),IF(F51<>"",IF(F51<>0,K51/F51,""),"")),"") -> 0.1
A52: 7 | B52: Selada | C52: Kg | D52: 30 | E52: ='Daftar Harga'!D84 -> 34000 | F52: =IF(E52<>"",D52*E52,"") -> 1020000 | G52: 35000 | H52: =IF(G52<>"",D52*G52,"") -> 1050000 | I52: 36000 | J52: =IF(I52<>"",D52*I52,"") -> 1080000 | K52: =IF(J52<>"",IF(H52<>"",J52-H52,IF(F52<>"",J52-F52,"")),"") -> 30000 | L52: =IF(K52<>"",IF(H52<>"",IF(H52<>0,K52/H52,""),IF(F52<>"",IF(F52<>0,K52/F52,""),"")),"") -> 0.028571429
A53: 9 | B53: Tepung Cakra | C53: Kg | D53: 25 | E53: ='Daftar Harga'!D94 | F53: =IF(E53<>"",D53*E53,"") | G53: 11750 | H53: =IF(G53<>"",D53*G53,"") -> 293750 | I53: 13000 | J53: =IF(I53<>"",D53*I53,"") -> 325000 | K53: =IF(J53<>"",IF(H53<>"",J53-H53,IF(F53<>"",J53-F53,"")),"") -> 31250 | L53: =IF(K53<>"",IF(H53<>"",IF(H53<>0,K53/H53,""),IF(F53<>"",IF(F53<>0,K53/F53,""),"")),"") -> 0.10638298
A54: 10 | B54: Tepung Serbaguna | C54: Kg | D54: 30 | E54: ='Daftar Harga'!D95 -> 23000 | F54: =IF(E54<>"",D54*E54,"") -> 690000 | G54: 22700 | H54: =IF(G54<>"",D54*G54,"") -> 681000 | I54: 25000 | J54: =IF(I54<>"",D54*I54,"") -> 750000 | K54: =IF(J54<>"",IF(H54<>"",J54-H54,IF(F54<>"",J54-F54,"")),"") -> 69000 | L54: =IF(K54<>"",IF(H54<>"",IF(H54<>0,K54/H54,""),IF(F54<>"",IF(F54<>0,K54/F54,""),"")),"") -> 0.10132159 | P54: =J58+J67 -> 48234800
A55: 11 | B55: Tepung Terigu | C55: Kg | D55: 50 | E55: ='Daftar Harga'!D97 -> 11500 | F55: =IF(E55<>"",D55*E55,"") -> 575000 | G55: 11500 | H55: =IF(G55<>"",D55*G55,"") -> 575000 | I55: 12000 | J55: =IF(I55<>"",D55*I55,"") -> 600000 | K55: =IF(J55<>"",IF(H55<>"",J55-H55,IF(F55<>"",J55-F55,"")),"") -> 25000 | L55: =IF(K55<>"",IF(H55<>"",IF(H55<>0,K55/H55,""),IF(F55<>"",IF(F55<>0,K55/F55,""),"")),"") -> 0.043478261
A56: 12 | B56: Timun | C56: Kg | D56: 80 | E56: ='Daftar Harga'!D99 -> 8000 | F56: =IF(E56<>"",D56*E56,"") -> 640000 | G56: 8000 | H56: =IF(G56<>"",D56*G56,"") -> 640000 | I56: 10000 | J56: =IF(I56<>"",D56*I56,"") -> 800000 | K56: =IF(J56<>"",IF(H56<>"",J56-H56,IF(F56<>"",J56-F56,"")),"") -> 160000 | L56: =IF(K56<>"",IF(H56<>"",IF(H56<>0,K56/H56,""),IF(F56<>"",IF(F56<>0,K56/F56,""),"")),"") -> 0.25
A57: 13 | B57: Pisang Ambon | C57: Pcs | D57: 2600 | F57: =IF(E57<>"",D57*E57,"") | G57: 1800 | H57: =IF(G57<>"",D57*G57,"") -> 4680000 | I57: 2000 | J57: =IF(I57<>"",D57*I57,"") -> 5200000 | K57: =IF(J57<>"",IF(H57<>"",J57-H57,IF(F57<>"",J57-F57,"")),"") -> 520000 | L57: =IF(K57<>"",IF(H57<>"",IF(H57<>0,K57/H57,""),IF(F57<>"",IF(F57<>0,K57/F57,""),"")),"") -> 0.11111111
A58: SUBTOTAL 28 May 2026 | F58: =SUMIF(F47:F56,"<>",F47:F56) -> 18356000 | H58: =SUMIF(H47:H57,"<>",H47:H57) -> 23267650 | J58: =SUMIF(J47:J57,"<>",J47:J57) -> 25136600 | K58: =IF(J58<>"",IF(H58<>"",J58-H58,IF(F58<>"",J58-F58,"")),"") -> 1868950 | L58: =IF(K58<>"",IF(H58<>"",IF(H58<>0,K58/H58,""),IF(F58<>"",IF(F58<>0,K58/F58,""),"")),"") -> 0.080323969
A60: 📅 Friday, 29 May 2026
A61: No | B61: Nama Barang | C61: Satuan | D61: Qty | E61: 📊 ESTIMASI | G61: 🧾 REALISASI BELI | I61: 💰 PENJUALAN | K61: 📈 MARGIN | M61: Keterangan
A62: No | B62: Nama Barang | C62: Satuan | D62: Qty | E62: Est. Harga Beli (Rp) | F62: Total Estimasi (Rp) | G62: Harga Beli Nota (Rp) | H62: Total Beli Nota (Rp) | I62: Harga Jual (Rp) | J62: Total Jual (Rp) | K62: Margin (Rp) | L62: Margin (%) | M62: Keterangan
A63: 1 | B63: Apel | C63: Kg | D63: 21 | F63: =IF(E63<>"",D63*E63,"") | G63: 590000 | H63: =IF(G63<>"",D63*G63,"") -> 12390000 | I63: 600000 | J63: =IF(I63<>"",D63*I63,"") -> 12600000 | K63: =IF(J63<>"",IF(H63<>"",J63-H63,IF(F63<>"",J63-F63,"")),"") -> 210000 | L63: =IF(K63<>"",IF(H63<>"",IF(H63<>0,K63/H63,""),IF(F63<>"",IF(F63<>0,K63/F63,""),"")),"") -> 0.016949153
A64: 2 | B64: Telur Ayam | C64: Kg | D64: 40 | F64: =IF(E64<>"",D64*E64,"") | G64: 25500 | H64: =IF(G64<>"",D64*G64,"") -> 1020000 | I64: 27000 | J64: =IF(I64<>"",D64*I64,"") -> 1080000 | K64: =IF(J64<>"",IF(H64<>"",J64-H64,IF(F64<>"",J64-F64,"")),"") -> 60000 | L64: =IF(K64<>"",IF(H64<>"",IF(H64<>0,K64/H64,""),IF(F64<>"",IF(F64<>0,K64/F64,""),"")),"") -> 0.058823529
A65: 3 | B65: Saos Tomat | C65: Pcs | D65: 2000 | F65: =IF(E65<>"",D65*E65,"") | G65: 240 | H65: =IF(G65<>"",D65*G65,"") -> 480000 | I65: 300 | J65: =IF(I65<>"",D65*I65,"") -> 600000 | K65: =IF(J65<>"",IF(H65<>"",J65-H65,IF(F65<>"",J65-F65,"")),"") -> 120000 | L65: =IF(K65<>"",IF(H65<>"",IF(H65<>0,K65/H65,""),IF(F65<>"",IF(F65<>0,K65/F65,""),"")),"") -> 0.25
A66: 4 | B66: Susu Uht | C66: Pcs | D66: 2556 | G66: 3167 | H66: =IF(G66<>"",D66*G66,"") -> 8094852 | I66: 3450 | J66: =IF(I66<>"",D66*I66,"") -> 8818200 | K66: =IF(J66<>"",IF(H66<>"",J66-H66,IF(F66<>"",J66-F66,"")),"") -> 723348 | L66: =IF(K66<>"",IF(H66<>"",IF(H66<>0,K66/H66,""),IF(F66<>"",IF(F66<>0,K66/F66,""),"")),"") -> 0.089359015
A67: SUBTOTAL 28 May 2026 | F67: =SUMIF(F63:F65,"<>",F63:F65) -> 0 | H67: =SUMIF(H63:H66,"<>",H63:H66) -> 21984852 | J67: =SUMIF(J63:J66,"<>",J63:J66) -> 23098200 | K67: =IF(J67<>"",IF(H67<>"",J67-H67,IF(F67<>"",J67-F67,"")),"") -> 1113348 | L67: =IF(K67<>"",IF(H67<>"",IF(H67<>0,K67/H67,""),IF(F67<>"",IF(F67<>0,K67/F67,""),"")),"") -> 0.050641596
A69: 📅 Monday, 01 June 2026
A70: No | B70: Nama Barang | C70: Satuan | D70: Qty | E70: 📊 ESTIMASI | G70: 🧾 REALISASI BELI | I70: 💰 PENJUALAN | K70: 📈 MARGIN | M70: Keterangan
A71: No | B71: Nama Barang | C71: Satuan | D71: Qty | E71: Est. Harga Beli (Rp) | F71: Total Estimasi (Rp) | G71: Harga Beli Nota (Rp) | H71: Total Beli Nota (Rp) | I71: Harga Jual (Rp) | J71: Total Jual (Rp) | K71: Margin (Rp) | L71: Margin (%) | M71: Keterangan
A72: 1 | B72: Bawang Merah Kupas | C72: Kg | D72: 3 | F72: =IF(E72<>"",D72*E72,"") | G72: 40000 | H72: =IF(G72<>"",D72*G72,"") -> 120000 | I72: 45000 | J72: =IF(I72<>"",D72*I72,"") -> 135000 | K72: =IF(J72<>"",IF(H72<>"",J72-H72,IF(F72<>"",J72-F72,"")),"") -> 15000 | L72: =IF(K72<>"",IF(H72<>"",IF(H72<>0,K72/H72,""),IF(F72<>"",IF(F72<>0,K72/F72,""),"")),"") -> 0.125
A73: 2 | B73: Bawang Putih Kupas | C73: Kg | D73: 3 | F73: =IF(E73<>"",D73*E73,"") | G73: 30000 | H73: =IF(G73<>"",D73*G73,"") -> 90000 | I73: 44000 | J73: =IF(I73<>"",D73*I73,"") -> 132000 | K73: =IF(J73<>"",IF(H73<>"",J73-H73,IF(F73<>"",J73-F73,"")),"") -> 42000 | L73: =IF(K73<>"",IF(H73<>"",IF(H73<>0,K73/H73,""),IF(F73<>"",IF(F73<>0,K73/F73,""),"")),"") -> 0.46666667
A74: 3 | B74: Beras | C74: Kg | D74: 125 | F74: =IF(E74<>"",D74*E74,"") | G74: 14500 | H74: =IF(G74<>"",D74*G74,"") -> 1812500 | I74: 15500 | J74: =IF(I74<>"",D74*I74,"") -> 1937500 | K74: =IF(J74<>"",IF(H74<>"",J74-H74,IF(F74<>"",J74-F74,"")),"") -> 125000 | L74: =IF(K74<>"",IF(H74<>"",IF(H74<>0,K74/H74,""),IF(F74<>"",IF(F74<>0,K74/F74,""),"")),"") -> 0.068965517
A75: 4 | B75: Daun Bawang | C75: Kg | D75: 3 | F75: =IF(E75<>"",D75*E75,"") | G75: 15000 | H75: =IF(G75<>"",D75*G75,"") -> 45000 | I75: 12000 | J75: =IF(I75<>"",D75*I75,"") -> 36000 | K75: =IF(J75<>"",IF(H75<>"",J75-H75,IF(F75<>"",J75-F75,"")),"") -> -9000 | L75: =IF(K75<>"",IF(H75<>"",IF(H75<>0,K75/H75,""),IF(F75<>"",IF(F75<>0,K75/F75,""),"")),"") -> -0.2
A76: 5 | B76: Kecap Manis | C76: Dirigen | D76: 2 | F76: =IF(E76<>"",D76*E76,"") | G76: 190000 | H76: =IF(G76<>"",D76*G76,"") -> 380000 | I76: 210000 | J76: =IF(I76<>"",D76*I76,"") -> 420000 | K76: =IF(J76<>"",IF(H76<>"",J76-H76,IF(F76<>"",J76-F76,"")),"") -> 40000 | L76: =IF(K76<>"",IF(H76<>"",IF(H76<>0,K76/H76,""),IF(F76<>"",IF(F76<>0,K76/F76,""),"")),"") -> 0.10526316
A77: 6 | B77: Knorr | C77: Kg | D77: 1 | F77: =IF(E77<>"",D77*E77,"") | G77: 94000 | H77: =IF(G77<>"",D77*G77,"") -> 94000 | I77: 105000 | J77: =IF(I77<>"",D77*I77,"") -> 105000 | K77: =IF(J77<>"",IF(H77<>"",J77-H77,IF(F77<>"",J77-F77,"")),"") -> 11000 | L77: =IF(K77<>"",IF(H77<>"",IF(H77<>0,K77/H77,""),IF(F77<>"",IF(F77<>0,K77/F77,""),"")),"") -> 0.11702128
A78: 7 | B78: Kol | C78: Kg | D78: 80 | F78: =IF(E78<>"",D78*E78,"") | G78: 7000 | H78: =IF(G78<>"",D78*G78,"") -> 560000 | I78: 14000 | J78: =IF(I78<>"",D78*I78,"") -> 1120000 | K78: =IF(J78<>"",IF(H78<>"",J78-H78,IF(F78<>"",J78-F78,"")),"") -> 560000 | L78: =IF(K78<>"",IF(H78<>"",IF(H78<>0,K78/H78,""),IF(F78<>"",IF(F78<>0,K78/F78,""),"")),"") -> 1
A79: 8 | B79: Minyak | C79: Liter | D79: 60 | F79: =IF(E79<>"",D79*E79,"") | G79: 21500 | H79: =IF(G79<>"",D79*G79,"") -> 1290000 | I79: 23000 | J79: =IF(I79<>"",D79*I79,"") -> 1380000 | K79: =IF(J79<>"",IF(H79<>"",J79-H79,IF(F79<>"",J79-F79,"")),"") -> 90000 | L79: =IF(K79<>"",IF(H79<>"",IF(H79<>0,K79/H79,""),IF(F79<>"",IF(F79<>0,K79/F79,""),"")),"") -> 0.069767442
A80: 9 | B80: Pisang | C80: Pcs | D80: 2550 | F80: =IF(E80<>"",D80*E80,"") | G80: 1800 | H80: =IF(G80<>"",D80*G80,"") -> 4590000 | I80: 2000 | J80: =IF(I80<>"",D80*I80,"") -> 5100000 | K80: =IF(J80<>"",IF(H80<>"",J80-H80,IF(F80<>"",J80-F80,"")),"") -> 510000 | L80: =IF(K80<>"",IF(H80<>"",IF(H80<>0,K80/H80,""),IF(F80<>"",IF(F80<>0,K80/F80,""),"")),"") -> 0.11111111
A81: 10 | B81: Saus Tomat Sachet | C81: Pcs | D81: 2550 | F81: =IF(E81<>"",D81*E81,"") | G81: 240 | H81: =IF(G81<>"",D81*G81,"") -> 612000 | I81: 350 | J81: =IF(I81<>"",D81*I81,"") -> 892500 | K81: =IF(J81<>"",IF(H81<>"",J81-H81,IF(F81<>"",J81-F81,"")),"") -> 280500 | L81: =IF(K81<>"",IF(H81<>"",IF(H81<>0,K81/H81,""),IF(F81<>"",IF(F81<>0,K81/F81,""),"")),"") -> 0.45833333
A82: 11 | B82: Sawi Hijau | C82: Kg | D82: 20 | F82: =IF(E82<>"",D82*E82,"") | G82: 6000 | H82: =IF(G82<>"",D82*G82,"") -> 120000 | I82: 12000 | J82: =IF(I82<>"",D82*I82,"") -> 240000 | K82: =IF(J82<>"",IF(H82<>"",J82-H82,IF(F82<>"",J82-F82,"")),"") -> 120000 | L82: =IF(K82<>"",IF(H82<>"",IF(H82<>0,K82/H82,""),IF(F82<>"",IF(F82<>0,K82/F82,""),"")),"") -> 1
A83: 12 | B83: Tahu Pong | C83: Pcs | D83: 2600 | F83: =IF(E83<>"",D83*E83,"") | G83: 560 | H83: =IF(G83<>"",D83*G83,"") -> 1456000 | I83: 700 | J83: =IF(I83<>"",D83*I83,"") -> 1820000 | K83: =IF(J83<>"",IF(H83<>"",J83-H83,IF(F83<>"",J83-F83,"")),"") -> 364000 | L83: =IF(K83<>"",IF(H83<>"",IF(H83<>0,K83/H83,""),IF(F83<>"",IF(F83<>0,K83/F83,""),"")),"") -> 0.25
... A87: 16 | B87: Wortel | C87: Kg | D87: 40 | F87: =IF(E87<>"",D87*E87,"") | G87: 15000 | H87: =IF(G87<>"",D87*G87,"") -> 600000 | I87: 18000 | J87: =IF(I87<>"",D87*I87,"") -> 720000 | K87: =IF(J87<>"",IF(H87<>"",J87-H87,IF(F87<>"",J87-F87,"")),"") -> 120000 | L87: =IF(K87<>"",IF(H87<>"",IF(H87<>0,K87/H87,""),IF(F87<>"",IF(F87<>0,K87/F87,""),"")),"") -> 0.2
A88: SUBTOTAL 01 Jun 2026 | F88: =SUMIF(F72:F87,"<>",F72:F87) -> 0 | H88: =SUMIF(H72:H87,"<>",H72:H87) -> 16946175 | J88: =SUMIF(J72:J87,"<>",J72:J87) -> 19738000 | K88: =IF(J88<>"",IF(H88<>"",J88-H88,IF(F88<>"",J88-F88,"")),"") -> 2791825 | L88: =IF(K88<>"",IF(H88<>"",IF(H88<>0,K88/H88,""),IF(F88<>"",IF(F88<>0,K88/F88,""),"")),"") -> 0.16474662
A90: 📅 Tuesday, 02 June 2026
A91: No | B91: Nama Barang | C91: Satuan | D91: Qty | E91: 📊 ESTIMASI | G91: 🧾 REALISASI BELI | I91: 💰 PENJUALAN | K91: 📈 MARGIN | M91: Keterangan
A92: No | B92: Nama Barang | C92: Satuan | D92: Qty | E92: Est. Harga Beli (Rp) | F92: Total Estimasi (Rp) | G92: Harga Beli Nota (Rp) | H92: Total Beli Nota (Rp) | I92: Harga Jual (Rp) | J92: Total Jual (Rp) | K92: Margin (Rp) | L92: Margin (%) | M92: Keterangan
A93: 1 | B93: Bawang Bombay | C93: Kg | D93: 3 | E93: ='Daftar Harga'!D76 -> 115000 | F93: =IF(E93<>"",D93*E93,"") -> 345000 | G93: 28000 | H93: =IF(G93<>"",D93*G93,"") -> 84000 | I93: 35000 | J93: =IF(I93<>"",D93*I93,"") -> 105000 | K93: =IF(J93<>"",IF(H93<>"",J93-H93,IF(F93<>"",J93-F93,"")),"") -> 21000 | L93: =IF(K93<>"",IF(H93<>"",IF(H93<>0,K93/H93,""),IF(F93<>"",IF(F93<>0,K93/F93,""),"")),"") -> 0.25
A94: 2 | B94: Beras | C94: Kg | D94: 125 | E94: ='Daftar Harga'!D84 -> 34000 | F94: =IF(E94<>"",D94*E94,"") -> 4250000 | G94: 14500 | H94: =IF(G94<>"",D94*G94,"") -> 1812500 | I94: 15500 | J94: =IF(I94<>"",D94*I94,"") -> 1937500 | K94: =IF(J94<>"",IF(H94<>"",J94-H94,IF(F94<>"",J94-F94,"")),"") -> 125000 | L94: =IF(K94<>"",IF(H94<>"",IF(H94<>0,K94/H94,""),IF(F94<>"",IF(F94<>0,K94/F94,""),"")),"") -> 0.068965517
A95: 3 | B95: Daging Ayam Giling | C95: Kg | D95: 110 | E95: ='Daftar Harga'!D95 -> 23000 | F95: =IF(E95<>"",D95*E95,"") -> 2530000 | G95: 50500 | H95: =IF(G95<>"",D95*G95,"") -> 5555000 | I95: 60000 | J95: =IF(I95<>"",D95*I95,"") -> 6600000 | K95: =IF(J95<>"",IF(H95<>"",J95-H95,IF(F95<>"",J95-F95,"")),"") -> 1045000 | L95: =IF(K95<>"",IF(H95<>"",IF(H95<>0,K95/H95,""),IF(F95<>"",IF(F95<>0,K95/F95,""),"")),"") -> 0.18811881
A96: 4 | B96: Kacang Edamame | C96: Kg | D96: 100 | E96: ='Daftar Harga'!D114 | F96: =IF(E96<>"",D96*E96,"") | G96: 34000 | H96: =IF(G96<>"",D96*G96,"") -> 3400000 | I96: 36000 | J96: =IF(I96<>"",D96*I96,"") -> 3600000 | K96: =IF(J96<>"",IF(H96<>"",J96-H96,IF(F96<>"",J96-F96,"")),"") -> 200000 | L96: =IF(K96<>"",IF(H96<>"",IF(H96<>0,K96/H96,""),IF(F96<>"",IF(F96<>0,K96/F96,""),"")),"") -> 0.058823529
A97: 5 | B97: Keju Parut | C97: Kg | D97: 5 | E97: ='Daftar Harga'!D120 | F97: =IF(E97<>"",D97*E97,"") | G97: 140000 | H97: =IF(G97<>"",D97*G97,"") -> 700000 | I97: 145000 | J97: =IF(I97<>"",D97*I97,"") -> 725000 | K97: =IF(J97<>"",IF(H97<>"",J97-H97,IF(F97<>"",J97-F97,"")),"") -> 25000 | L97: =IF(K97<>"",IF(H97<>"",IF(H97<>0,K97/H97,""),IF(F97<>"",IF(F97<>0,K97/F97,""),"")),"") -> 0.035714286
A98: 6 | B98: Knorr | C98: Kg | D98: 2 | E98: ='Daftar Harga'!D126 | F98: =IF(E98<>"",D98*E98,"") | G98: 94000 | H98: =IF(G98<>"",D98*G98,"") -> 188000 | I98: 105000 | J98: =IF(I98<>"",D98*I98,"") -> 210000 | K98: =IF(J98<>"",IF(H98<>"",J98-H98,IF(F98<>"",J98-F98,"")),"") -> 22000 | L98: =IF(K98<>"",IF(H98<>"",IF(H98<>0,K98/H98,""),IF(F98<>"",IF(F98<>0,K98/F98,""),"")),"") -> 0.11702128
A99: 7 | B99: Lada Bubuk | C99: Kg | D99: 2 | E99: ='Daftar Harga'!D131 | F99: =IF(E99<>"",D99*E99,"") | G99: 140000 | H99: =IF(G99<>"",D99*G99,"") -> 280000 | I99: 190000 | J99: =IF(I99<>"",D99*I99,"") -> 380000 | K99: =IF(J99<>"",IF(H99<>"",J99-H99,IF(F99<>"",J99-F99,"")),"") -> 100000 | L99: =IF(K99<>"",IF(H99<>"",IF(H99<>0,K99/H99,""),IF(F99<>"",IF(F99<>0,K99/F99,""),"")),"") -> 0.35714286
A100: 8 | B100: Margarin | C100: Kg | D100: 5 | E100: ='Daftar Harga'!D137 | F100: =IF(E100<>"",D100*E100,"") | G100: 25000 | H100: =IF(G100<>"",D100*G100,"") -> 125000 | I100: 26000 | J100: =IF(I100<>"",D100*I100,"") -> 130000 | K100: =IF(J100<>"",IF(H100<>"",J100-H100,IF(F100<>"",J100-F100,"")),"") -> 5000 | L100: =IF(K100<>"",IF(H100<>"",IF(H100<>0,K100/H100,""),IF(F100<>"",IF(F100<>0,K100/F100,""),"")),"") -> 0.04
A101: 9 | B101: Melon | C101: Kg | D101: 256 | E101: ='Daftar Harga'!D138 | F101: =IF(E101<>"",D101*E101,"") | G101: 19500 | H101: =IF(G101<>"",D101*G101,"") -> 4992000 | I101: 21000 | J101: =IF(I101<>"",D101*I101,"") -> 5376000 | K101: =IF(J101<>"",IF(H101<>"",J101-H101,IF(F101<>"",J101-F101,"")),"") -> 384000 | L101: =IF(K101<>"",IF(H101<>"",IF(H101<>0,K101/H101,""),IF(F101<>"",IF(F101<>0,K101/F101,""),"")),"") -> 0.076923077
A102: 10 | B102: Minyak | C102: Liter | D102: 50 | E102: ='Daftar Harga'!D140 | F102: =IF(E102<>"",D102*E102,"") | G102: 21500 | H102: =IF(G102<>"",D102*G102,"") -> 1075000 | I102: 23000 | J102: =IF(I102<>"",D102*I102,"") -> 1150000 | K102: =IF(J102<>"",IF(H102<>"",J102-H102,IF(F102<>"",J102-F102,"")),"") -> 75000 | L102: =IF(K102<>"",IF(H102<>"",IF(H102<>0,K102/H102,""),IF(F102<>"",IF(F102<>0,K102/F102,""),"")),"") -> 0.069767442
A103: 11 | B103: Mix Vegetable | C103: Kg | D103: 60 | E103: ='Daftar Harga'!D142 | F103: =IF(E103<>"",D103*E103,"") | G103: 28000 | H103: =IF(G103<>"",D103*G103,"") -> 1680000 | I103: 34000 | J103: =IF(I103<>"",D103*I103,"") -> 2040000 | K103: =IF(J103<>"",IF(H103<>"",J103-H103,IF(F103<>"",J103-F103,"")),"") -> 360000 | L103: =IF(K103<>"",IF(H103<>"",IF(H103<>0,K103/H103,""),IF(F103<>"",IF(F103<>0,K103/F103,""),"")),"") -> 0.21428571
A104: 12 | B104: Saus Tomat Sachet | C104: Pcs | D104: 2000 | E104: ='Daftar Harga'!D153 | F104: =IF(E104<>"",D104*E104,"") | G104: 240 | H104: =IF(G104<>"",D104*G104,"") -> 480000 | I104: 280 | J104: =IF(I104<>"",D104*I104,"") -> 560000 | K104: =IF(J104<>"",IF(H104<>"",J104-H104,IF(F104<>"",J104-F104,"")),"") -> 80000 | L104: =IF(K104<>"",IF(H104<>"",IF(H104<>0,K104/H104,""),IF(F104<>"",IF(F104<>0,K104/F104,""),"")),"") -> 0.16666667
A105: 13 | B105: Smoke Beef | C105: Pack | D105: 20 | E105: 13000 | F105: =IF(E105<>"",D105*E105,"") -> 260000 | G105: 13000 | H105: =IF(G105<>"",D105*G105,"") -> 260000 | I105: 27500 | J105: =IF(I105<>"",D105*I105,"") -> 550000 | K105: =IF(J105<>"",IF(H105<>"",J105-H105,IF(F105<>"",J105-F105,"")),"") -> 290000 | L105: =IF(K105<>"",IF(H105<>"",IF(H105<>0,K105/H105,""),IF(F105<>"",IF(F105<>0,K105/F105,""),"")),"") -> 1.1153846
A106: 14 | B106: Telur Ayam | C106: Kg | D106: 30 | E106: ='Daftar Harga'!D168 | F106: =IF(E106<>"",D106*E106,"") | G106: 25500 | H106: =IF(G106<>"",D106*G106,"") -> 765000 | I106: 28000 | J106: =IF(I106<>"",D106*I106,"") -> 840000 | K106: =IF(J106<>"",IF(H106<>"",J106-H106,IF(F106<>"",J106-F106,"")),"") -> 75000 | L106: =IF(K106<>"",IF(H106<>"",IF(H106<>0,K106/H106,""),IF(F106<>"",IF(F106<>0,K106/F106,""),"")),"") -> 0.098039216
A107: 15 | B107: Tepung Roti | C107: Kg | D107: 40 | E107: ='Daftar Harga'!D173 | F107: =IF(E107<>"",D107*E107,"") | G107: 14000 | H107: =IF(G107<>"",D107*G107,"") -> 560000 | I107: 16000 | J107: =IF(I107<>"",D107*I107,"") -> 640000 | K107: =IF(J107<>"",IF(H107<>"",J107-H107,IF(F107<>"",J107-F107,"")),"") -> 80000 | L107: =IF(K107<>"",IF(H107<>"",IF(H107<>0,K107/H107,""),IF(F107<>"",IF(F107<>0,K107/F107,""),"")),"") -> 0.14285714
A108: SUBTOTAL 02 Jun 2026 | F108: =SUMIF(F93:F107,"<>",F93:F107) -> 7385000 | H108: =SUMIF(H93:H107,"<>",H93:H107) -> 21956500 | J108: =SUMIF(J93:J107,"<>",J93:J107) -> 24843500 | K108: =IF(J108<>"",IF(H108<>"",J108-H108,IF(F108<>"",J108-F108,"")),"") -> 2887000 | L108: =IF(K108<>"",IF(H108<>"",IF(H108<>0,K108/H108,""),IF(F108<>"",IF(F108<>0,K108/F108,""),"")),"") -> 0.13148726
...

Sheet Invoice OPS B01
A1: 🧾 DRAFT INVOICE — BAKUNG 01
A2: Periode: Mei-Juni 2026 | 🟢 Hijau = linked Daftar Harga | 🔵 Biru = input manual (isi setelah nota datang)
A3: Kolom G (Harga Beli Nota) dikosongkan — isi saat barang tiba. Margin: pakai Nota jika ada, fallback ke Estimasi.
A4: 📅 Sunday, 24 May 2026
A5: No | B5: Nama Barang | C5: Satuan | D5: Qty | E5: 📊 ESTIMASI | G5: 🧾 REALISASI BELI | I5: 💰 PENJUALAN | K5: 📈 MARGIN | M5: Keterangan
A6: No | B6: Nama Barang | C6: Satuan | D6: Qty | E6: Est. Harga Beli (Rp) | F6: Total Estimasi (Rp) | G6: Harga Beli Nota (Rp) | H6: Total Beli Nota (Rp) | I6: Harga Jual (Rp) | J6: Total Jual (Rp) | K6: Margin (Rp) | L6: Margin (%) | M6: Keterangan
A7: 1 | B7: Sarung Tangan Finnil | C7: Pack | D7: 10 | F7: =IF(E7<>"",D7*E7,"") | G7: 65000 | H7: =IF(G7<>"",D7*G7,"") -> 650000 | I7: 75000 | J7: =IF(I7<>"",D7*I7,"") -> 750000 | K7: =IF(J7<>"",IF(H7<>"",J7-H7,IF(F7<>"",J7-F7,"")),"") -> 100000 | L7: =IF(K7<>"",IF(H7<>"",IF(H7<>0,K7/H7,""),IF(F7<>"",IF(F7<>0,K7/F7,""),"")),"") -> 0.15384615
A8: 2 | B8: Plastik Es Wayang | C8: Pack | D8: 40 | F8: =IF(E8<>"",D8*E8,"") | G8: 13000 | H8: =IF(G8<>"",D8*G8,"") -> 520000 | I8: 17000 | J8: =IF(I8<>"",D8*I8,"") -> 680000 | K8: =IF(J8<>"",IF(H8<>"",J8-H8,IF(F8<>"",J8-F8,"")),"") -> 160000 | L8: =IF(K8<>"",IF(H8<>"",IF(H8<>0,K8/H8,""),IF(F8<>"",IF(F8<>0,K8/F8,""),"")),"") -> 0.30769231
A9: 3 | B9: Gas 50Kg | C9: Tabung | D9: 2 | F9: =IF(E9<>"",D9*E9,"") | G9: 1125000 | H9: =IF(G9<>"",D9*G9,"") -> 2250000 | I9: 1250000 | J9: =IF(I9<>"",D9*I9,"") -> 2500000 | K9: =IF(J9<>"",IF(H9<>"",J9-H9,IF(F9<>"",J9-F9,"")),"") -> 250000 | L9: =IF(K9<>"",IF(H9<>"",IF(H9<>0,K9/H9,""),IF(F9<>"",IF(F9<>0,K9/F9,""),"")),"") -> 0.11111111
A10: 4 | B10: Payung | C10: Pcs | D10: 5 | F10: =IF(E10<>"",D10*E10,"") | G10: 25500 | H10: =IF(G10<>"",D10*G10,"") -> 127500 | I10: 35000 | J10: =IF(I10<>"",D10*I10,"") -> 175000 | K10: =IF(J10<>"",IF(H10<>"",J10-H10,IF(F10<>"",J10-F10,"")),"") -> 47500 | L10: =IF(K10<>"",IF(H10<>"",IF(H10<>0,K10/H10,""),IF(F10<>"",IF(F10<>0,K10/F10,""),"")),"") -> 0.37254902
A11: 5 | B11: Kaporit Bubuk | C11: Ember | D11: 1 | F11: =IF(E11<>"",D11*E11,"") | G11: 470000 | H11: =IF(G11<>"",D11*G11,"") -> 470000 | I11: 500000 | J11: =IF(I11<>"",D11*I11,"") -> 500000 | K11: =IF(J11<>"",IF(H11<>"",J11-H11,IF(F11<>"",J11-F11,"")),"") -> 30000 | L11: =IF(K11<>"",IF(H11<>"",IF(H11<>0,K11/H11,""),IF(F11<>"",IF(F11<>0,K11/F11,""),"")),"") -> 0.063829787
A12: 6 | B12: Baygon | C12: Pcs | D12: 5 | F12: =IF(E12<>"",D12*E12,"") | G12: 34000 | H12: =IF(G12<>"",D12*G12,"") -> 170000 | I12: 38000 | J12: =IF(I12<>"",D12*I12,"") -> 190000 | K12: =IF(J12<>"",IF(H12<>"",J12-H12,IF(F12<>"",J12-F12,"")),"") -> 20000 | L12: =IF(K12<>"",IF(H12<>"",IF(H12<>0,K12/H12,""),IF(F12<>"",IF(F12<>0,K12/F12,""),"")),"") -> 0.11764706
A13: 7 | B13: Sabun Cuci Piring | C13: Drigen | D13: 10 | F13: =IF(E13<>"",D13*E13,"") | G13: 65000 | H13: =IF(G13<>"",D13*G13,"") -> 650000 | I13: 75000 | J13: =IF(I13<>"",D13*I13,"") -> 750000 | K13: =IF(J13<>"",IF(H13<>"",J13-H13,IF(F13<>"",J13-F13,"")),"") -> 100000 | L13: =IF(K13<>"",IF(H13<>"",IF(H13<>0,K13/H13,""),IF(F13<>"",IF(F13<>0,K13/F13,""),"")),"") -> 0.15384615
A14: SUBTOTAL 25 May 2026 | F14: =SUMIF(F7:F9,"<>",F7:F9) -> 0 | H14: =SUMIF(H7:H13,"<>",H7:H13) -> 4837500 | J14: =SUMIF(J7:J13,"<>",J7:J13) -> 5545000 | K14: =IF(J14<>"",IF(H14<>"",J14-H14,IF(F14<>"",J14-F14,"")),"") -> 707500 | L14: =IF(K14<>"",IF(H14<>"",IF(H14<>0,K14/H14,""),IF(F14<>"",IF(F14<>0,K14/F14,""),"")),"") -> 0.14625323
A17: 📅 Friday, 29 May 2026
A18: No | B18: Nama Barang | C18: Satuan | D18: Qty | E18: 📊 ESTIMASI | G18: 🧾 REALISASI BELI | I18: 💰 PENJUALAN | K18: 📈 MARGIN | M18: Keterangan
A19: No | B19: Nama Barang | C19: Satuan | D19: Qty | E19: Est. Harga Beli (Rp) | F19: Total Estimasi (Rp) | G19: Harga Beli Nota (Rp) | H19: Total Beli Nota (Rp) | I19: Harga Jual (Rp) | J19: Total Jual (Rp) | K19: Margin (Rp) | L19: Margin (%) | M19: Keterangan
A20: 1 | B20: Ember | C20: Pcs | D20: 4 | G20: 45000 | H20: =IF(G20<>"",D20*G20,"") -> 180000 | I20: 60000 | J20: =IF(I20<>"",D20*I20,"") -> 240000 | K20: =IF(J20<>"",IF(H20<>"",J20-H20,IF(F20<>"",J20-F20,"")),"") -> 60000 | L20: =IF(K20<>"",IF(H20<>"",IF(H20<>0,K20/H20,""),IF(F20<>"",IF(F20<>0,K20/F20,""),"")),"") -> 0.33333333
A21: 2 | B21: Gelas Plastik | C21: Lusin | D21: 1 | G21: 78000 | H21: =IF(G21<>"",D21*G21,"") -> 78000 | I21: 320000 | J21: =IF(I21<>"",D21*I21,"") -> 320000 | K21: =IF(J21<>"",IF(H21<>"",J21-H21,IF(F21<>"",J21-F21,"")),"") -> 242000 | L21: =IF(K21<>"",IF(H21<>"",IF(H21<>0,K21/H21,""),IF(F21<>"",IF(F21<>0,K21/F21,""),"")),"") -> 3.1025641
A22: 3 | B22: Gas 50Kg | C22: Tabung | D22: 1 | F22: =IF(E22<>"",D22*E22,"") | G22: 1125000 | H22: =IF(G22<>"",D22*G22,"") -> 1125000 | I22: 1250000 | J22: =IF(I22<>"",D22*I22,"") -> 1250000 | K22: =IF(J22<>"",IF(H22<>"",J22-H22,IF(F22<>"",J22-F22,"")),"") -> 125000 | L22: =IF(K22<>"",IF(H22<>"",IF(H22<>0,K22/H22,""),IF(F22<>"",IF(F22<>0,K22/F22,""),"")),"") -> 0.11111111
A23: SUBTOTAL 25 May 2026 | F23: =SUMIF(F20:F22,"<>",F20:F22) -> 0 | H23: =SUMIF(H20:H22,"<>",H20:H22) -> 1383000 | J23: =SUMIF(J20:J22,"<>",J20:J22) -> 1810000 | K23: =IF(J23<>"",IF(H23<>"",J23-H23,IF(F23<>"",J23-F23,"")),"") -> 427000 | L23: =IF(K23<>"",IF(H23<>"",IF(H23<>0,K23/H23,""),IF(F23<>"",IF(F23<>0,K23/F23,""),"")),"") -> 0.3087491
A25: 📅 Wednesday, 03 June 2026
A26: No | B26: Nama Barang | C26: Satuan | D26: Qty | E26: 📊 ESTIMASI | G26: 🧾 REALISASI BELI | I26: 💰 PENJUALAN | K26: 📈 MARGIN | M26: Keterangan
A27: No | B27: Nama Barang | C27: Satuan | D27: Qty | E27: Est. Harga Beli (Rp) | F27: Total Estimasi (Rp) | G27: Harga Beli Nota (Rp) | H27: Total Beli Nota (Rp) | I27: Harga Jual (Rp) | J27: Total Jual (Rp) | K27: Margin (Rp) | L27: Margin (%) | M27: Keterangan
A28: 1 | B28: Sarung Tangan Finnil | C28: Pack | D28: 10 | F28: =IF(E28<>"",D28*E28,"") | G28: 85000 | H28: =IF(G28<>"",D28*G28,"") -> 850000 | I28: 85000 | J28: =IF(I28<>"",D28*I28,"") -> 850000 | K28: =IF(J28<>"",IF(H28<>"",J28-H28,IF(F28<>"",J28-F28,"")),"") -> 0 | L28: =IF(K28<>"",IF(H28<>"",IF(H28<>0,K28/H28,""),IF(F28<>"",IF(F28<>0,K28/F28,""),"")),"") -> 0
A29: 2 | B29: Plastik Es wayang | C29: Pack | D29: 40 | F29: =IF(E29<>"",D29*E29,"") | G29: 9875 | H29: =IF(G29<>"",D29*G29,"") -> 395000 | I29: 17500 | J29: =IF(I29<>"",D29*I29,"") -> 700000 | K29: =IF(J29<>"",IF(H29<>"",J29-H29,IF(F29<>"",J29-F29,"")),"") -> 305000 | L29: =IF(K29<>"",IF(H29<>"",IF(H29<>0,K29/H29,""),IF(F29<>"",IF(F29<>0,K29/F29,""),"")),"") -> 0.7721519
A30: 3 | B30: Gas 50kg | C30: Tabung | D30: 2 | F30: =IF(E30<>"",D30*E30,"") | G30: 1125000 | H30: =IF(G30<>"",D30*G30,"") -> 2250000 | I30: 1250000 | J30: =IF(I30<>"",D30*I30,"") -> 2500000 | K30: =IF(J30<>"",IF(H30<>"",J30-H30,IF(F30<>"",J30-F30,"")),"") -> 250000 | L30: =IF(K30<>"",IF(H30<>"",IF(H30<>0,K30/H30,""),IF(F30<>"",IF(F30<>0,K30/F30,""),"")),"") -> 0.11111111
A31: 4 | B31: Sushi Roll | C31: Pcs | D31: 10 | F31: =IF(E31<>"",D31*E31,"") | G31: 27000 | H31: =IF(G31<>"",D31*G31,"") -> 270000 | I31: 30000 | J31: =IF(I31<>"",D31*I31,"") -> 300000 | K31: =IF(J31<>"",IF(H31<>"",J31-H31,IF(F31<>"",J31-F31,"")),"") -> 30000 | L31: =IF(K31<>"",IF(H31<>"",IF(H31<>0,K31/H31,""),IF(F31<>"",IF(F31<>0,K31/F31,""),"")),"") -> 0.11111111
A32: 5 | B32: MieSedap Goreng | C32: Dud | D32: 1 | F32: =IF(E32<>"",D32*E32,"") | G32: 124000 | H32: =IF(G32<>"",D32*G32,"") -> 124000 | I32: 150000 | J32: =IF(I32<>"",D32*I32,"") -> 150000 | K32: =IF(J32<>"",IF(H32<>"",J32-H32,IF(F32<>"",J32-F32,"")),"") -> 26000 | L32: =IF(K32<>"",IF(H32<>"",IF(H32<>0,K32/H32,""),IF(F32<>"",IF(F32<>0,K32/F32,""),"")),"") -> 0.20967742
A33: 6 | B33: Kopi Hitam Kapal api + gula | C33: Dus | D33: 1 | F33: =IF(E33<>"",D33*E33,"") | G33: 225000 | H33: =IF(G33<>"",D33*G33,"") -> 225000 | I33: 250000 | J33: =IF(I33<>"",D33*I33,"") -> 250000 | K33: =IF(J33<>"",IF(H33<>"",J33-H33,IF(F33<>"",J33-F33,"")),"") -> 25000 | L33: =IF(K33<>"",IF(H33<>"",IF(H33<>0,K33/H33,""),IF(F33<>"",IF(F33<>0,K33/F33,""),"")),"") -> 0.11111111
A34: 7 | B34: Gooday Merah | C34: Dus | D34: 1 | F34: =IF(E34<>"",D34*E34,"") | G34: 230000 | H34: =IF(G34<>"",D34*G34,"") -> 230000 | I34: 265000 | J34: =IF(I34<>"",D34*I34,"") -> 265000 | K34: =IF(J34<>"",IF(H34<>"",J34-H34,IF(F34<>"",J34-F34,"")),"") -> 35000 | L34: =IF(K34<>"",IF(H34<>"",IF(H34<>0,K34/H34,""),IF(F34<>"",IF(F34<>0,K34/F34,""),"")),"") -> 0.15217391
A35: 8 | B35: Gooday Freeze | C35: Dus | D35: 1 | F35: =IF(E35<>"",D35*E35,"") | G35: 302000 | H35: =IF(G35<>"",D35*G35,"") -> 302000 | I35: 330000 | J35: =IF(I35<>"",D35*I35,"") -> 330000 | K35: =IF(J35<>"",IF(H35<>"",J35-H35,IF(F35<>"",J35-F35,"")),"") -> 28000 | L35: =IF(K35<>"",IF(H35<>"",IF(H35<>0,K35/H35,""),IF(F35<>"",IF(F35<>0,K35/F35,""),"")),"") -> 0.092715232
A36: 9 | B36: Galon Aqua | C36: Galon | D36: 75 | F36: =IF(E36<>"",D36*E36,"") | G36: 19200 | H36: =IF(G36<>"",D36*G36,"") -> 1440000 | I36: 22500 | J36: =IF(I36<>"",D36*I36,"") -> 1687500 | K36: =IF(J36<>"",IF(H36<>"",J36-H36,IF(F36<>"",J36-F36,"")),"") -> 247500 | L36: =IF(K36<>"",IF(H36<>"",IF(H36<>0,K36/H36,""),IF(F36<>"",IF(F36<>0,K36/F36,""),"")),"") -> 0.171875
A37: 10 | B37: Sabun Cuci Piring | C37: Drigen | D37: 15 | F37: =IF(E37<>"",D37*E37,"") | G37: 65000 | H37: =IF(G37<>"",D37*G37,"") -> 975000 | I37: 75000 | J37: =IF(I37<>"",D37*I37,"") -> 1125000 | K37: =IF(J37<>"",IF(H37<>"",J37-H37,IF(F37<>"",J37-F37,"")),"") -> 150000 | L37: =IF(K37<>"",IF(H37<>"",IF(H37<>0,K37/H37,""),IF(F37<>"",IF(F37<>0,K37/F37,""),"")),"") -> 0.15384615
A38: 11 | B38: Thin Wall 200ml Bulat | C38: Pcs | D38: 2550 | F38: =IF(E38<>"",D38*E38,"") | G38: 540 | H38: =IF(G38<>"",D38*G38,"") -> 1377000 | I38: 750 | J38: =IF(I38<>"",D38*I38,"") -> 1912500 | K38: =IF(J38<>"",IF(H38<>"",J38-H38,IF(F38<>"",J38-F38,"")),"") -> 535500 | L38: =IF(K38<>"",IF(H38<>"",IF(H38<>0,K38/H38,""),IF(F38<>"",IF(F38<>0,K38/F38,""),"")),"") -> 0.38888889
A39: 12 | B39: Baygon | C39: Pcs | D39: 5 | F39: =IF(E39<>"",D39*E39,"") | G39: 32500 | H39: =IF(G39<>"",D39*G39,"") -> 162500 | I39: 37500 | J39: =IF(I39<>"",D39*I39,"") -> 187500 | K39: =IF(J39<>"",IF(H39<>"",J39-H39,IF(F39<>"",J39-F39,"")),"") -> 25000 | L39: =IF(K39<>"",IF(H39<>"",IF(H39<>0,K39/H39,""),IF(F39<>"",IF(F39<>0,K39/F39,""),"")),"") -> 0.15384615
A40: 13 | B40: Plester | C40: Pack | D40: 10 | G40: 35000 | H40: =IF(G40<>"",D40*G40,"") -> 350000 | I40: 45000 | J40: =IF(I40<>"",D40*I40,"") -> 450000
A41: 14 | B41: Karbol Untuk Toilet | C41: Pack | D41: 10 | G41: 27000 | H41: =IF(G41<>"",D41*G41,"") -> 270000 | I41: 35000 | J41: =IF(I41<>"",D41*I41,"") -> 350000
A42: 15 | B42: Gayung | C42: Pcs | D42: 5 | F42: =IF(E42<>"",D42*E42,"") | G42: 10000 | H42: =IF(G42<>"",D42*G42,"") -> 50000 | I42: 15000 | J42: =IF(I42<>"",D42*I42,"") -> 75000 | K42: =IF(J42<>"",IF(H42<>"",J42-H42,IF(F42<>"",J42-F42,"")),"") -> 25000 | L42: =IF(K42<>"",IF(H42<>"",IF(H42<>0,K42/H42,""),IF(F42<>"",IF(F42<>0,K42/F42,""),"")),"") -> 0.5
A43: 16 | B43: Thinwall Saos | C43: Pcs | D43: 2600 | F43: =IF(E43<>"",D43*E43,"") | G43: 225 | H43: =IF(G43<>"",D43*G43,"") -> 585000 | I43: 350 | J43: =IF(I43<>"",D43*I43,"") -> 910000 | K43: =IF(J43<>"",IF(H43<>"",J43-H43,IF(F43<>"",J43-F43,"")),"") -> 325000 | L43: =IF(K43<>"",IF(H43<>"",IF(H43<>0,K43/H43,""),IF(F43<>"",IF(F43<>0,K43/F43,""),"")),"") -> 0.55555556
A44: SUBTOTAL 3 JUN | F44: =SUMIF(F28:F43,"<>",F28:F43) -> 0 | H44: =SUMIF(H28:H43,"<>",H28:H43) -> 9855500 | J44: =SUMIF(J28:J43,"<>",J28:J43) -> 12042500 | K44: =IF(J44<>"",IF(H44<>"",J44-H44,IF(F44<>"",J44-F44,"")),"") -> 2187000 | L44: =IF(K44<>"",IF(H44<>"",IF(H44<>0,K44/H44,""),IF(F44<>"",IF(F44<>0,K44/F44,""),"")),"") -> 0.22190655
A46: 📅 Friday, 05 June 2026
A47: No | B47: Nama Barang | C47: Satuan | D47: Qty | E47: 📊 ESTIMASI | G47: 🧾 REALISASI BELI | I47: 💰 PENJUALAN | K47: 📈 MARGIN | M47: Keterangan
A48: No | B48: Nama Barang | C48: Satuan | D48: Qty | E48: Est. Harga Beli (Rp) | F48: Total Estimasi (Rp) | G48: Harga Beli Nota (Rp) | H48: Total Beli Nota (Rp) | I48: Harga Jual (Rp) | J48: Total Jual (Rp) | K48: Margin (Rp) | L48: Margin (%) | M48: Keterangan
A49: 1 | B49: Sewa Traga | C49: unit | D49: 1 | F49: =IF(E49<>"",D49*E49,"") | G49: 3272000 | H49: =IF(G49<>"",D49*G49,"") -> 3272000 | I49: 3272000 | J49: =IF(I49<>"",D49*I49,"") -> 3272000 | K49: =IF(J49<>"",IF(H49<>"",J49-H49,IF(F49<>"",J49-F49,"")),"") -> 0 | L49: =IF(K49<>"",IF(H49<>"",IF(H49<>0,K49/H49,""),IF(F49<>"",IF(F49<>0,K49/F49,""),"")),"") -> 0
A50: 2 | B50: Sewa Traga | C50: unit | D50: 1 | F50: =IF(E50<>"",D50*E50,"") | G50: 3272000 | H50: =IF(G50<>"",D50*G50,"") -> 3272000 | I50: 3272000 | J50: =IF(I50<>"",D50*I50,"") -> 3272000 | K50: =IF(J50<>"",IF(H50<>"",J50-H50,IF(F50<>"",J50-F50,"")),"") -> 0 | L50: =IF(K50<>"",IF(H50<>"",IF(H50<>0,K50/H50,""),IF(F50<>"",IF(F50<>0,K50/F50,""),"")),"") -> 0
F51: =SUMIF(F49:F50,"<>",F49:F50) -> 0 | H51: =SUMIF(H49:H50,"<>",H49:H50) -> 6544000 | J51: =SUMIF(J49:J50,"<>",J49:J50) -> 6544000 | K51: =IF(J51<>"",IF(H51<>"",J51-H51,IF(F51<>"",J51-F51,"")),"") -> 0 | L51: =IF(K51<>"",IF(H51<>"",IF(H51<>0,K51/H51,""),IF(F51<>"",IF(F51<>0,K51/F51,""),"")),"") -> 0
A53: 📅 Friday, 05 June 2026
A54: No | B54: Nama Barang | C54: Satuan | D54: Qty | E54: 📊 ESTIMASI | G54: 🧾 REALISASI BELI | I54: 💰 PENJUALAN | K54: 📈 MARGIN | M54: Keterangan
A55: No | B55: Nama Barang | C55: Satuan | D55: Qty | E55: Est. Harga Beli (Rp) | F55: Total Estimasi (Rp) | G55: Harga Beli Nota (Rp) | H55: Total Beli Nota (Rp) | I55: Harga Jual (Rp) | J55: Total Jual (Rp) | K55: Margin (Rp) | L55: Margin (%) | M55: Keterangan
A56: 1 | B56: Gas 50kg | C56: Tabung | D56: 2 | F56: =IF(E56<>"",D56*E56,"") | G56: 1125000 | H56: =IF(G56<>"",D56*G56,"") -> 2250000 | I56: 1250000 | J56: =IF(I56<>"",D56*I56,"") -> 2500000 | K56: =IF(J56<>"",IF(H56<>"",J56-H56,IF(F56<>"",J56-F56,"")),"") -> 250000 | L56: =IF(K56<>"",IF(H56<>"",IF(H56<>0,K56/H56,""),IF(F56<>"",IF(F56<>0,K56/F56,""),"")),"") -> 0.11111111
A57: 2 | B57: Map Plastik | C57: Pcs | D57: 20 | F57: =IF(E57<>"",D57*E57,"") | G57: 3500 | H57: =IF(G57<>"",D57*G57,"") -> 70000 | I57: 10000 | J57: =IF(I57<>"",D57*I57,"") -> 200000 | K57: =IF(J57<>"",IF(H57<>"",J57-H57,IF(F57<>"",J57-F57,"")),"") -> 130000 | L57: =IF(K57<>"",IF(H57<>"",IF(H57<>0,K57/H57,""),IF(F57<>"",IF(F57<>0,K57/F57,""),"")),"") -> 1.8571429
A58: SUBTOTAL 5 JUN | F58: =SUMIF(F56:F57,"<>",F56:F57) -> 0 | H58: =SUMIF(H56:H57,"<>",H56:H57) -> 2320000 | J58: =SUMIF(J56:J57,"<>",J56:J57) -> 2700000 | K58: =IF(J58<>"",IF(H58<>"",J58-H58,IF(F58<>"",J58-F58,"")),"") -> 380000 | L58: =IF(K58<>"",IF(H58<>"",IF(H58<>0,K58/H58,""),IF(F58<>"",IF(F58<>0,K58/F58,""),"")),"") -> 0.1637931
A60: 📅 Thursday, 11 June 2026
A61: No | B61: Nama Barang | C61: Satuan | D61: Qty | E61: 📊 ESTIMASI | G61: 🧾 REALISASI BELI | I61: 💰 PENJUALAN | K61: 📈 MARGIN | M61: Keterangan
A62: No | B62: Nama Barang | C62: Satuan | D62: Qty | E62: Est. Harga Beli (Rp) | F62: Total Estimasi (Rp) | G62: Harga Beli Nota (Rp) | H62: Total Beli Nota (Rp) | I62: Harga Jual (Rp) | J62: Total Jual (Rp) | K62: Margin (Rp) | L62: Margin (%) | M62: Keterangan
A63: 1 | B63: Sarung Tangan Finnil | C63: Pack | D63: 10 | F63: =IF(E63<>"",D63*E63,"") | G63: 70000 | H63: =IF(G63<>"",D63*G63,"") -> 700000 | I63: 85000 | J63: =IF(I63<>"",D63*I63,"") -> 850000 | K63: =IF(J63<>"",IF(H63<>"",J63-H63,IF(F63<>"",J63-F63,"")),"") -> 150000 | L63: =IF(K63<>"",IF(H63<>"",IF(H63<>0,K63/H63,""),IF(F63<>"",IF(F63<>0,K63/F63,""),"")),"") -> 0.21428571
A64: 2 | B64: Plastik Es wayang | C64: Pack | D64: 40 | F64: =IF(E64<>"",D64*E64,"") | G64: 13000 | H64: =IF(G64<>"",D64*G64,"") -> 520000 | I64: 17500 | J64: =IF(I64<>"",D64*I64,"") -> 700000 | K64: =IF(J64<>"",IF(H64<>"",J64-H64,IF(F64<>"",J64-F64,"")),"") -> 180000 | L64: =IF(K64<>"",IF(H64<>"",IF(H64<>0,K64/H64,""),IF(F64<>"",IF(F64<>0,K64/F64,""),"")),"") -> 0.34615385
A65: 3 | B65: Tisu | C65: Pack | D65: 10 | F65: =IF(E65<>"",D65*E65,"") | G65: 10000 | H65: =IF(G65<>"",D65*G65,"") -> 100000 | I65: 12000 | J65: =IF(I65<>"",D65*I65,"") -> 120000 | K65: =IF(J65<>"",IF(H65<>"",J65-H65,IF(F65<>"",J65-F65,"")),"") -> 20000 | L65: =IF(K65<>"",IF(H65<>"",IF(H65<>0,K65/H65,""),IF(F65<>"",IF(F65<>0,K65/F65,""),"")),"") -> 0.2
A66: 4 | B66: Thinwall 500 ml | C66: Pcs | D66: 2550 | F66: =IF(E66<>"",D66*E66,"") | G66: 1060 | H66: =IF(G66<>"",D66*G66,"") -> 2703000 | I66: 1500 | J66: =IF(I66<>"",D66*I66,"") -> 3825000 | K66: =IF(J66<>"",IF(H66<>"",J66-H66,IF(F66<>"",J66-F66,"")),"") -> 1122000 | L66: =IF(K66<>"",IF(H66<>"",IF(H66<>0,K66/H66,""),IF(F66<>"",IF(F66<>0,K66/F66,""),"")),"") -> 0.41509434
A67: 5 | B67: Baygon | C67: Pcs | D67: 5 | F67: =IF(E67<>"",D67*E67,"") | G67: 43000 | H67: =IF(G67<>"",D67*G67,"") -> 215000 | I67: 40000 | J67: =IF(I67<>"",D67*I67,"") -> 200000 | K67: =IF(J67<>"",IF(H67<>"",J67-H67,IF(F67<>"",J67-F67,"")),"") -> -15000 | L67: =IF(K67<>"",IF(H67<>"",IF(H67<>0,K67/H67,""),IF(F67<>"",IF(F67<>0,K67/F67,""),"")),"") -> -0.069767442
A68: 6 | B68: Sabun Cuci Piring | C68: Drigen | D68: 35 | F68: =IF(E68<>"",D68*E68,"") | G68: 65000 | H68: =IF(G68<>"",D68*G68,"") -> 2275000 | I68: 75000 | J68: =IF(I68<>"",D68*I68,"") -> 2625000 | K68: =IF(J68<>"",IF(H68<>"",J68-H68,IF(F68<>"",J68-F68,"")),"") -> 350000 | L68: =IF(K68<>"",IF(H68<>"",IF(H68<>0,K68/H68,""),IF(F68<>"",IF(F68<>0,K68/F68,""),"")),"") -> 0.15384615
A69: 7 | B69: Gelas Ujur 2000 Ml | C69: Pcs | D69: 3 | F69: =IF(E69<>"",D69*E69,"") | G69: 15000 | H69: =IF(G69<>"",D69*G69,"") -> 45000 | I69: 25000 | J69: =IF(I69<>"",D69*I69,"") -> 75000 | K69: =IF(J69<>"",IF(H69<>"",J69-H69,IF(F69<>"",J69-F69,"")),"") -> 30000 | L69: =IF(K69<>"",IF(H69<>"",IF(H69<>0,K69/H69,""),IF(F69<>"",IF(F69<>0,K69/F69,""),"")),"") -> 0.66666667
A70: 8 | B70: Gelas Ukur 1000 Ml | C70: Pcs | D70: 2 | F70: =IF(E70<>"",D70*E70,"") | G70: 10000 | H70: =IF(G70<>"",D70*G70,"") -> 20000 | I70: 20000 | J70: =IF(I70<>"",D70*I70,"") -> 40000 | K70: =IF(J70<>"",IF(H70<>"",J70-H70,IF(F70<>"",J70-F70,"")),"") -> 20000 | L70: =IF(K70<>"",IF(H70<>"",IF(H70<>0,K70/H70,""),IF(F70<>"",IF(F70<>0,K70/F70,""),"")),"") -> 1
A71: 9 | B71: Kaporit | C71: Ember | D71: 1 | F71: =IF(E71<>"",D71*E71,"") | G71: 470000 | H71: =IF(G71<>"",D71*G71,"") -> 470000 | I71: 550000 | J71: =IF(I71<>"",D71*I71,"") -> 550000 | K71: =IF(J71<>"",IF(H71<>"",J71-H71,IF(F71<>"",J71-F71,"")),"") -> 80000 | L71: =IF(K71<>"",IF(H71<>"",IF(H71<>0,K71/H71,""),IF(F71<>"",IF(F71<>0,K71/F71,""),"")),"") -> 0.17021277
A72: 10 | B72: Tali Rapia Hitam | C72: Roll Besar | D72: 60.7 | F72: =IF(E72<>"",D72*E72,"") | G72: 14500 | H72: =IF(G72<>"",D72*G72,"") -> 880150 | I72: 20000 | J72: =IF(I72<>"",D72*I72,"") -> 1214000 | K72: =IF(J72<>"",IF(H72<>"",J72-H72,IF(F72<>"",J72-F72,"")),"") -> 333850 | L72: =IF(K72<>"",IF(H72<>"",IF(H72<>0,K72/H72,""),IF(F72<>"",IF(F72<>0,K72/F72,""),"")),"") -> 0.37931034
A73: 11 | B73: Tali Rapia Pink | C73: Roll Sedang | D73: 14.9 | F73: =IF(E73<>"",D73*E73,"") | G73: 19000 | H73: =IF(G73<>"",D73*G73,"") -> 283100 | I73: 30000 | J73: =IF(I73<>"",D73*I73,"") -> 447000 | K73: =IF(J73<>"",IF(H73<>"",J73-H73,IF(F73<>"",J73-F73,"")),"") -> 163900 | L73: =IF(K73<>"",IF(H73<>"",IF(H73<>0,K73/H73,""),IF(F73<>"",IF(F73<>0,K73/F73,""),"")),"") -> 0.57894737
A74: 12 | B74: Karet | C74: Bungkus | D74: 9 | F74: =IF(E74<>"",D74*E74,"") | G74: 27000 | H74: =IF(G74<>"",D74*G74,"") -> 243000 | I74: 35000 | J74: =IF(I74<>"",D74*I74,"") -> 315000 | K74: =IF(J74<>"",IF(H74<>"",J74-H74,IF(F74<>"",J74-F74,"")),"") -> 72000 | L74: =IF(K74<>"",IF(H74<>"",IF(H74<>0,K74/H74,""),IF(F74<>"",IF(F74<>0,K74/F74,""),"")),"") -> 0.2962963
... A76: 14 | B76: Soda Api | C76: Karung | D76: 1 | F76: =IF(E76<>"",D76*E76,"") | G76: 22000 | H76: =IF(G76<>"",D76*G76,"") -> 22000 | I76: 650000 | J76: =IF(I76<>"",D76*I76,"") -> 650000 | K76: =IF(J76<>"",IF(H76<>"",J76-H76,IF(F76<>"",J76-F76,"")),"") -> 628000 | L76: =IF(K76<>"",IF(H76<>"",IF(H76<>0,K76/H76,""),IF(F76<>"",IF(F76<>0,K76/F76,""),"")),"") -> 28.545455
A77: SUBTOTAL 11 JUN | F77: =SUMIF(F63:F76,"<>",F63:F76) -> 0 | H77: =SUMIF(H63:H76,"<>",H63:H76) -> 10312250 | J77: =SUMIF(J63:J76,"<>",J63:J76) -> 13651000 | K77: =IF(J77<>"",IF(H77<>"",J77-H77,IF(F77<>"",J77-F77,"")),"") -> 3338750 | L77: =IF(K77<>"",IF(H77<>"",IF(H77<>0,K77/H77,""),IF(F77<>"",IF(F77<>0,K77/F77,""),"")),"") -> 0.32376542
A79: 📅 Tuesday, 16 June 2026
A80: No | B80: Nama Barang | C80: Satuan | D80: Qty | E80: 📊 ESTIMASI | G80: 🧾 REALISASI BELI | I80: 💰 PENJUALAN | K80: 📈 MARGIN | M80: Keterangan
A81: No | B81: Nama Barang | C81: Satuan | D81: Qty | E81: Est. Harga Beli (Rp) | F81: Total Estimasi (Rp) | G81: Harga Beli Nota (Rp) | H81: Total Beli Nota (Rp) | I81: Harga Jual (Rp) | J81: Total Jual (Rp) | K81: Margin (Rp) | L81: Margin (%) | M81: Keterangan
A82: 1 | B82: Sarung Tangan Finnil | C82: Pack | D82: 10 | F82: =IF(E82<>"",D82*E82,"") | G82: 73000 | H82: =IF(G82<>"",D82*G82,"") -> 730000 | I82: 85000 | J82: =IF(I82<>"",D82*I82,"") -> 850000 | K82: =IF(J82<>"",IF(H82<>"",J82-H82,IF(F82<>"",J82-F82,"")),"") -> 120000 | L82: =IF(K82<>"",IF(H82<>"",IF(H82<>0,K82/H82,""),IF(F82<>"",IF(F82<>0,K82/F82,""),"")),"") -> 0.16438356
A83: 2 | B83: Plastik Es wayang | C83: Pack | D83: 40 | F83: =IF(E83<>"",D83*E83,"") | G83: 9500 | H83: =IF(G83<>"",D83*G83,"") -> 380000 | I83: 17500 | J83: =IF(I83<>"",D83*I83,"") -> 700000 | K83: =IF(J83<>"",IF(H83<>"",J83-H83,IF(F83<>"",J83-F83,"")),"") -> 320000 | L83: =IF(K83<>"",IF(H83<>"",IF(H83<>0,K83/H83,""),IF(F83<>"",IF(F83<>0,K83/F83,""),"")),"") -> 0.84210526
A84: 3 | B84: Gas 50kg | C84: Tabung | D84: 4 | F84: =IF(E84<>"",D84*E84,"") | G84: 1190000 | H84: =IF(G84<>"",D84*G84,"") -> 4760000 | I84: 1350000 | J84: =IF(I84<>"",D84*I84,"") -> 5400000 | K84: =IF(J84<>"",IF(H84<>"",J84-H84,IF(F84<>"",J84-F84,"")),"") -> 640000 | L84: =IF(K84<>"",IF(H84<>"",IF(H84<>0,K84/H84,""),IF(F84<>"",IF(F84<>0,K84/F84,""),"")),"") -> 0.13445378
A85: 4 | B85: Masker Hijab | C85: Pack | D85: 10 | F85: =IF(E85<>"",D85*E85,"") | G85: 25000 | H85: =IF(G85<>"",D85*G85,"") -> 250000 | I85: 30000 | J85: =IF(I85<>"",D85*I85,"") -> 300000 | K85: =IF(J85<>"",IF(H85<>"",J85-H85,IF(F85<>"",J85-F85,"")),"") -> 50000 | L85: =IF(K85<>"",IF(H85<>"",IF(H85<>0,K85/H85,""),IF(F85<>"",IF(F85<>0,K85/F85,""),"")),"") -> 0.2
A86: 5 | B86: Kopi Hitam Kapal Api + Gula | C86: Dus | D86: 1 | F86: =IF(E86<>"",D86*E86,"") | G86: 208000 | H86: =IF(G86<>"",D86*G86,"") -> 208000 | I86: 245000 | J86: =IF(I86<>"",D86*I86,"") -> 245000 | K86: =IF(J86<>"",IF(H86<>"",J86-H86,IF(F86<>"",J86-F86,"")),"") -> 37000 | L86: =IF(K86<>"",IF(H86<>"",IF(H86<>0,K86/H86,""),IF(F86<>"",IF(F86<>0,K86/F86,""),"")),"") -> 0.17788462
A87: 6 | B87: Kopi Gooday Merah | C87: Dus | D87: 1 | F87: =IF(E87<>"",D87*E87,"") | G87: 180000 | H87: =IF(G87<>"",D87*G87,"") -> 180000 | I87: 210000 | J87: =IF(I87<>"",D87*I87,"") -> 210000 | K87: =IF(J87<>"",IF(H87<>"",J87-H87,IF(F87<>"",J87-F87,"")),"") -> 30000 | L87: =IF(K87<>"",IF(H87<>"",IF(H87<>0,K87/H87,""),IF(F87<>"",IF(F87<>0,K87/F87,""),"")),"") -> 0.16666667
A88: 7 | B88: Kopi Gooday Freeze | C88: Dus | D88: 1 | F88: =IF(E88<>"",D88*E88,"") | G88: 285000 | H88: =IF(G88<>"",D88*G88,"") -> 285000 | I88: 325000 | J88: =IF(I88<>"",D88*I88,"") -> 325000 | K88: =IF(J88<>"",IF(H88<>"",J88-H88,IF(F88<>"",J88-F88,"")),"") -> 40000 | L88: =IF(K88<>"",IF(H88<>"",IF(H88<>0,K88/H88,""),IF(F88<>"",IF(F88<>0,K88/F88,""),"")),"") -> 0.14035088
A89: 8 | B89: Galon Aqua | C89: Galon | D89: 75 | F89: =IF(E89<>"",D89*E89,"") | G89: 19200 | H89: =IF(G89<>"",D89*G89,"") -> 1440000 | I89: 22500 | J89: =IF(I89<>"",D89*I89,"") -> 1687500 | K89: =IF(J89<>"",IF(H89<>"",J89-H89,IF(F89<>"",J89-F89,"")),"") -> 247500 | L89: =IF(K89<>"",IF(H89<>"",IF(H89<>0,K89/H89,""),IF(F89<>"",IF(F89<>0,K89/F89,""),"")),"") -> 0.171875
A90: 9 | B90: Sabun Cuci Piring | C90: Drigen | D90: 15 | F90: =IF(E90<>"",D90*E90,"") | G90: 65000 | H90: =IF(G90<>"",D90*G90,"") -> 975000 | I90: 75000 | J90: =IF(I90<>"",D90*I90,"") -> 1125000 | K90: =IF(J90<>"",IF(H90<>"",J90-H90,IF(F90<>"",J90-F90,"")),"") -> 150000 | L90: =IF(K90<>"",IF(H90<>"",IF(H90<>0,K90/H90,""),IF(F90<>"",IF(F90<>0,K90/F90,""),"")),"") -> 0.15384615
A91: 10 | B91: Sabun Pel | C91: Drigen | D91: 5 | F91: =IF(E91<>"",D91*E91,"") | G91: 51000 | H91: =IF(G91<>"",D91*G91,"") -> 255000 | I91: 75000 | J91: =IF(I91<>"",D91*I91,"") -> 375000 | K91: =IF(J91<>"",IF(H91<>"",J91-H91,IF(F91<>"",J91-F91,"")),"") -> 120000 | L91: =IF(K91<>"",IF(H91<>"",IF(H91<>0,K91/H91,""),IF(F91<>"",IF(F91<>0,K91/F91,""),"")),"") -> 0.47058824
A92: 11 | B92: Milo | C92: Bungks | D92: 1 | F92: =IF(E92<>"",D92*E92,"") | G92: 128000 | H92: =IF(G92<>"",D92*G92,"") -> 128000 | I92: 320000 | J92: =IF(I92<>"",D92*I92,"") -> 320000 | K92: =IF(J92<>"",IF(H92<>"",J92-H92,IF(F92<>"",J92-F92,"")),"") -> 192000 | L92: =IF(K92<>"",IF(H92<>"",IF(H92<>0,K92/H92,""),IF(F92<>"",IF(F92<>0,K92/F92,""),"")),"") -> 1.5
A93: 12 | B93: Thin Wall Saos | C93: Pcs | D93: 2550 | F93: =IF(E93<>"",D93*E93,"") | G93: 425 | H93: =IF(G93<>"",D93*G93,"") -> 1083750 | I93: 450 | J93: =IF(I93<>"",D93*I93,"") -> 1147500 | K93: =IF(J93<>"",IF(H93<>"",J93-H93,IF(F93<>"",J93-F93,"")),"") -> 63750 | L93: =IF(K93<>"",IF(H93<>"",IF(H93<>0,K93/H93,""),IF(F93<>"",IF(F93<>0,K93/F93,""),"")),"") -> 0.058823529
A94: SUBTOTAL 16 JUN | F94: =SUMIF(F82:F93,"<>",F82:F93) -> 0 | H94: =SUMIF(H82:H93,"<>",H82:H93) -> 10674750 | J94: =SUMIF(J82:J93,"<>",J82:J93) -> 12685000 | K94: =IF(J94<>"",IF(H94<>"",J94-H94,IF(F94<>"",J94-F94,"")),"") -> 2010250 | L94: =IF(K94<>"",IF(H94<>"",IF(H94<>0,K94/H94,""),IF(F94<>"",IF(F94<>0,K94/F94,""),"")),"") -> 0.18831823
A96: 📅 Thursday, 18 June 2026
A97: No | B97: Nama Barang | C97: Satuan | D97: Qty | E97: 📊 ESTIMASI | G97: 🧾 REALISASI BELI | I97: 💰 PENJUALAN | K97: 📈 MARGIN | M97: Keterangan
A98: No | B98: Nama Barang | C98: Satuan | D98: Qty | E98: Est. Harga Beli (Rp) | F98: Total Estimasi (Rp) | G98: Harga Beli Nota (Rp) | H98: Total Beli Nota (Rp) | I98: Harga Jual (Rp) | J98: Total Jual (Rp) | K98: Margin (Rp) | L98: Margin (%) | M98: Keterangan
A99: 1 | B99: Sewa Daihatsu Grand Max | C99: unit | D99: 1 | F99: =IF(E99<>"",D99*E99,"") | G99: 3272500 | H99: =IF(G99<>"",D99*G99,"") -> 3272500 | I99: 3272500 | J99: =IF(I99<>"",D99*I99,"") -> 3272500 | K99: =IF(J99<>"",IF(H99<>"",J99-H99,IF(F99<>"",J99-F99,"")),"") -> 0 | L99: =IF(K99<>"",IF(H99<>"",IF(H99<>0,K99/H99,""),IF(F99<>"",IF(F99<>0,K99/F99,""),"")),"") -> 0
A100: 2 | B100: Sewa Daihatsu Grand Max | C100: unit | D100: 1 | F100: =IF(E100<>"",D100*E100,"") | G100: 3272500 | H100: =IF(G100<>"",D100*G100,"") -> 3272500 | I100: 3272500 | J100: =IF(I100<>"",D100*I100,"") -> 3272500 | K100: =IF(J100<>"",IF(H100<>"",J100-H100,IF(F100<>"",J100-F100,"")),"") -> 0 | L100: =IF(K100<>"",IF(H100<>"",IF(H100<>0,K100/H100,""),IF(F100<>"",IF(F100<>0,K100/F100,""),"")),"") -> 0
A101: SUBTOTAL 18 JUN | F101: =SUMIF(F99:F100,"<>",F99:F100) -> 0 | H101: =SUMIF(H99:H100,"<>",H99:H100) -> 6545000 | J101: =SUMIF(J99:J100,"<>",J99:J100) -> 6545000 | K101: =IF(J101<>"",IF(H101<>"",J101-H101,IF(F101<>"",J101-F101,"")),"") -> 0 | L101: =IF(K101<>"",IF(H101<>"",IF(H101<>0,K101/H101,""),IF(F101<>"",IF(F101<>0,K101/F101,""),"")),"") -> 0
A103: 📅 Thursday, 18 June 2026
A104: No | B104: Nama Barang | C104: Satuan | D104: Qty | E104: 📊 ESTIMASI | G104: 🧾 REALISASI BELI | I104: 💰 PENJUALAN | K104: 📈 MARGIN | M104: Keterangan
A105: No | B105: Nama Barang | C105: Satuan | D105: Qty | E105: Est. Harga Beli (Rp) | F105: Total Estimasi (Rp) | G105: Harga Beli Nota (Rp) | H105: Total Beli Nota (Rp) | I105: Harga Jual (Rp) | J105: Total Jual (Rp) | K105: Margin (Rp) | L105: Margin (%) | M105: Keterangan
A106: 1 | B106: Sarung Tangan Finnil | C106: Pack | D106: 10 | F106: =IF(E106<>"",D106*E106,"") | G106: 73000 | H106: =IF(G106<>"",D106*G106,"") -> 730000 | I106: 85000 | J106: =IF(I106<>"",D106*I106,"") -> 850000 | K106: =IF(J106<>"",IF(H106<>"",J106-H106,IF(F106<>"",J106-F106,"")),"") -> 120000 | L106: =IF(K106<>"",IF(H106<>"",IF(H106<>0,K106/H106,""),IF(F106<>"",IF(F106<>0,K106/F106,""),"")),"") -> 0.16438356
A107: 2 | B107: Plastik Clip | C107: Pack | D107: 26 | F107: =IF(E107<>"",D107*E107,"") | G107: 9600 | H107: =IF(G107<>"",D107*G107,"") -> 249600 | I107: 12500 | J107: =IF(I107<>"",D107*I107,"") -> 325000 | K107: =IF(J107<>"",IF(H107<>"",J107-H107,IF(F107<>"",J107-F107,"")),"") -> 75400 | L107: =IF(K107<>"",IF(H107<>"",IF(H107<>0,K107/H107,""),IF(F107<>"",IF(F107<>0,K107/F107,""),"")),"") -> 0.30208333
A108: SUBTOTAL 18 JUN | F108: =SUMIF(F106:F107,"<>",F106:F107) -> 0 | H108: =SUMIF(H106:H107,"<>",H106:H107) -> 979600 | J108: =SUMIF(J106:J107,"<>",J106:J107) -> 1175000 | K108: =IF(J108<>"",IF(H108<>"",J108-H108,IF(F108<>"",J108-F108,"")),"") -> 195400 | L108: =IF(K108<>"",IF(H108<>"",IF(H108<>0,K108/H108,""),IF(F108<>"",IF(F108<>0,K108/F108,""),"")),"") -> 0.19946917
A110: 🏆 GRAND TOTAL — Bakung 01 | F110: =F14+F23+F44+F51+F58+F77+F94+F101+F108 -> 0 | H110: =H14+H23+H44+H51+H58+H77+H94+H101+H108 -> 53451600 | J110: =J14+J23+J44+J51+J58+J77+J94+J101+J108 -> 62697500 | K110: =K14+K23+K44+K51+K58+K77+K94+K101 -> 9050500 | L110: =IF(K110<>"",IF(H110<>0,K110/H110,IF(F110<>0,K110/F110,"")),"") -> 0.1693214

Sheet Invoice B02
A1: 🧾 DRAFT INVOICE — BAKUNG 02
A2: Periode: Mei-Juni 2026 | 🟢 Hijau = linked Daftar Harga | 🔵 Biru = input manual (isi setelah nota datang)
A3: Kolom G (Harga Beli Nota) dikosongkan — isi saat barang tiba. Margin: pakai Nota jika ada, fallback ke Estimasi.
A4: 📅 Sunday, 24 May 2026
A5: No | B5: Nama Barang | C5: Satuan | D5: Qty | E5: 📊 ESTIMASI | G5: 🧾 REALISASI BELI | I5: 💰 PENJUALAN | K5: 📈 MARGIN | M5: Keterangan
A6: No | B6: Nama Barang | C6: Satuan | D6: Qty | E6: Est. Harga Beli (Rp) | F6: Total Estimasi (Rp) | G6: Harga Beli Nota (Rp) | H6: Total Beli Nota (Rp) | I6: Harga Jual (Rp) | J6: Total Jual (Rp) | K6: Margin (Rp) | L6: Margin (%) | M6: Keterangan
A7: 1 | B7: Ayam Potong Sayap | C7: Kg | D7: 215 | E7: ='Daftar Harga'!D10 -> 36500 | F7: =IF(E7<>"",D7*E7,"") -> 7847500 | G7: 33500 | H7: =IF(G7<>"",D7*G7,"") -> 7202500 | I7: 38000 | J7: =IF(I7<>"",D7*I7,"") -> 8170000 | K7: =IF(J7<>"",IF(H7<>"",J7-H7,IF(F7<>"",J7-F7,"")),"") -> 967500 | L7: =IF(K7<>"",IF(H7<>"",IF(H7<>0,K7/H7,""),IF(F7<>"",IF(F7<>0,K7/F7,""),"")),"") -> 0.13432836
A8: 2 | B8: Bawang Bombay | C8: Kg | D8: 2 | E8: ='Daftar Harga'!D12 -> 30000 | F8: =IF(E8<>"",D8*E8,"") -> 60000 | G8: 19000 | H8: =IF(G8<>"",D8*G8,"") -> 38000 | I8: 35000 | J8: =IF(I8<>"",D8*I8,"") -> 70000 | K8: =IF(J8<>"",IF(H8<>"",J8-H8,IF(F8<>"",J8-F8,"")),"") -> 32000 | L8: =IF(K8<>"",IF(H8<>"",IF(H8<>0,K8/H8,""),IF(F8<>"",IF(F8<>0,K8/F8,""),"")),"") -> 0.84210526
A9: 3 | B9: Bawang putih kupas | C9: Kg | D9: 5 | E9: ='Daftar Harga'!D16 -> 33000 | F9: =IF(E9<>"",D9*E9,"") -> 165000 | G9: 30000 | H9: =IF(G9<>"",D9*G9,"") -> 150000 | I9: 44000 | J9: =IF(I9<>"",D9*I9,"") -> 220000 | K9: =IF(J9<>"",IF(H9<>"",J9-H9,IF(F9<>"",J9-F9,"")),"") -> 70000 | L9: =IF(K9<>"",IF(H9<>"",IF(H9<>0,K9/H9,""),IF(F9<>"",IF(F9<>0,K9/F9,""),"")),"") -> 0.46666667
A10: 4 | B10: Beras | C10: Kg | D10: 130 | E10: ='Daftar Harga'!D17 -> 15500 | F10: =IF(E10<>"",D10*E10,"") -> 2015000 | G10: 14500 | H10: =IF(G10<>"",D10*G10,"") -> 1885000 | I10: 15500 | J10: =IF(I10<>"",D10*I10,"") -> 2015000 | K10: =IF(J10<>"",IF(H10<>"",J10-H10,IF(F10<>"",J10-F10,"")),"") -> 130000 | L10: =IF(K10<>"",IF(H10<>"",IF(H10<>0,K10/H10,""),IF(F10<>"",IF(F10<>0,K10/F10,""),"")),"") -> 0.068965517
A11: 5 | B11: Bubuk Cabe | C11: Kg | D11: 1 | E11: ='Daftar Harga'!D21 -> 170000 | F11: =IF(E11<>"",D11*E11,"") -> 170000 | G11: 85000 | H11: =IF(G11<>"",D11*G11,"") -> 85000 | I11: 105000 | J11: =IF(I11<>"",D11*I11,"") -> 105000 | K11: =IF(J11<>"",IF(H11<>"",J11-H11,IF(F11<>"",J11-F11,"")),"") -> 20000 | L11: =IF(K11<>"",IF(H11<>"",IF(H11<>0,K11/H11,""),IF(F11<>"",IF(F11<>0,K11/F11,""),"")),"") -> 0.23529412
A12: 6 | B12: Buncis | C12: Kg | D12: 30 | E12: ='Daftar Harga'!D24 -> 13000 | F12: =IF(E12<>"",D12*E12,"") -> 390000 | G12: 20000 | H12: =IF(G12<>"",D12*G12,"") -> 600000 | I12: 16000 | J12: =IF(I12<>"",D12*I12,"") -> 480000 | K12: =IF(J12<>"",IF(H12<>"",J12-H12,IF(F12<>"",J12-F12,"")),"") -> -120000 | L12: =IF(K12<>"",IF(H12<>"",IF(H12<>0,K12/H12,""),IF(F12<>"",IF(F12<>0,K12/F12,""),"")),"") -> -0.2
A13: 7 | B13: Cabai merah besar | C13: Kg | D13: 2 | E13: ='Daftar Harga'!D26 -> 47000 | F13: =IF(E13<>"",D13*E13,"") -> 94000 | G13: 70000 | H13: =IF(G13<>"",D13*G13,"") -> 140000 | I13: 75000 | J13: =IF(I13<>"",D13*I13,"") -> 150000 | K13: =IF(J13<>"",IF(H13<>"",J13-H13,IF(F13<>"",J13-F13,"")),"") -> 10000 | L13: =IF(K13<>"",IF(H13<>"",IF(H13<>0,K13/H13,""),IF(F13<>"",IF(F13<>0,K13/F13,""),"")),"") -> 0.071428571
A14: 8 | B14: Daun pandan | C14: Kg | D14: 0.25 | E14: ='Daftar Harga'!D31 -> 40000 | F14: =IF(E14<>"",D14*E14,"") -> 10000 | G14: 35000 | H14: =IF(G14<>"",D14*G14,"") -> 8750 | I14: 45000 | J14: =IF(I14<>"",D14*I14,"") -> 11250 | K14: =IF(J14<>"",IF(H14<>"",J14-H14,IF(F14<>"",J14-F14,"")),"") -> 2500 | L14: =IF(K14<>"",IF(H14<>"",IF(H14<>0,K14/H14,""),IF(F14<>"",IF(F14<>0,K14/F14,""),"")),"") -> 0.28571429
A15: 9 | B15: Gula pasir | C15: Kg | D15: 8 | E15: ='Daftar Harga'!D36 -> 19000 | F15: =IF(E15<>"",D15*E15,"") -> 152000 | G15: 18500 | H15: =IF(G15<>"",D15*G15,"") -> 148000 | I15: 20000 | J15: =IF(I15<>"",D15*I15,"") -> 160000 | K15: =IF(J15<>"",IF(H15<>"",J15-H15,IF(F15<>"",J15-F15,"")),"") -> 12000 | L15: =IF(K15<>"",IF(H15<>"",IF(H15<>0,K15/H15,""),IF(F15<>"",IF(F15<>0,K15/F15,""),"")),"") -> 0.081081081
A16: 10 | B16: Jahe | C16: Kg | D16: 1 | E16: ='Daftar Harga'!D39 -> 20000 | F16: =IF(E16<>"",D16*E16,"") -> 20000 | G16: 20000 | H16: =IF(G16<>"",D16*G16,"") -> 20000 | I16: 26000 | J16: =IF(I16<>"",D16*I16,"") -> 26000 | K16: =IF(J16<>"",IF(H16<>"",J16-H16,IF(F16<>"",J16-F16,"")),"") -> 6000 | L16: =IF(K16<>"",IF(H16<>"",IF(H16<>0,K16/H16,""),IF(F16<>"",IF(F16<>0,K16/F16,""),"")),"") -> 0.3
A17: 11 | B17: Kecap Inggris | C17: Botol | D17: 1 | E17: ='Daftar Harga'!D49 -> 47000 | F17: =IF(E17<>"",D17*E17,"") -> 47000 | G17: 47000 | H17: =IF(G17<>"",D17*G17,"") -> 47000 | I17: 55000 | J17: =IF(I17<>"",D17*I17,"") -> 55000 | K17: =IF(J17<>"",IF(H17<>"",J17-H17,IF(F17<>"",J17-F17,"")),"") -> 8000 | L17: =IF(K17<>"",IF(H17<>"",IF(H17<>0,K17/H17,""),IF(F17<>"",IF(F17<>0,K17/F17,""),"")),"") -> 0.17021277
A18: 12 | B18: Minyak | C18: Liter | D18: 72 | E18: ='Daftar Harga'!D69 -> 205000 | F18: =IF(E18<>"",D18*E18,"") -> 14760000 | G18: 22000 | H18: =IF(G18<>"",D18*G18,"") -> 1584000 | I18: 23000 | J18: =IF(I18<>"",D18*I18,"") -> 1656000 | K18: =IF(J18<>"",IF(H18<>"",J18-H18,IF(F18<>"",J18-F18,"")),"") -> 72000 | L18: =IF(K18<>"",IF(H18<>"",IF(H18<>0,K18/H18,""),IF(F18<>"",IF(F18<>0,K18/F18,""),"")),"") -> 0.045454545
A19: 13 | B19: Pisang | C19: Pcs | D19: 2020 | E19: ='Daftar Harga'!D71 -> 1900 | F19: =IF(E19<>"",D19*E19,"") -> 3838000 | G19: 1800 | H19: =IF(G19<>"",D19*G19,"") -> 3636000 | I19: 2000 | J19: =IF(I19<>"",D19*I19,"") -> 4040000 | K19: =IF(J19<>"",IF(H19<>"",J19-H19,IF(F19<>"",J19-F19,"")),"") -> 404000 | L19: =IF(K19<>"",IF(H19<>"",IF(H19<>0,K19/H19,""),IF(F19<>"",IF(F19<>0,K19/F19,""),"")),"") -> 0.11111111
A20: 14 | B20: Royko | C20: Kg | D20: 3 | E20: ='Daftar Harga'!D74 -> 42000 | F20: =IF(E20<>"",D20*E20,"") -> 126000 | G20: 42000 | H20: =IF(G20<>"",D20*G20,"") -> 126000 | I20: 46000 | J20: =IF(I20<>"",D20*I20,"") -> 138000 | K20: =IF(J20<>"",IF(H20<>"",J20-H20,IF(F20<>"",J20-F20,"")),"") -> 12000 | L20: =IF(K20<>"",IF(H20<>"",IF(H20<>0,K20/H20,""),IF(F20<>"",IF(F20<>0,K20/F20,""),"")),"") -> 0.095238095
A21: 15 | B21: Saus Pedas | C21: Dirigen | D21: 1 | E21: ='Daftar Harga'!D77 -> 135000 | F21: =IF(E21<>"",D21*E21,"") -> 135000 | G21: 115000 | H21: =IF(G21<>"",D21*G21,"") -> 115000 | I21: 130000 | J21: =IF(I21<>"",D21*I21,"") -> 130000 | K21: =IF(J21<>"",IF(H21<>"",J21-H21,IF(F21<>"",J21-F21,"")),"") -> 15000 | L21: =IF(K21<>"",IF(H21<>"",IF(H21<>0,K21/H21,""),IF(F21<>"",IF(F21<>0,K21/F21,""),"")),"") -> 0.13043478
A22: 16 | B22: Saus tiram | C22: Botol | D22: 2 | E22: ='Daftar Harga'!D79 -> 52000 | F22: =IF(E22<>"",D22*E22,"") -> 104000 | G22: 52000 | H22: =IF(G22<>"",D22*G22,"") -> 104000 | I22: 56000 | J22: =IF(I22<>"",D22*I22,"") -> 112000 | K22: =IF(J22<>"",IF(H22<>"",J22-H22,IF(F22<>"",J22-F22,"")),"") -> 8000 | L22: =IF(K22<>"",IF(H22<>"",IF(H22<>0,K22/H22,""),IF(F22<>"",IF(F22<>0,K22/F22,""),"")),"") -> 0.076923077
A23: 17 | B23: Saus tomat | C23: Dirigen | D23: 2 | E23: ='Daftar Harga'!D80 -> 95000 | F23: =IF(E23<>"",D23*E23,"") -> 190000 | G23: 95000 | H23: =IF(G23<>"",D23*G23,"") -> 190000 | I23: 110000 | J23: =IF(I23<>"",D23*I23,"") -> 220000 | K23: =IF(J23<>"",IF(H23<>"",J23-H23,IF(F23<>"",J23-F23,"")),"") -> 30000 | L23: =IF(K23<>"",IF(H23<>"",IF(H23<>0,K23/H23,""),IF(F23<>"",IF(F23<>0,K23/F23,""),"")),"") -> 0.15789474
A24: 18 | B24: Tahu Bulat | C24: Pcs | D24: 4000 | E24: ='Daftar Harga'!D89 -> 500 | F24: =IF(E24<>"",D24*E24,"") -> 2000000 | G24: 400 | H24: =IF(G24<>"",D24*G24,"") -> 1600000 | I24: 500 | J24: =IF(I24<>"",D24*I24,"") -> 2000000 | K24: =IF(J24<>"",IF(H24<>"",J24-H24,IF(F24<>"",J24-F24,"")),"") -> 400000 | L24: =IF(K24<>"",IF(H24<>"",IF(H24<>0,K24/H24,""),IF(F24<>"",IF(F24<>0,K24/F24,""),"")),"") -> 0.25
A25: 19 | B25: Wortel | C25: Kg | D25: 35 | E25: ='Daftar Harga'!D101 -> 9000 | F25: =IF(E25<>"",D25*E25,"") -> 315000 | G25: 12000 | H25: =IF(G25<>"",D25*G25,"") -> 420000 | I25: 14000 | J25: =IF(I25<>"",D25*I25,"") -> 490000 | K25: =IF(J25<>"",IF(H25<>"",J25-H25,IF(F25<>"",J25-F25,"")),"") -> 70000 | L25: =IF(K25<>"",IF(H25<>"",IF(H25<>0,K25/H25,""),IF(F25<>"",IF(F25<>0,K25/F25,""),"")),"") -> 0.16666667
A26: SUBTOTAL 24 May 2026 | F26: =SUMIF(F7:F25,"<>",F7:F25) -> 32438500 | H26: =SUMIF(H7:H25,"<>",H7:H25) -> 18099250 | J26: =SUMIF(J7:J25,"<>",J7:J25) -> 20248250 | K26: =IF(J26<>"",IF(H26<>"",J26-H26,IF(F26<>"",J26-F26,"")),"") -> 2149000 | L26: =IF(K26<>"",IF(H26<>"",IF(H26<>0,K26/H26,""),IF(F26<>"",IF(F26<>0,K26/F26,""),"")),"") -> 0.1187342
A28: 📅 Monday, 25 May 2026
A29: No | B29: Nama Barang | C29: Satuan | D29: Qty | E29: 📊 ESTIMASI | G29: 🧾 REALISASI BELI | I29: 💰 PENJUALAN | K29: 📈 MARGIN | M29: Keterangan
A30: No | B30: Nama Barang | C30: Satuan | D30: Qty | E30: Est. Harga Beli (Rp) | F30: Total Estimasi (Rp) | G30: Harga Beli Nota (Rp) | H30: Total Beli Nota (Rp) | I30: Harga Jual (Rp) | J30: Total Jual (Rp) | K30: Margin (Rp) | L30: Margin (%) | M30: Keterangan
A31: 1 | B31: Asam Jawa | C31: Kg | D31: 2 | E31: ='Daftar Harga'!D6 | F31: =IF(E31<>"",D31*E31,"") | G31: 20000 | H31: =IF(G31<>"",D31*G31,"") -> 40000 | I31: 23000 | J31: =IF(I31<>"",D31*I31,"") -> 46000 | K31: =IF(J31<>"",IF(H31<>"",J31-H31,IF(F31<>"",J31-F31,"")),"") -> 6000 | L31: =IF(K31<>"",IF(H31<>"",IF(H31<>0,K31/H31,""),IF(F31<>"",IF(F31<>0,K31/F31,""),"")),"") -> 0.15
A32: 2 | B32: Bawang merah kupas | C32: Kg | D32: 8 | E32: ='Daftar Harga'!D14 -> 40000 | F32: =IF(E32<>"",D32*E32,"") -> 320000 | G32: 40000 | H32: =IF(G32<>"",D32*G32,"") -> 320000 | I32: 45000 | J32: =IF(I32<>"",D32*I32,"") -> 360000 | K32: =IF(J32<>"",IF(H32<>"",J32-H32,IF(F32<>"",J32-F32,"")),"") -> 40000 | L32: =IF(K32<>"",IF(H32<>"",IF(H32<>0,K32/H32,""),IF(F32<>"",IF(F32<>0,K32/F32,""),"")),"") -> 0.125
A33: 3 | B33: Bawang putih kupas | C33: Kg | D33: 5 | E33: ='Daftar Harga'!D16 -> 33000 | F33: =IF(E33<>"",D33*E33,"") -> 165000 | G33: 30000 | H33: =IF(G33<>"",D33*G33,"") -> 150000 | I33: 40000 | J33: =IF(I33<>"",D33*I33,"") -> 200000 | K33: =IF(J33<>"",IF(H33<>"",J33-H33,IF(F33<>"",J33-F33,"")),"") -> 50000 | L33: =IF(K33<>"",IF(H33<>"",IF(H33<>0,K33/H33,""),IF(F33<>"",IF(F33<>0,K33/F33,""),"")),"") -> 0.33333333
A34: 4 | B34: Beras | C34: Kg | D34: 130 | E34: ='Daftar Harga'!D17 -> 15500 | F34: =IF(E34<>"",D34*E34,"") -> 2015000 | G34: 14500 | H34: =IF(G34<>"",D34*G34,"") -> 1885000 | I34: 15500 | J34: =IF(I34<>"",D34*I34,"") -> 2015000 | K34: =IF(J34<>"",IF(H34<>"",J34-H34,IF(F34<>"",J34-F34,"")),"") -> 130000 | L34: =IF(K34<>"",IF(H34<>"",IF(H34<>0,K34/H34,""),IF(F34<>"",IF(F34<>0,K34/F34,""),"")),"") -> 0.068965517
A35: 5 | B35: Daun Salam | C35: Kg | D35: 0.25 | E35: ='Daftar Harga'!D32 -> 21600 | F35: =IF(E35<>"",D35*E35,"") -> 5400 | G35: 28000 | H35: =IF(G35<>"",D35*G35,"") -> 7000 | I35: 30000 | J35: =IF(I35<>"",D35*I35,"") -> 7500 | K35: =IF(J35<>"",IF(H35<>"",J35-H35,IF(F35<>"",J35-F35,"")),"") -> 500 | L35: =IF(K35<>"",IF(H35<>"",IF(H35<>0,K35/H35,""),IF(F35<>"",IF(F35<>0,K35/F35,""),"")),"") -> 0.071428571
A36: 6 | B36: Gula merah | C36: Kg | D36: 3 | E36: ='Daftar Harga'!D35 -> 17000 | F36: =IF(E36<>"",D36*E36,"") -> 51000 | G36: 17000 | H36: =IF(G36<>"",D36*G36,"") -> 51000 | I36: 20000 | J36: =IF(I36<>"",D36*I36,"") -> 60000 | K36: =IF(J36<>"",IF(H36<>"",J36-H36,IF(F36<>"",J36-F36,"")),"") -> 9000 | L36: =IF(K36<>"",IF(H36<>"",IF(H36<>0,K36/H36,""),IF(F36<>"",IF(F36<>0,K36/F36,""),"")),"") -> 0.17647059
A37: 7 | B37: Gula pasir | C37: Kg | D37: 6 | E37: ='Daftar Harga'!D36 -> 19000 | F37: =IF(E37<>"",D37*E37,"") -> 114000 | G37: 18500 | H37: =IF(G37<>"",D37*G37,"") -> 111000 | I37: 20000 | J37: =IF(I37<>"",D37*I37,"") -> 120000 | K37: =IF(J37<>"",IF(H37<>"",J37-H37,IF(F37<>"",J37-F37,"")),"") -> 9000 | L37: =IF(K37<>"",IF(H37<>"",IF(H37<>0,K37/H37,""),IF(F37<>"",IF(F37<>0,K37/F37,""),"")),"") -> 0.081081081
A38: 8 | B38: Jeruk Limau | C38: Kg | D38: 0.5 | E38: ='Daftar Harga'!D41 -> 29000 | F38: =IF(E38<>"",D38*E38,"") -> 14500 | G38: 18000 | H38: =IF(G38<>"",D38*G38,"") -> 9000 | I38: 25000 | J38: =IF(I38<>"",D38*I38,"") -> 12500 | K38: =IF(J38<>"",IF(H38<>"",J38-H38,IF(F38<>"",J38-F38,"")),"") -> 3500 | L38: =IF(K38<>"",IF(H38<>"",IF(H38<>0,K38/H38,""),IF(F38<>"",IF(F38<>0,K38/F38,""),"")),"") -> 0.38888889
A39: 9 | B39: Kecap manis | C39: Dirigen | D39: 1 | E39: ='Daftar Harga'!D50 -> 190000 | F39: =IF(E39<>"",D39*E39,"") -> 190000 | G39: 190000 | H39: =IF(G39<>"",D39*G39,"") -> 190000 | I39: 210000 | J39: =IF(I39<>"",D39*I39,"") -> 210000 | K39: =IF(J39<>"",IF(H39<>"",J39-H39,IF(F39<>"",J39-F39,"")),"") -> 20000 | L39: =IF(K39<>"",IF(H39<>"",IF(H39<>0,K39/H39,""),IF(F39<>"",IF(F39<>0,K39/F39,""),"")),"") -> 0.10526316
A40: 10 | B40: Jeruk | C40: Kg | D40: 200 | E40: ='Daftar Harga'!D53 | F40: =IF(E40<>"",D40*E40,"") | G40: 25000 | H40: =IF(G40<>"",D40*G40,"") -> 5000000 | I40: 29000 | J40: =IF(I40<>"",D40*I40,"") -> 5800000 | K40: =IF(J40<>"",IF(H40<>"",J40-H40,IF(F40<>"",J40-F40,"")),"") -> 800000 | L40: =IF(K40<>"",IF(H40<>"",IF(H40<>0,K40/H40,""),IF(F40<>"",IF(F40<>0,K40/F40,""),"")),"") -> 0.16
A41: 11 | B41: Kemiri | C41: Kg | D41: 2 | E41: ='Daftar Harga'!D54 -> 45000 | F41: =IF(E41<>"",D41*E41,"") -> 90000 | G41: 43000 | H41: =IF(G41<>"",D41*G41,"") -> 86000 | I41: 48000 | J41: =IF(I41<>"",D41*I41,"") -> 96000 | K41: =IF(J41<>"",IF(H41<>"",J41-H41,IF(F41<>"",J41-F41,"")),"") -> 10000 | L41: =IF(K41<>"",IF(H41<>"",IF(H41<>0,K41/H41,""),IF(F41<>"",IF(F41<>0,K41/F41,""),"")),"") -> 0.11627907
A42: 12 | B42: Kunyit | C42: Kg | D42: 1 | E42: ='Daftar Harga'!D60 -> 12000 | F42: =IF(E42<>"",D42*E42,"") -> 12000 | G42: 11667 | H42: =IF(G42<>"",D42*G42,"") -> 11667 | I42: 12000 | J42: =IF(I42<>"",D42*I42,"") -> 12000 | K42: =IF(J42<>"",IF(H42<>"",J42-H42,IF(F42<>"",J42-F42,"")),"") -> 333 | L42: =IF(K42<>"",IF(H42<>"",IF(H42<>0,K42/H42,""),IF(F42<>"",IF(F42<>0,K42/F42,""),"")),"") -> 0.028542042
A43: 13 | B43: Lengkuas | C43: Kg | D43: 5 | E43: ='Daftar Harga'!D65 -> 16000 | F43: =IF(E43<>"",D43*E43,"") -> 80000 | G43: 12000 | H43: =IF(G43<>"",D43*G43,"") -> 60000 | I43: 14000 | J43: =IF(I43<>"",D43*I43,"") -> 70000 | K43: =IF(J43<>"",IF(H43<>"",J43-H43,IF(F43<>"",J43-F43,"")),"") -> 10000 | L43: =IF(K43<>"",IF(H43<>"",IF(H43<>0,K43/H43,""),IF(F43<>"",IF(F43<>0,K43/F43,""),"")),"") -> 0.16666667
A44: 14 | B44: Minyak | C44: Liter | D44: 36 | E44: ='Daftar Harga'!D69 -> 205000 | F44: =IF(E44<>"",D44*E44,"") -> 7380000 | G44: 22000 | H44: =IF(G44<>"",D44*G44,"") -> 792000 | I44: 25000 | J44: =IF(I44<>"",D44*I44,"") -> 900000 | K44: =IF(J44<>"",IF(H44<>"",J44-H44,IF(F44<>"",J44-F44,"")),"") -> 108000 | L44: =IF(K44<>"",IF(H44<>"",IF(H44<>0,K44/H44,""),IF(F44<>"",IF(F44<>0,K44/F44,""),"")),"") -> 0.13636364
A45: 15 | B45: Royko | C45: Kg | D45: 4 | E45: ='Daftar Harga'!D74 -> 42000 | F45: =IF(E45<>"",D45*E45,"") -> 168000 | G45: 42000 | H45: =IF(G45<>"",D45*G45,"") -> 168000 | I45: 46000 | J45: =IF(I45<>"",D45*I45,"") -> 184000 | K45: =IF(J45<>"",IF(H45<>"",J45-H45,IF(F45<>"",J45-F45,"")),"") -> 16000 | L45: =IF(K45<>"",IF(H45<>"",IF(H45<>0,K45/H45,""),IF(F45<>"",IF(F45<>0,K45/F45,""),"")),"") -> 0.095238095
A46: 16 | B46: Sereh | C46: Kg | D46: 1 | E46: ='Daftar Harga'!D86 -> 12000 | F46: =IF(E46<>"",D46*E46,"") -> 12000 | G46: 11000 | H46: =IF(G46<>"",D46*G46,"") -> 11000 | I46: 14000 | J46: =IF(I46<>"",D46*I46,"") -> 14000 | K46: =IF(J46<>"",IF(H46<>"",J46-H46,IF(F46<>"",J46-F46,"")),"") -> 3000 | L46: =IF(K46<>"",IF(H46<>"",IF(H46<>0,K46/H46,""),IF(F46<>"",IF(F46<>0,K46/F46,""),"")),"") -> 0.27272727
A47: 17 | B47: Telur Ayam | C47: Kg | D47: 135 | E47: ='Daftar Harga'!D92 -> 28000 | F47: =IF(E47<>"",D47*E47,"") -> 3780000 | G47: 25500 | H47: =IF(G47<>"",D47*G47,"") -> 3442500 | I47: 28000 | J47: =IF(I47<>"",D47*I47,"") -> 3780000 | K47: =IF(J47<>"",IF(H47<>"",J47-H47,IF(F47<>"",J47-F47,"")),"") -> 337500 | L47: =IF(K47<>"",IF(H47<>"",IF(H47<>0,K47/H47,""),IF(F47<>"",IF(F47<>0,K47/F47,""),"")),"") -> 0.098039216
A48: 18 | B48: Tempe | C48: Papan | D48: 83 | E48: ='Daftar Harga'!D93 -> 12000 | F48: =IF(E48<>"",D48*E48,"") -> 996000 | G48: 12000 | H48: =IF(G48<>"",D48*G48,"") -> 996000 | I48: 14000 | J48: =IF(I48<>"",D48*I48,"") -> 1162000 | K48: =IF(J48<>"",IF(H48<>"",J48-H48,IF(F48<>"",J48-F48,"")),"") -> 166000 | L48: =IF(K48<>"",IF(H48<>"",IF(H48<>0,K48/H48,""),IF(F48<>"",IF(F48<>0,K48/F48,""),"")),"") -> 0.16666667
A49: 19 | B49: Terasi | C49: Kg | D49: 0.25 | E49: ='Daftar Harga'!D98 -> 7000 | F49: =IF(E49<>"",D49*E49,"") -> 1750 | G49: 24000 | H49: =IF(G49<>"",D49*G49,"") -> 6000 | I49: 30000 | J49: =IF(I49<>"",D49*I49,"") -> 7500 | K49: =IF(J49<>"",IF(H49<>"",J49-H49,IF(F49<>"",J49-F49,"")),"") -> 1500 | L49: =IF(K49<>"",IF(H49<>"",IF(H49<>0,K49/H49,""),IF(F49<>"",IF(F49<>0,K49/F49,""),"")),"") -> 0.25
A50: 20 | B50: Timun | C50: Kg | D50: 35 | E50: ='Daftar Harga'!D99 -> 8000 | F50: =IF(E50<>"",D50*E50,"") -> 280000 | G50: 9000 | H50: =IF(G50<>"",D50*G50,"") -> 315000 | I50: 14000 | J50: =IF(I50<>"",D50*I50,"") -> 490000 | K50: =IF(J50<>"",IF(H50<>"",J50-H50,IF(F50<>"",J50-F50,"")),"") -> 175000 | L50: =IF(K50<>"",IF(H50<>"",IF(H50<>0,K50/H50,""),IF(F50<>"",IF(F50<>0,K50/F50,""),"")),"") -> 0.55555556
A51: 21 | B51: Wortel | C51: Kg | D51: 30 | E51: ='Daftar Harga'!D101 -> 9000 | F51: =IF(E51<>"",D51*E51,"") -> 270000 | G51: 12000 | H51: =IF(G51<>"",D51*G51,"") -> 360000 | I51: 15000 | J51: =IF(I51<>"",D51*I51,"") -> 450000 | K51: =IF(J51<>"",IF(H51<>"",J51-H51,IF(F51<>"",J51-F51,"")),"") -> 90000 | L51: =IF(K51<>"",IF(H51<>"",IF(H51<>0,K51/H51,""),IF(F51<>"",IF(F51<>0,K51/F51,""),"")),"") -> 0.25
A52: SUBTOTAL 25 May 2026 | F52: =SUMIF(F31:F51,"<>",F31:F51) -> 15944650 | H52: =SUMIF(H31:H51,"<>",H31:H51) -> 14011167 | J52: =SUMIF(J31:J51,"<>",J31:J51) -> 15996500 | K52: =IF(J52<>"",IF(H52<>"",J52-H52,IF(F52<>"",J52-F52,"")),"") -> 1985333 | L52: =IF(K52<>"",IF(H52<>"",IF(H52<>0,K52/H52,""),IF(F52<>"",IF(F52<>0,K52/F52,""),"")),"") -> 0.14169648
A54: 📅 Thursday, 28 May 2026
A55: No | B55: Nama Barang | C55: Satuan | D55: Qty | E55: 📊 ESTIMASI | G55: 🧾 REALISASI BELI | I55: 💰 PENJUALAN | K55: 📈 MARGIN | M55: Keterangan
A56: No | B56: Nama Barang | C56: Satuan | D56: Qty | E56: Est. Harga Beli (Rp) | F56: Total Estimasi (Rp) | G56: Harga Beli Nota (Rp) | H56: Total Beli Nota (Rp) | I56: Harga Jual (Rp) | J56: Total Jual (Rp) | K56: Margin (Rp) | L56: Margin (%) | M56: Keterangan
A57: 1 | B57: Kulit Kebab | C57: Pcs | D57: 83 | F57: =IF(E57<>"",D57*E57,"") | G57: 29000 | H57: =IF(G57<>"",D57*G57,"") -> 2407000 | I57: 32000 | J57: =IF(I57<>"",D57*I57,"") -> 2656000 | K57: =IF(J57<>"",IF(H57<>"",J57-H57,IF(F57<>"",J57-F57,"")),"") -> 249000 | L57: =IF(K57<>"",IF(H57<>"",IF(H57<>0,K57/H57,""),IF(F57<>"",IF(F57<>0,K57/F57,""),"")),"") -> 0.10344828
A58: 2 | B58: Ayam Dada Fillet | C58: Kg | D58: 90 | F58: =IF(E58<>"",D58*E58,"") | G58: 46500 | H58: =IF(G58<>"",D58*G58,"") -> 4185000 | I58: 48500 | J58: =IF(I58<>"",D58*I58,"") -> 4365000 | K58: =IF(J58<>"",IF(H58<>"",J58-H58,IF(F58<>"",J58-F58,"")),"") -> 180000 | L58: =IF(K58<>"",IF(H58<>"",IF(H58<>0,K58/H58,""),IF(F58<>"",IF(F58<>0,K58/F58,""),"")),"") -> 0.043010753
A59: 3 | B59: Bubuk Pprika | C59: Kg | D59: 1 | F59: =IF(E59<>"",D59*E59,"") | G59: 90000 | H59: =IF(G59<>"",D59*G59,"") -> 90000 | I59: 100000 | J59: =IF(I59<>"",D59*I59,"") -> 100000 | K59: =IF(J59<>"",IF(H59<>"",J59-H59,IF(F59<>"",J59-F59,"")),"") -> 10000 | L59: =IF(K59<>"",IF(H59<>"",IF(H59<>0,K59/H59,""),IF(F59<>"",IF(F59<>0,K59/F59,""),"")),"") -> 0.11111111
A60: 4 | B60: Bawang Putih Kupas | C60: Kg | D60: 1.5 | F60: =IF(E60<>"",D60*E60,"") | G60: 30000 | H60: =IF(G60<>"",D60*G60,"") -> 45000 | I60: 44000 | J60: =IF(I60<>"",D60*I60,"") -> 66000 | K60: =IF(J60<>"",IF(H60<>"",J60-H60,IF(F60<>"",J60-F60,"")),"") -> 21000 | L60: =IF(K60<>"",IF(H60<>"",IF(H60<>0,K60/H60,""),IF(F60<>"",IF(F60<>0,K60/F60,""),"")),"") -> 0.46666667
A61: 5 | B61: Margarin | C61: Pcs | D61: 1 | F61: =IF(E61<>"",D61*E61,"") | G61: 24000 | H61: =IF(G61<>"",D61*G61,"") -> 24000 | I61: 25000 | J61: =IF(I61<>"",D61*I61,"") -> 25000 | K61: =IF(J61<>"",IF(H61<>"",J61-H61,IF(F61<>"",J61-F61,"")),"") -> 1000 | L61: =IF(K61<>"",IF(H61<>"",IF(H61<>0,K61/H61,""),IF(F61<>"",IF(F61<>0,K61/F61,""),"")),"") -> 0.041666667
A62: 6 | B62: Bubuk Ngohiong | C62: Dus | D62: 1 | F62: =IF(E62<>"",D62*E62,"") | G62: 400000 | H62: =IF(G62<>"",D62*G62,"") -> 400000 | I62: 420000 | J62: =IF(I62<>"",D62*I62,"") -> 420000 | K62: =IF(J62<>"",IF(H62<>"",J62-H62,IF(F62<>"",J62-F62,"")),"") -> 20000 | L62: =IF(K62<>"",IF(H62<>"",IF(H62<>0,K62/H62,""),IF(F62<>"",IF(F62<>0,K62/F62,""),"")),"") -> 0.05
A63: 7 | B63: Minyak wijen | C63: Kg | D63: 1 | F63: =IF(E63<>"",D63*E63,"") | G63: 52000 | H63: =IF(G63<>"",D63*G63,"") -> 52000 | I63: 55000 | J63: =IF(I63<>"",D63*I63,"") -> 55000 | K63: =IF(J63<>"",IF(H63<>"",J63-H63,IF(F63<>"",J63-F63,"")),"") -> 3000 | L63: =IF(K63<>"",IF(H63<>"",IF(H63<>0,K63/H63,""),IF(F63<>"",IF(F63<>0,K63/F63,""),"")),"") -> 0.057692308
A64: 8 | B64: Jahe | C64: Kg | D64: 0.5 | F64: =IF(E64<>"",D64*E64,"") | G64: 23000 | H64: =IF(G64<>"",D64*G64,"") -> 11500 | I64: 26000 | J64: =IF(I64<>"",D64*I64,"") -> 13000 | K64: =IF(J64<>"",IF(H64<>"",J64-H64,IF(F64<>"",J64-F64,"")),"") -> 1500 | L64: =IF(K64<>"",IF(H64<>"",IF(H64<>0,K64/H64,""),IF(F64<>"",IF(F64<>0,K64/F64,""),"")),"") -> 0.13043478
A65: 9 | B65: Royko | C65: Kg | D65: 2 | F65: =IF(E65<>"",D65*E65,"") | G65: 45000 | H65: =IF(G65<>"",D65*G65,"") -> 90000 | I65: 46000 | J65: =IF(I65<>"",D65*I65,"") -> 92000 | K65: =IF(J65<>"",IF(H65<>"",J65-H65,IF(F65<>"",J65-F65,"")),"") -> 2000 | L65: =IF(K65<>"",IF(H65<>"",IF(H65<>0,K65/H65,""),IF(F65<>"",IF(F65<>0,K65/F65,""),"")),"") -> 0.022222222
A66: 10 | B66: Saua Sambal Sachet Indofood | C66: Pcs | D66: 3 | F66: =IF(E66<>"",D66*E66,"") | G66: 127000 | H66: =IF(G66<>"",D66*G66,"") -> 381000 | I66: 135000 | J66: =IF(I66<>"",D66*I66,"") -> 405000 | K66: =IF(J66<>"",IF(H66<>"",J66-H66,IF(F66<>"",J66-F66,"")),"") -> 24000 | L66: =IF(K66<>"",IF(H66<>"",IF(H66<>0,K66/H66,""),IF(F66<>"",IF(F66<>0,K66/F66,""),"")),"") -> 0.062992126
A67: 11 | B67: Saus Tomat Sachet Delmonte | C67: Kg | D67: 1 | F67: =IF(E67<>"",D67*E67,"") | G67: 117000 | H67: =IF(G67<>"",D67*G67,"") -> 117000 | I67: 120000 | J67: =IF(I67<>"",D67*I67,"") -> 120000 | K67: =IF(J67<>"",IF(H67<>"",J67-H67,IF(F67<>"",J67-F67,"")),"") -> 3000 | L67: =IF(K67<>"",IF(H67<>"",IF(H67<>0,K67/H67,""),IF(F67<>"",IF(F67<>0,K67/F67,""),"")),"") -> 0.025641026
A68: 12 | B68: Tahu Putih | C68: Liter | D68: 2077 | F68: =IF(E68<>"",D68*E68,"") | G68: 480 | H68: =IF(G68<>"",D68*G68,"") -> 996960 | I68: 700 | J68: =IF(I68<>"",D68*I68,"") -> 1453900 | K68: =IF(J68<>"",IF(H68<>"",J68-H68,IF(F68<>"",J68-F68,"")),"") -> 456940 | L68: =IF(K68<>"",IF(H68<>"",IF(H68<>0,K68/H68,""),IF(F68<>"",IF(F68<>0,K68/F68,""),"")),"") -> 0.45833333
... A72: 16 | B72: Jeruk Wokam | C72: Pcs | D72: 29 | F72: =IF(E72<>"",D72*E72,"") | G72: 250000 | H72: =IF(G72<>"",D72*G72,"") -> 7250000 | I72: 260000 | J72: =IF(I72<>"",D72*I72,"") -> 7540000 | K72: =IF(J72<>"",IF(H72<>"",J72-H72,IF(F72<>"",J72-F72,"")),"") -> 290000 | L72: =IF(K72<>"",IF(H72<>"",IF(H72<>0,K72/H72,""),IF(F72<>"",IF(F72<>0,K72/F72,""),"")),"") -> 0.04
A73: SUBTOTAL 28 May 2026 | F73: =SUMIF(F57:F72,"<>",F57:F72) -> 0 | H73: =SUMIF(H57:H72,"<>",H57:H72) -> 17641460 | J73: =SUMIF(J57:J72,"<>",J57:J72) -> 19032900 | K73: =IF(J73<>"",IF(H73<>"",J73-H73,IF(F73<>"",J73-F73,"")),"") -> 1391440 | L73: =IF(K73<>"",IF(H73<>"",IF(H73<>0,K73/H73,""),IF(F73<>"",IF(F73<>0,K73/F73,""),"")),"") -> 0.078873291
A75: 📅 Thursday, 28 May 2026
A76: No | B76: Nama Barang | C76: Satuan | D76: Qty | E76: 📊 ESTIMASI | G76: 🧾 REALISASI BELI | I76: 💰 PENJUALAN | K76: 📈 MARGIN | M76: Keterangan
A77: No | B77: Nama Barang | C77: Satuan | D77: Qty | E77: Est. Harga Beli (Rp) | F77: Total Estimasi (Rp) | G77: Harga Beli Nota (Rp) | H77: Total Beli Nota (Rp) | I77: Harga Jual (Rp) | J77: Total Jual (Rp) | K77: Margin (Rp) | L77: Margin (%) | M77: Keterangan
A78: 1 | B78: Susu Plan | C78: Karton | D78: 2016 | F78: =IF(E78<>"",D78*E78,"") | G78: 3167 | H78: =IF(G78<>"",D78*G78,"") -> 6384672 | I78: 3600 | J78: =IF(I78<>"",D78*I78,"") -> 7257600 | K78: =IF(J78<>"",IF(H78<>"",J78-H78,IF(F78<>"",J78-F78,"")),"") -> 872928 | L78: =IF(K78<>"",IF(H78<>"",IF(H78<>0,K78/H78,""),IF(F78<>"",IF(F78<>0,K78/F78,""),"")),"") -> 0.13672245
A79: 2 | B79: Apel Porsi Kecil | C79: Dus | D79: 5 | F79: =IF(E79<>"",D79*E79,"") | G79: 590000 | H79: =IF(G79<>"",D79*G79,"") -> 2950000 | I79: 610000 | J79: =IF(I79<>"",D79*I79,"") -> 3050000 | K79: =IF(J79<>"",IF(H79<>"",J79-H79,IF(F79<>"",J79-F79,"")),"") -> 100000 | L79: =IF(K79<>"",IF(H79<>"",IF(H79<>0,K79/H79,""),IF(F79<>"",IF(F79<>0,K79/F79,""),"")),"") -> 0.033898305
A80: 3 | B80: Pear Porsi Besar | C80: Dus | D80: 18 | F80: =IF(E80<>"",D80*E80,"") | G80: 355000 | H80: =IF(G80<>"",D80*G80,"") -> 6390000 | I80: 380000 | J80: =IF(I80<>"",D80*I80,"") -> 6840000 | K80: =IF(J80<>"",IF(H80<>"",J80-H80,IF(F80<>"",J80-F80,"")),"") -> 450000 | L80: =IF(K80<>"",IF(H80<>"",IF(H80<>0,K80/H80,""),IF(F80<>"",IF(F80<>0,K80/F80,""),"")),"") -> 0.070422535
A81: SUBTOTAL 28 May 2026 | F81: =SUMIF(F68:F80,"<>",F68:F80) -> 0 | H81: =SUMIF(H78:H80,"<>",H78:H80) -> 15724672 | J81: =SUMIF(J78:J80,"<>",J78:J80) -> 17147600 | K81: =IF(J81<>"",IF(H81<>"",J81-H81,IF(F81<>"",J81-F81,"")),"") -> 1422928 | L81: =IF(K81<>"",IF(H81<>"",IF(H81<>0,K81/H81,""),IF(F81<>"",IF(F81<>0,K81/F81,""),"")),"") -> 0.090490155
A83: 📅 Thursday, 28 May 2026
A84: No | B84: Nama Barang | C84: Satuan | D84: Qty | E84: 📊 ESTIMASI | G84: 🧾 REALISASI BELI | I84: 💰 PENJUALAN | K84: 📈 MARGIN | M84: Keterangan
A85: No | B85: Nama Barang | C85: Satuan | D85: Qty | E85: Est. Harga Beli (Rp) | F85: Total Estimasi (Rp) | G85: Harga Beli Nota (Rp) | H85: Total Beli Nota (Rp) | I85: Harga Jual (Rp) | J85: Total Jual (Rp) | K85: Margin (Rp) | L85: Margin (%) | M85: Keterangan
A86: 1 | B86: Apel | C86: Box | D86: 1 | F86: =IF(E86<>"",D86*E86,"") | G86: 590000 | H86: =IF(G86<>"",D86*G86,"") -> 590000 | I86: 610000 | J86: =IF(I86<>"",D86*I86,"") -> 610000 | K86: =IF(J86<>"",IF(H86<>"",J86-H86,IF(F86<>"",J86-F86,"")),"") -> 20000 | L86: =IF(K86<>"",IF(H86<>"",IF(H86<>0,K86/H86,""),IF(F86<>"",IF(F86<>0,K86/F86,""),"")),"") -> 0.033898305
A87: SUBTOTAL 28 May 2026 | F87: =SUMIF(F68:F86,"<>",F68:F86) -> 0 | H87: =SUMIF(H86,"<>",H86) -> 590000 | J87: =SUMIF(J86,"<>",J86) -> 610000 | K87: =IF(J87<>"",IF(H87<>"",J87-H87,IF(F87<>"",J87-F87,"")),"") -> 20000 | L87: =IF(K87<>"",IF(H87<>"",IF(H87<>0,K87/H87,""),IF(F87<>"",IF(F87<>0,K87/F87,""),"")),"") -> 0.033898305
A89: 📅 Monday, 01 June 2026
A90: No | B90: Nama Barang | C90: Satuan | D90: Qty | E90: 📊 ESTIMASI | G90: 🧾 REALISASI BELI | I90: 💰 PENJUALAN | K90: 📈 MARGIN | M90: Keterangan
A91: No | B91: Nama Barang | C91: Satuan | D91: Qty | E91: Est. Harga Beli (Rp) | F91: Total Estimasi (Rp) | G91: Harga Beli Nota (Rp) | H91: Total Beli Nota (Rp) | I91: Harga Jual (Rp) | J91: Total Jual (Rp) | K91: Margin (Rp) | L91: Margin (%) | M91: Keterangan
A92: 1 | B92: Asam Jawa | C92: Kg | D92: 1 | F92: =IF(E92<>"",D92*E92,"") | G92: 20000 | H92: =IF(G92<>"",D92*G92,"") -> 20000 | I92: 25000 | J92: =IF(I92<>"",D92*I92,"") -> 25000 | K92: =IF(J92<>"",IF(H92<>"",J92-H92,IF(F92<>"",J92-F92,"")),"") -> 5000 | L92: =IF(K92<>"",IF(H92<>"",IF(H92<>0,K92/H92,""),IF(F92<>"",IF(F92<>0,K92/F92,""),"")),"") -> 0.25
A93: 2 | B93: Ayam Potong | C93: Kg | D93: 215 | F93: =IF(E93<>"",D93*E93,"") | G93: 33000 | H93: =IF(G93<>"",D93*G93,"") -> 7095000 | I93: 38000 | J93: =IF(I93<>"",D93*I93,"") -> 8170000 | K93: =IF(J93<>"",IF(H93<>"",J93-H93,IF(F93<>"",J93-F93,"")),"") -> 1075000 | L93: =IF(K93<>"",IF(H93<>"",IF(H93<>0,K93/H93,""),IF(F93<>"",IF(F93<>0,K93/F93,""),"")),"") -> 0.15151515
A94: 3 | B94: Bawang Bombay | C94: Kg | D94: 4 | F94: =IF(E94<>"",D94*E94,"") | G94: 28000 | H94: =IF(G94<>"",D94*G94,"") -> 112000 | I94: 35000 | J94: =IF(I94<>"",D94*I94,"") -> 140000 | K94: =IF(J94<>"",IF(H94<>"",J94-H94,IF(F94<>"",J94-F94,"")),"") -> 28000 | L94: =IF(K94<>"",IF(H94<>"",IF(H94<>0,K94/H94,""),IF(F94<>"",IF(F94<>0,K94/F94,""),"")),"") -> 0.25
A95: 4 | B95: Bawang Merah Kupas | C95: Kg | D95: 3 | F95: =IF(E95<>"",D95*E95,"") | G95: 40000 | H95: =IF(G95<>"",D95*G95,"") -> 120000 | I95: 45000 | J95: =IF(I95<>"",D95*I95,"") -> 135000 | K95: =IF(J95<>"",IF(H95<>"",J95-H95,IF(F95<>"",J95-F95,"")),"") -> 15000 | L95: =IF(K95<>"",IF(H95<>"",IF(H95<>0,K95/H95,""),IF(F95<>"",IF(F95<>0,K95/F95,""),"")),"") -> 0.125
A96: 5 | B96: Bawang Putih Kupas | C96: Kg | D96: 4 | F96: =IF(E96<>"",D96*E96,"") | G96: 30000 | H96: =IF(G96<>"",D96*G96,"") -> 120000 | I96: 44000 | J96: =IF(I96<>"",D96*I96,"") -> 176000 | K96: =IF(J96<>"",IF(H96<>"",J96-H96,IF(F96<>"",J96-F96,"")),"") -> 56000 | L96: =IF(K96<>"",IF(H96<>"",IF(H96<>0,K96/H96,""),IF(F96<>"",IF(F96<>0,K96/F96,""),"")),"") -> 0.46666667
A97: 6 | B97: Cabai Merah Besar | C97: Kg | D97: 5 | F97: =IF(E97<>"",D97*E97,"") | G97: 60000 | H97: =IF(G97<>"",D97*G97,"") -> 300000 | I97: 70000 | J97: =IF(I97<>"",D97*I97,"") -> 350000 | K97: =IF(J97<>"",IF(H97<>"",J97-H97,IF(F97<>"",J97-F97,"")),"") -> 50000 | L97: =IF(K97<>"",IF(H97<>"",IF(H97<>0,K97/H97,""),IF(F97<>"",IF(F97<>0,K97/F97,""),"")),"") -> 0.16666667
A98: 7 | B98: Cabai Merah Keriting | C98: Kg | D98: 2 | F98: =IF(E98<>"",D98*E98,"") | G98: 65000 | H98: =IF(G98<>"",D98*G98,"") -> 130000 | I98: 75000 | J98: =IF(I98<>"",D98*I98,"") -> 150000 | K98: =IF(J98<>"",IF(H98<>"",J98-H98,IF(F98<>"",J98-F98,"")),"") -> 20000 | L98: =IF(K98<>"",IF(H98<>"",IF(H98<>0,K98/H98,""),IF(F98<>"",IF(F98<>0,K98/F98,""),"")),"") -> 0.15384615
A99: 9 | B99: Daun Salam | C99: Kg | D99: 0.2 | F99: =IF(E99<>"",D99*E99,"") | G99: 32308 | H99: =IF(G99<>"",D99*G99,"") -> 6461.6 | I99: 15000 | J99: =IF(I99<>"",D99*I99,"") -> 3000 | K99: =IF(J99<>"",IF(H99<>"",J99-H99,IF(F99<>"",J99-F99,"")),"") -> -3461.6 | L99: =IF(K99<>"",IF(H99<>"",IF(H99<>0,K99/H99,""),IF(F99<>"",IF(F99<>0,K99/F99,""),"")),"") -> -0.53571871
A100: 10 | B100: Garam Masala | C100: Kg | D100: 7 | F100: =IF(E100<>"",D100*E100,"") | G100: 30000 | H100: =IF(G100<>"",D100*G100,"") -> 210000 | I100: 35000 | J100: =IF(I100<>"",D100*I100,"") -> 245000 | K100: =IF(J100<>"",IF(H100<>"",J100-H100,IF(F100<>"",J100-F100,"")),"") -> 35000 | L100: =IF(K100<>"",IF(H100<>"",IF(H100<>0,K100/H100,""),IF(F100<>"",IF(F100<>0,K100/F100,""),"")),"") -> 0.16666667
A101: 11 | B101: Gula Merah | C101: Kg | D101: 5 | F101: =IF(E101<>"",D101*E101,"") | G101: 16000 | H101: =IF(G101<>"",D101*G101,"") -> 80000 | I101: 22000 | J101: =IF(I101<>"",D101*I101,"") -> 110000 | K101: =IF(J101<>"",IF(H101<>"",J101-H101,IF(F101<>"",J101-F101,"")),"") -> 30000 | L101: =IF(K101<>"",IF(H101<>"",IF(H101<>0,K101/H101,""),IF(F101<>"",IF(F101<>0,K101/F101,""),"")),"") -> 0.375
A102: 12 | B102: Jahe | C102: Kg | D102: 1 | F102: =IF(E102<>"",D102*E102,"") | G102: 20000 | H102: =IF(G102<>"",D102*G102,"") -> 20000 | I102: 26000 | J102: =IF(I102<>"",D102*I102,"") -> 26000 | K102: =IF(J102<>"",IF(H102<>"",J102-H102,IF(F102<>"",J102-F102,"")),"") -> 6000 | L102: =IF(K102<>"",IF(H102<>"",IF(H102<>0,K102/H102,""),IF(F102<>"",IF(F102<>0,K102/F102,""),"")),"") -> 0.3
A103: 13 | B103: Kecap Manis | C103: Dirigen | D103: 4 | F103: =IF(E103<>"",D103*E103,"") | G103: 190000 | H103: =IF(G103<>"",D103*G103,"") -> 760000 | I103: 210000 | J103: =IF(I103<>"",D103*I103,"") -> 840000 | K103: =IF(J103<>"",IF(H103<>"",J103-H103,IF(F103<>"",J103-F103,"")),"") -> 80000 | L103: =IF(K103<>"",IF(H103<>"",IF(H103<>0,K103/H103,""),IF(F103<>"",IF(F103<>0,K103/F103,""),"")),"") -> 0.10526316
... A113: 23 | B113: Wortel | C113: Kg | D113: 30 | F113: =IF(E113<>"",D113*E113,"") | G113: 15000 | H113: =IF(G113<>"",D113*G113,"") -> 450000 | I113: 18000 | J113: =IF(I113<>"",D113*I113,"") -> 540000 | K113: =IF(J113<>"",IF(H113<>"",J113-H113,IF(F113<>"",J113-F113,"")),"") -> 90000 | L113: =IF(K113<>"",IF(H113<>"",IF(H113<>0,K113/H113,""),IF(F113<>"",IF(F113<>0,K113/F113,""),"")),"") -> 0.2
A114: SUBTOTAL 01 Jun 2026 | F114: =SUMIF(F92:F113,"<>",F92:F113) -> 0 | H114: =SUMIF(H92:H113,"<>",H92:H113) -> 14845795 | J114: =SUMIF(J92:J113,"<>",J92:J113) -> 17128500 | K114: =IF(J114<>"",IF(H114<>"",J114-H114,IF(F114<>"",J114-F114,"")),"") -> 2282704.9 | L114: =IF(K114<>"",IF(H114<>"",IF(H114<>0,K114/H114,""),IF(F114<>"",IF(F114<>0,K114/F114,""),"")),"") -> 0.15376104
A116: 📅 Tuesday, 02 June 2026
A117: No | B117: Nama Barang | C117: Satuan | D117: Qty | E117: 📊 ESTIMASI | G117: 🧾 REALISASI BELI | I117: 💰 PENJUALAN | K117: 📈 MARGIN | M117: Keterangan
A118: No | B118: Nama Barang | C118: Satuan | D118: Qty | E118: Est. Harga Beli (Rp) | F118: Total Estimasi (Rp) | G118: Harga Beli Nota (Rp) | H118: Total Beli Nota (Rp) | I118: Harga Jual (Rp) | J118: Total Jual (Rp) | K118: Margin (Rp) | L118: Margin (%) | M118: Keterangan
...

Sheet Invoice OPS B02
A1: 🧾 DRAFT INVOICE — BAKUNG 02
A2: Periode: 24–29 Mei 2026 | 🟢 Hijau = linked Daftar Harga | 🔵 Biru = input manual (isi setelah nota datang)
A3: Kolom G (Harga Beli Nota) dikosongkan — isi saat barang tiba. Margin: pakai Nota jika ada, fallback ke Estimasi.
A4: 📅 Sunday, 24 May 2026
A5: No | B5: Nama Barang | C5: Satuan | D5: Qty | E5: 📊 ESTIMASI | G5: 🧾 REALISASI BELI | I5: 💰 PENJUALAN | K5: 📈 MARGIN | M5: Keterangan
A6: No | B6: Nama Barang | C6: Satuan | D6: Qty | E6: Est. Harga Beli (Rp) | F6: Total Estimasi (Rp) | G6: Harga Beli Nota (Rp) | H6: Total Beli Nota (Rp) | I6: Harga Jual (Rp) | J6: Total Jual (Rp) | K6: Margin (Rp) | L6: Margin (%) | M6: Keterangan
A7: 1 | B7: Trashbag | C7: Pack | D7: 20 | F7: =IF(E7<>"",D7*E7,"") | G7: 9000 | H7: =IF(G7<>"",D7*G7,"") -> 180000 | I7: 13000 | J7: =IF(I7<>"",D7*I7,"") -> 260000 | K7: =IF(J7<>"",IF(H7<>"",J7-H7,IF(F7<>"",J7-F7,"")),"") -> 80000 | L7: =IF(K7<>"",IF(H7<>"",IF(H7<>0,K7/H7,""),IF(F7<>"",IF(F7<>0,K7/F7,""),"")),"") -> 0.44444444
A8: 2 | B8: Wipol | C8: Botol | D8: 5 | F8: =IF(E8<>"",D8*E8,"") | G8: 20000 | H8: =IF(G8<>"",D8*G8,"") -> 100000 | I8: 25000 | J8: =IF(I8<>"",D8*I8,"") -> 125000 | K8: =IF(J8<>"",IF(H8<>"",J8-H8,IF(F8<>"",J8-F8,"")),"") -> 25000 | L8: =IF(K8<>"",IF(H8<>"",IF(H8<>0,K8/H8,""),IF(F8<>"",IF(F8<>0,K8/F8,""),"")),"") -> 0.25
A9: 3 | B9: Soklin Lantai | C9: Drigen | D9: 2 | F9: =IF(E9<>"",D9*E9,"") | G9: 53000 | H9: =IF(G9<>"",D9*G9,"") -> 106000 | I9: 75000 | J9: =IF(I9<>"",D9*I9,"") -> 150000 | K9: =IF(J9<>"",IF(H9<>"",J9-H9,IF(F9<>"",J9-F9,"")),"") -> 44000 | L9: =IF(K9<>"",IF(H9<>"",IF(H9<>0,K9/H9,""),IF(F9<>"",IF(F9<>0,K9/F9,""),"")),"") -> 0.41509434
A10: SUBTOTAL 24 May 2026 | F10: =SUMIF(F7:F9,"<>",F7:F9) -> 0 | H10: =SUMIF(H7:H9,"<>",H7:H9) -> 386000 | J10: =SUMIF(J7:J9,"<>",J7:J9) -> 535000 | K10: =IF(J10<>"",IF(H10<>"",J10-H10,IF(F10<>"",J10-F10,"")),"") -> 149000 | L10: =IF(K10<>"",IF(H10<>"",IF(H10<>0,K10/H10,""),IF(F10<>"",IF(F10<>0,K10/F10,""),"")),"") -> 0.38601036
A12: 📅 Monday, 25 May 2026
A13: No | B13: Nama Barang | C13: Satuan | D13: Qty | E13: 📊 ESTIMASI | G13: 🧾 REALISASI BELI | I13: 💰 PENJUALAN | K13: 📈 MARGIN | M13: Keterangan
A14: No | B14: Nama Barang | C14: Satuan | D14: Qty | E14: Est. Harga Beli (Rp) | F14: Total Estimasi (Rp) | G14: Harga Beli Nota (Rp) | H14: Total Beli Nota (Rp) | I14: Harga Jual (Rp) | J14: Total Jual (Rp) | K14: Margin (Rp) | L14: Margin (%) | M14: Keterangan
A15: 1 | B15: Air Mineral Galon | C15: Galon | D15: 60 | F15: =IF(E15<>"",D15*E15,"") | G15: 19200 | H15: =IF(G15<>"",D15*G15,"") -> 1152000 | I15: 22500 | J15: =IF(I15<>"",D15*I15,"") -> 1350000 | K15: =IF(J15<>"",IF(H15<>"",J15-H15,IF(F15<>"",J15-F15,"")),"") -> 198000 | L15: =IF(K15<>"",IF(H15<>"",IF(H15<>0,K15/H15,""),IF(F15<>"",IF(F15<>0,K15/F15,""),"")),"") -> 0.171875
A16: 2 | B16: Dingklik/Jengkok | C16: Pcs | D16: 16 | F16: =IF(E16<>"",D16*E16,"") | G16: 40000 | H16: =IF(G16<>"",D16*G16,"") -> 640000 | I16: 50000 | J16: =IF(I16<>"",D16*I16,"") -> 800000 | K16: =IF(J16<>"",IF(H16<>"",J16-H16,IF(F16<>"",J16-F16,"")),"") -> 160000 | L16: =IF(K16<>"",IF(H16<>"",IF(H16<>0,K16/H16,""),IF(F16<>"",IF(F16<>0,K16/F16,""),"")),"") -> 0.25
A17: 3 | B17: Plastik Es 12x25 | C17: Pack | D17: 20 | F17: =IF(E17<>"",D17*E17,"") | G17: 13000 | H17: =IF(G17<>"",D17*G17,"") -> 260000 | I17: 17500 | J17: =IF(I17<>"",D17*I17,"") -> 350000 | K17: =IF(J17<>"",IF(H17<>"",J17-H17,IF(F17<>"",J17-F17,"")),"") -> 90000 | L17: =IF(K17<>"",IF(H17<>"",IF(H17<>0,K17/H17,""),IF(F17<>"",IF(F17<>0,K17/F17,""),"")),"") -> 0.34615385
A18: 4 | B18: Tisu Dapur | C18: Pcs | D18: 10 | F18: =IF(E18<>"",D18*E18,"") | G18: 15500 | H18: =IF(G18<>"",D18*G18,"") -> 155000 | I18: 20000 | J18: =IF(I18<>"",D18*I18,"") -> 200000 | K18: =IF(J18<>"",IF(H18<>"",J18-H18,IF(F18<>"",J18-F18,"")),"") -> 45000 | L18: =IF(K18<>"",IF(H18<>"",IF(H18<>0,K18/H18,""),IF(F18<>"",IF(F18<>0,K18/F18,""),"")),"") -> 0.29032258
A19: 5 | B19: Gas 50Kg | C19: Tabung | D19: 1 | F19: =IF(E19<>"",D19*E19,"") | G19: 1125000 | H19: =IF(G19<>"",D19*G19,"") -> 1125000 | I19: 1250000 | J19: =IF(I19<>"",D19*I19,"") -> 1250000 | K19: =IF(J19<>"",IF(H19<>"",J19-H19,IF(F19<>"",J19-F19,"")),"") -> 125000 | L19: =IF(K19<>"",IF(H19<>"",IF(H19<>0,K19/H19,""),IF(F19<>"",IF(F19<>0,K19/F19,""),"")),"") -> 0.11111111
A20: 6 | B20: Tisu Wajah | C20: Pcs | D20: 10 | F20: =IF(E20<>"",D20*E20,"") | G20: 9000 | H20: =IF(G20<>"",D20*G20,"") -> 90000 | I20: 13000 | J20: =IF(I20<>"",D20*I20,"") -> 130000 | K20: =IF(J20<>"",IF(H20<>"",J20-H20,IF(F20<>"",J20-F20,"")),"") -> 40000 | L20: =IF(K20<>"",IF(H20<>"",IF(H20<>0,K20/H20,""),IF(F20<>"",IF(F20<>0,K20/F20,""),"")),"") -> 0.44444444
A21: SUBTOTAL 25 May 2026 | F21: =SUMIF(F15:F20,"<>",F15:F20) -> 0 | H21: =SUMIF(H15:H20,"<>",H15:H20) -> 3422000 | J21: =SUMIF(J15:J20,"<>",J15:J20) -> 4080000 | K21: =IF(J21<>"",IF(H21<>"",J21-H21,IF(F21<>"",J21-F21,"")),"") -> 658000 | L21: =IF(K21<>"",IF(H21<>"",IF(H21<>0,K21/H21,""),IF(F21<>"",IF(F21<>0,K21/F21,""),"")),"") -> 0.19228521
A23: 📅 Thursday, 28 May 2026
A24: No | B24: Nama Barang | C24: Satuan | D24: Qty | E24: 📊 ESTIMASI | G24: 🧾 REALISASI BELI | I24: 💰 PENJUALAN | K24: 📈 MARGIN | M24: Keterangan
A25: No | B25: Nama Barang | C25: Satuan | D25: Qty | E25: Est. Harga Beli (Rp) | F25: Total Estimasi (Rp) | G25: Harga Beli Nota (Rp) | H25: Total Beli Nota (Rp) | I25: Harga Jual (Rp) | J25: Total Jual (Rp) | K25: Margin (Rp) | L25: Margin (%) | M25: Keterangan
A26: 1 | B26: Teflon Maxim 28CM | C26: Karton | D26: 4 | F26: =IF(E26<>"",D26*E26,"") | G26: 165000 | H26: =IF(G26<>"",D26*G26,"") -> 660000 | I26: 175000 | J26: =IF(I26<>"",D26*I26,"") -> 700000 | K26: =IF(J26<>"",IF(H26<>"",J26-H26,IF(F26<>"",J26-F26,"")),"") -> 40000 | L26: =IF(K26<>"",IF(H26<>"",IF(H26<>0,K26/H26,""),IF(F26<>"",IF(F26<>0,K26/F26,""),"")),"") -> 0.060606061
A27: 2 | B27: Gas 50kg | C27: Dus | D27: 1 | F27: =IF(E27<>"",D27*E27,"") | G27: 1125000 | H27: =IF(G27<>"",D27*G27,"") -> 1125000 | I27: 1250000 | J27: =IF(I27<>"",D27*I27,"") -> 1250000 | K27: =IF(J27<>"",IF(H27<>"",J27-H27,IF(F27<>"",J27-F27,"")),"") -> 125000 | L27: =IF(K27<>"",IF(H27<>"",IF(H27<>0,K27/H27,""),IF(F27<>"",IF(F27<>0,K27/F27,""),"")),"") -> 0.11111111
A28: SUBTOTAL 28 May 2026 | F28: =SUMIF(F26:F27,"<>",F26:F27) -> 0 | H28: =SUMIF(H26:H27,"<>",H26:H27) -> 1785000 | J28: =SUMIF(J26:J27,"<>",J26:J27) -> 1950000 | K28: =IF(J28<>"",IF(H28<>"",J28-H28,IF(F28<>"",J28-F28,"")),"") -> 165000 | L28: =IF(K28<>"",IF(H28<>"",IF(H28<>0,K28/H28,""),IF(F28<>"",IF(F28<>0,K28/F28,""),"")),"") -> 0.092436975
A30: 📅 Friday, 29 May 2026
A31: No | B31: Nama Barang | C31: Satuan | D31: Qty | E31: 📊 ESTIMASI | G31: 🧾 REALISASI BELI | I31: 💰 PENJUALAN | K31: 📈 MARGIN | M31: Keterangan
A32: No | B32: Nama Barang | C32: Satuan | D32: Qty | E32: Est. Harga Beli (Rp) | F32: Total Estimasi (Rp) | G32: Harga Beli Nota (Rp) | H32: Total Beli Nota (Rp) | I32: Harga Jual (Rp) | J32: Total Jual (Rp) | K32: Margin (Rp) | L32: Margin (%) | M32: Keterangan
A33: 1 | B33: Gas 50Kg | C33: Tabung | D33: 2 | F33: =IF(E33<>"",D33*E33,"") | G33: 1125000 | H33: =IF(G33<>"",D33*G33,"") -> 2250000 | I33: 1250000 | J33: =D33*I33 -> 2500000 | K33: =IF(J33<>"",IF(H33<>"",J33-H33,IF(F33<>"",J33-F33,"")),"") -> 250000 | L33: =IF(K33<>"",IF(H33<>"",IF(H33<>0,K33/H33,""),IF(F33<>"",IF(F33<>0,K33/F33,""),"")),"") -> 0.11111111
A34: SUBTOTAL 28 May 2026 | F34: =SUMIF(F33,"<>",F33) -> 0 | H34: =SUMIF(H33,"<>",H33) -> 2250000 | J34: =SUMIF(J33,"<>",J33) -> 2500000 | K34: =IF(J34<>"",IF(H34<>"",J34-H34,IF(F34<>"",J34-F34,"")),"") -> 250000 | L34: =IF(K34<>"",IF(H34<>"",IF(H34<>0,K34/H34,""),IF(F34<>"",IF(F34<>0,K34/F34,""),"")),"") -> 0.11111111
D36: 📅 Monday, 01 June 2026
A37: No | B37: Nama Barang | C37: Satuan | D37: Qty | E37: 📊 ESTIMASI | G37: 🧾 REALISASI BELI | I37: 💰 PENJUALAN | K37: 📈 MARGIN | M37: Keterangan
A38: No | B38: Nama Barang | C38: Satuan | D38: Qty | E38: Est. Harga Beli (Rp) | F38: Total Estimasi (Rp) | G38: Harga Beli Nota (Rp) | H38: Total Beli Nota (Rp) | I38: Harga Jual (Rp) | J38: Total Jual (Rp) | K38: Margin (Rp) | L38: Margin (%) | M38: Keterangan
A39: 1 | B39: So Klin Lantai Sereh | C39: Drigen | D39: 1 | F39: =IF(E39<>"",D39*E39,"") | G39: 53000 | H39: =IF(G39<>"",D39*G39,"") -> 53000 | I39: 80000 | J39: =IF(I39<>"",D39*I39,"") -> 80000 | K39: =IF(J39<>"",IF(H39<>"",J39-H39,IF(F39<>"",J39-F39,"")),"") -> 27000 | L39: =IF(K39<>"",IF(H39<>"",IF(H39<>0,K39/H39,""),IF(F39<>"",IF(F39<>0,K39/F39,""),"")),"") -> 0.50943396
A40: 2 | B40: Cup Sambal 25 ml | C40: Pcs | D40: 1350 | F40: =IF(E40<>"",D40*E40,"") | G40: 260 | H40: =IF(G40<>"",D40*G40,"") -> 351000 | I40: 300 | J40: =IF(I40<>"",D40*I40,"") -> 405000 | K40: =IF(J40<>"",IF(H40<>"",J40-H40,IF(F40<>"",J40-F40,"")),"") -> 54000 | L40: =IF(K40<>"",IF(H40<>"",IF(H40<>0,K40/H40,""),IF(F40<>"",IF(F40<>0,K40/F40,""),"")),"") -> 0.15384615
A41: 3 | B41: Plastik Es Ukuran 12x25 100's | C41: Pack | D41: 20 | F41: =IF(E41<>"",D41*E41,"") | G41: 13000 | H41: =IF(G41<>"",D41*G41,"") -> 260000 | I41: 17500 | J41: =IF(I41<>"",D41*I41,"") -> 350000 | K41: =IF(J41<>"",IF(H41<>"",J41-H41,IF(F41<>"",J41-F41,"")),"") -> 90000 | L41: =IF(K41<>"",IF(H41<>"",IF(H41<>0,K41/H41,""),IF(F41<>"",IF(F41<>0,K41/F41,""),"")),"") -> 0.34615385
A42: 4 | B42: Trashbag | C42: Pack | D42: 10 | F42: =IF(E42<>"",D42*E42,"") | G42: 9000 | H42: =IF(G42<>"",D42*G42,"") -> 90000 | I42: 13000 | J42: =IF(I42<>"",D42*I42,"") -> 130000 | K42: =IF(J42<>"",IF(H42<>"",J42-H42,IF(F42<>"",J42-F42,"")),"") -> 40000 | L42: =IF(K42<>"",IF(H42<>"",IF(H42<>0,K42/H42,""),IF(F42<>"",IF(F42<>0,K42/F42,""),"")),"") -> 0.44444444
A43: 5 | B43: Spons Cuci Piring Scotch Brite | C43: Pcs | D43: 10 | F43: =IF(E43<>"",D43*E43,"") | G43: 2000 | H43: =IF(G43<>"",D43*G43,"") -> 20000 | I43: 3000 | J43: =IF(I43<>"",D43*I43,"") -> 30000 | K43: =IF(J43<>"",IF(H43<>"",J43-H43,IF(F43<>"",J43-F43,"")),"") -> 10000 | L43: =IF(K43<>"",IF(H43<>"",IF(H43<>0,K43/H43,""),IF(F43<>"",IF(F43<>0,K43/F43,""),"")),"") -> 0.5
A44: 01 June SUBTOTAL | F44: =SUMIF(F39:F43,"<>",F39:F43) -> 0 | H44: =SUMIF(H39:H43,"<>",H39:H43) -> 774000 | J44: =SUMIF(J39:J43,"<>",J39:J43) -> 995000
D46: 📅 Tuesday, 02 June 2026
A47: No | B47: Nama Barang | C47: Satuan | D47: Qty | E47: 📊 ESTIMASI | G47: 🧾 REALISASI BELI | I47: 💰 PENJUALAN | K47: 📈 MARGIN | M47: Keterangan
A48: No | B48: Nama Barang | C48: Satuan | D48: Qty | E48: Est. Harga Beli (Rp) | F48: Total Estimasi (Rp) | G48: Harga Beli Nota (Rp) | H48: Total Beli Nota (Rp) | I48: Harga Jual (Rp) | J48: Total Jual (Rp) | K48: Margin (Rp) | L48: Margin (%) | M48: Keterangan
A49: 1 | B49: Sabun Cuci Ompreng Mama Lemon/Ekonomi | C49: Drigen | D49: 6 | F49: =IF(E49<>"",D49*E49,"") | G49: 65000 | H49: =IF(G49<>"",D49*G49,"") -> 390000 | I49: 90000 | J49: =IF(I49<>"",D49*I49,"") -> 540000 | K49: =IF(J49<>"",IF(H49<>"",J49-H49,IF(F49<>"",J49-F49,"")),"") -> 150000 | L49: =IF(K49<>"",IF(H49<>"",IF(H49<>0,K49/H49,""),IF(F49<>"",IF(F49<>0,K49/F49,""),"")),"") -> 0.38461538
A50: 2 | B50: Sabun Khusus Cuci Mobil | C50: Botol | D50: 1 | F50: =IF(E50<>"",D50*E50,"") | G50: 15000 | H50: =IF(G50<>"",D50*G50,"") -> 15000 | I50: 20000 | J50: =IF(I50<>"",D50*I50,"") -> 20000 | K50: =IF(J50<>"",IF(H50<>"",J50-H50,IF(F50<>"",J50-F50,"")),"") -> 5000 | L50: =IF(K50<>"",IF(H50<>"",IF(H50<>0,K50/H50,""),IF(F50<>"",IF(F50<>0,K50/F50,""),"")),"") -> 0.33333333
A51: 3 | B51: Hit Pink Blossom | C51: Pcs | D51: 2 | F51: =IF(E51<>"",D51*E51,"") | G51: 32500 | H51: =IF(G51<>"",D51*G51,"") -> 65000 | I51: 40000 | J51: =IF(I51<>"",D51*I51,"") -> 80000 | K51: =IF(J51<>"",IF(H51<>"",J51-H51,IF(F51<>"",J51-F51,"")),"") -> 15000 | L51: =IF(K51<>"",IF(H51<>"",IF(H51<>0,K51/H51,""),IF(F51<>"",IF(F51<>0,K51/F51,""),"")),"") -> 0.23076923
A52: 4 | B52: Lap/Serbet Dapur | C52: Pcs | D52: 10 | F52: =IF(E52<>"",D52*E52,"") | G52: 9670 | H52: =IF(G52<>"",D52*G52,"") -> 96700 | I52: 10000 | J52: =IF(I52<>"",D52*I52,"") -> 100000 | K52: =IF(J52<>"",IF(H52<>"",J52-H52,IF(F52<>"",J52-F52,"")),"") -> 3300 | L52: =IF(K52<>"",IF(H52<>"",IF(H52<>0,K52/H52,""),IF(F52<>"",IF(F52<>0,K52/F52,""),"")),"") -> 0.034126163
A53: 5 | B53: Map Tulang | C53: Pack | D53: 2 | F53: =IF(E53<>"",D53*E53,"") | G53: 3500 | H53: =IF(G53<>"",D53*G53,"") -> 7000 | I53: 50000 | J53: =IF(I53<>"",D53*I53,"") -> 100000 | K53: =IF(J53<>"",IF(H53<>"",J53-H53,IF(F53<>"",J53-F53,"")),"") -> 93000 | L53: =IF(K53<>"",IF(H53<>"",IF(H53<>0,K53/H53,""),IF(F53<>"",IF(F53<>0,K53/F53,""),"")),"") -> 13.285714
A54: 6 | B54: Plastik Packing MBG uk 25x30cm (isi 100) | C54: Pack | D54: 15 | G54: 42000 | H54: =IF(G54<>"",D54*G54,"") -> 630000 | I54: 50000 | J54: =IF(I54<>"",D54*I54,"") -> 750000 | K54: =IF(J54<>"",IF(H54<>"",J54-H54,IF(F54<>"",J54-F54,"")),"") -> 120000 | L54: =IF(K54<>"",IF(H54<>"",IF(H54<>0,K54/H54,""),IF(F54<>"",IF(F54<>0,K54/F54,""),"")),"") -> 0.19047619
A55: 7 | B55: Gas 50kg | C55: Tabung | D55: 1 | G55: 1125000 | H55: =IF(G55<>"",D55*G55,"") -> 1125000 | I55: 1250000 | J55: =IF(I55<>"",D55*I55,"") -> 1250000 | K55: =IF(J55<>"",IF(H55<>"",J55-H55,IF(F55<>"",J55-F55,"")),"") -> 125000 | L55: =IF(K55<>"",IF(H55<>"",IF(H55<>0,K55/H55,""),IF(F55<>"",IF(F55<>0,K55/F55,""),"")),"") -> 0.11111111
A56: 02 June SUBTOTAL | F56: =SUMIF(F49:F55,"<>",F49:F55) -> 0 | H56: =SUMIF(H49:H55,"<>",H49:H55) -> 2328700 | J56: =SUMIF(J49:J55,"<>",J49:J55) -> 2840000 | K56: =IF(J56<>"",IF(H56<>"",J56-H56,IF(F56<>"",J56-F56,"")),"") -> 511300 | L56: =IF(K56<>"",IF(H56<>"",IF(H56<>0,K56/H56,""),IF(F56<>"",IF(F56<>0,K56/F56,""),"")),"") -> 0.21956456
D58: 📅 Wednesday, 03 June 2026
A59: No | B59: Nama Barang | C59: Satuan | D59: Qty | E59: 📊 ESTIMASI | G59: 🧾 REALISASI BELI | I59: 💰 PENJUALAN | K59: 📈 MARGIN | M59: Keterangan
A60: No | B60: Nama Barang | C60: Satuan | D60: Qty | E60: Est. Harga Beli (Rp) | F60: Total Estimasi (Rp) | G60: Harga Beli Nota (Rp) | H60: Total Beli Nota (Rp) | I60: Harga Jual (Rp) | J60: Total Jual (Rp) | K60: Margin (Rp) | L60: Margin (%) | M60: Keterangan
A61: 1 | B61: Gas 50Kg | C61: Tabung | D61: 1 | F61: =IF(E61<>"",D61*E61,"") | G61: 1125000 | H61: =IF(G61<>"",D61*G61,"") -> 1125000 | I61: 1250000 | J61: =IF(I61<>"",D61*I61,"") -> 1250000 | K61: =IF(J61<>"",IF(H61<>"",J61-H61,IF(F61<>"",J61-F61,"")),"") -> 125000 | L61: =IF(K61<>"",IF(H61<>"",IF(H61<>0,K61/H61,""),IF(F61<>"",IF(F61<>0,K61/F61,""),"")),"") -> 0.11111111
A62: 2 | B62: Gas 12Kg | C62: Tabung | D62: 1 | F62: =IF(E62<>"",D62*E62,"") | G62: 255000 | H62: =IF(G62<>"",D62*G62,"") -> 255000 | I62: 295000 | J62: =IF(I62<>"",D62*I62,"") -> 295000 | K62: =IF(J62<>"",IF(H62<>"",J62-H62,IF(F62<>"",J62-F62,"")),"") -> 40000 | L62: =IF(K62<>"",IF(H62<>"",IF(H62<>0,K62/H62,""),IF(F62<>"",IF(F62<>0,K62/F62,""),"")),"") -> 0.15686275
A63: 3 | B63: Thinwall UK 200 ml | C63: Pcs | D63: 2500 | F63: =IF(E63<>"",D63*E63,"") | G63: 540 | H63: =IF(G63<>"",D63*G63,"") -> 1350000 | I63: 650 | J63: =IF(I63<>"",D63*I63,"") -> 1625000 | K63: =IF(J63<>"",IF(H63<>"",J63-H63,IF(F63<>"",J63-F63,"")),"") -> 275000 | L63: =IF(K63<>"",IF(H63<>"",IF(H63<>0,K63/H63,""),IF(F63<>"",IF(F63<>0,K63/F63,""),"")),"") -> 0.2037037
A64: 4 | B64: Plastik Es 12x25 | C64: Pack | D64: 20 | F64: =IF(E64<>"",D64*E64,"") | G64: 13000 | H64: =IF(G64<>"",D64*G64,"") -> 260000 | I64: 17500 | J64: =IF(I64<>"",D64*I64,"") -> 350000 | K64: =IF(J64<>"",IF(H64<>"",J64-H64,IF(F64<>"",J64-F64,"")),"") -> 90000 | L64: =IF(K64<>"",IF(H64<>"",IF(H64<>0,K64/H64,""),IF(F64<>"",IF(F64<>0,K64/F64,""),"")),"") -> 0.34615385
A65: 5 | B65: Obat IPAL BIO-L | C65: Pack | D65: 4 | F65: =IF(E65<>"",D65*E65,"") | G65: 42000 | H65: =IF(G65<>"",D65*G65,"") -> 168000 | I65: 55000 | J65: =IF(I65<>"",D65*I65,"") -> 220000 | K65: =IF(J65<>"",IF(H65<>"",J65-H65,IF(F65<>"",J65-F65,"")),"") -> 52000 | L65: =IF(K65<>"",IF(H65<>"",IF(H65<>0,K65/H65,""),IF(F65<>"",IF(F65<>0,K65/F65,""),"")),"") -> 0.30952381
A66: 03 June SUBTOTAL | F66: =SUMIF(F61:F65,"<>",F61:F65) -> 0 | H66: =SUMIF(H61:H65,"<>",H61:H65) -> 3158000 | J66: =SUMIF(J61:J65,"<>",J61:J65) -> 3740000 | K66: =IF(J66<>"",IF(H66<>"",J66-H66,IF(F66<>"",J66-F66,"")),"") -> 582000 | L66: =IF(K66<>"",IF(H66<>"",IF(H66<>0,K66/H66,""),IF(F66<>"",IF(F66<>0,K66/F66,""),"")),"") -> 0.18429386
D68: 📅 Thursday, 04 June 2026
A69: No | B69: Nama Barang | C69: Satuan | D69: Qty | E69: 📊 ESTIMASI | G69: 🧾 REALISASI BELI | I69: 💰 PENJUALAN | K69: 📈 MARGIN | M69: Keterangan
A70: No | B70: Nama Barang | C70: Satuan | D70: Qty | E70: Est. Harga Beli (Rp) | F70: Total Estimasi (Rp) | G70: Harga Beli Nota (Rp) | H70: Total Beli Nota (Rp) | I70: Harga Jual (Rp) | J70: Total Jual (Rp) | K70: Margin (Rp) | L70: Margin (%) | M70: Keterangan
A71: 1 | B71: Gas 50Kg | C71: Tabung | D71: 2 | F71: =IF(E71<>"",D71*E71,"") | G71: 1125000 | H71: =IF(G71<>"",D71*G71,"") -> 2250000 | I71: 1250000 | J71: =IF(I71<>"",D71*I71,"") -> 2500000 | K71: =IF(J71<>"",IF(H71<>"",J71-H71,IF(F71<>"",J71-F71,"")),"") -> 250000 | L71: =IF(K71<>"",IF(H71<>"",IF(H71<>0,K71/H71,""),IF(F71<>"",IF(F71<>0,K71/F71,""),"")),"") -> 0.11111111
A72: 2 | B72: Gas 12Kg | C72: Tabung | D72: 1 | F72: =IF(E72<>"",D72*E72,"") | G72: 255000 | H72: =IF(G72<>"",D72*G72,"") -> 255000 | I72: 295000 | J72: =IF(I72<>"",D72*I72,"") -> 295000 | K72: =IF(J72<>"",IF(H72<>"",J72-H72,IF(F72<>"",J72-F72,"")),"") -> 40000 | L72: =IF(K72<>"",IF(H72<>"",IF(H72<>0,K72/H72,""),IF(F72<>"",IF(F72<>0,K72/F72,""),"")),"") -> 0.15686275
A73: 04 June SUBTOTAL | F73: =SUMIF(F71:F72,"<>",F71:F72) -> 0 | H73: =SUMIF(H71:H72,"<>",H71:H72) -> 2505000 | J73: =SUMIF(J71:J72,"<>",J71:J72) -> 2795000 | K73: =IF(J73<>"",IF(H73<>"",J73-H73,IF(F73<>"",J73-F73,"")),"") -> 290000 | L73: =IF(K73<>"",IF(H73<>"",IF(H73<>0,K73/H73,""),IF(F73<>"",IF(F73<>0,K73/F73,""),"")),"") -> 0.11576846
C75: 📅 Friday, 05 June 2026
A76: No | B76: Nama Barang | C76: Satuan | D76: Qty | E76: 📊 ESTIMASI | G76: 🧾 REALISASI BELI | I76: 💰 PENJUALAN | K76: 📈 MARGIN | M76: Keterangan
A77: No | B77: Nama Barang | C77: Satuan | D77: Qty | E77: Est. Harga Beli (Rp) | F77: Total Estimasi (Rp) | G77: Harga Beli Nota (Rp) | H77: Total Beli Nota (Rp) | I77: Harga Jual (Rp) | J77: Total Jual (Rp) | K77: Margin (Rp) | L77: Margin (%) | M77: Keterangan
A78: 1 | B78: Sewa Daihatsu Grand Max | C78: unit | D78: 1 | F78: =IF(E78<>"",D78*E78,"") | G78: 3272000 | H78: =IF(G78<>"",D78*G78,"") -> 3272000 | I78: 3272000 | J78: =IF(I78<>"",D78*I78,"") -> 3272000 | K78: =IF(J78<>"",IF(H78<>"",J78-H78,IF(F78<>"",J78-F78,"")),"") -> 0 | L78: =IF(K78<>"",IF(H78<>"",IF(H78<>0,K78/H78,""),IF(F78<>"",IF(F78<>0,K78/F78,""),"")),"") -> 0
A79: 2 | B79: Sewa Traga | C79: unit | D79: 1 | F79: =IF(E79<>"",D79*E79,"") | G79: 3272000 | H79: =IF(G79<>"",D79*G79,"") -> 3272000 | I79: 3272000 | J79: =IF(I79<>"",D79*I79,"") -> 3272000 | K79: =IF(J79<>"",IF(H79<>"",J79-H79,IF(F79<>"",J79-F79,"")),"") -> 0 | L79: =IF(K79<>"",IF(H79<>"",IF(H79<>0,K79/H79,""),IF(F79<>"",IF(F79<>0,K79/F79,""),"")),"") -> 0
A80: 05 June SUBTOTAL | F80: =SUMIF(F78:F79,"<>",F78:F79) -> 0 | H80: =SUMIF(H78:H79,"<>",H78:H79) -> 6544000 | J80: =SUMIF(J78:J79,"<>",J78:J79) -> 6544000 | K80: =IF(J80<>"",IF(H80<>"",J80-H80,IF(F80<>"",J80-F80,"")),"") -> 0 | L80: =IF(K80<>"",IF(H80<>"",IF(H80<>0,K80/H80,""),IF(F80<>"",IF(F80<>0,K80/F80,""),"")),"") -> 0
C82: 📅 Friday, 05 June 2026
A83: No | B83: Nama Barang | C83: Satuan | D83: Qty | E83: 📊 ESTIMASI | G83: 🧾 REALISASI BELI | I83: 💰 PENJUALAN | K83: 📈 MARGIN | M83: Keterangan
A84: No | B84: Nama Barang | C84: Satuan | D84: Qty | E84: Est. Harga Beli (Rp) | F84: Total Estimasi (Rp) | G84: Harga Beli Nota (Rp) | H84: Total Beli Nota (Rp) | I84: Harga Jual (Rp) | J84: Total Jual (Rp) | K84: Margin (Rp) | L84: Margin (%) | M84: Keterangan
A85: 1 | B85: Gas 50kg | C85: Tabung | D85: 1 | F85: =IF(E85<>"",D85*E85,"") | G85: 1125000 | H85: =IF(G85<>"",D85*G85,"") -> 1125000 | I85: 1250000 | J85: =IF(I85<>"",D85*I85,"") -> 1250000 | K85: =IF(J85<>"",IF(H85<>"",J85-H85,IF(F85<>"",J85-F85,"")),"") -> 125000 | L85: =IF(K85<>"",IF(H85<>"",IF(H85<>0,K85/H85,""),IF(F85<>"",IF(F85<>0,K85/F85,""),"")),"") -> 0.11111111
A86: 05 June SUBTOTAL | F86: =SUMIF(F85,"<>",F85) -> 0 | H86: =SUMIF(H85,"<>",H85) -> 1125000 | J86: =SUMIF(J85,"<>",J85) -> 1250000 | K86: =IF(J86<>"",IF(H86<>"",J86-H86,IF(F86<>"",J86-F86,"")),"") -> 125000 | L86: =IF(K86<>"",IF(H86<>"",IF(H86<>0,K86/H86,""),IF(F86<>"",IF(F86<>0,K86/F86,""),"")),"") -> 0.11111111
A88: 📅 Tuesday, 09 June 2026
A89: No | B89: Nama Barang | C89: Satuan | D89: Qty | E89: 📊 ESTIMASI | G89: 🧾 REALISASI BELI | I89: 💰 PENJUALAN | K89: 📈 MARGIN | M89: Keterangan
A90: No | B90: Nama Barang | C90: Satuan | D90: Qty | E90: Est. Harga Beli (Rp) | F90: Total Estimasi (Rp) | G90: Harga Beli Nota (Rp) | H90: Total Beli Nota (Rp) | I90: Harga Jual (Rp) | J90: Total Jual (Rp) | K90: Margin (Rp) | L90: Margin (%) | M90: Keterangan
A91: 1 | B91: Plastik Es Ukuran 12x25 cm isi 100 | C91: Pack | D91: 15 | F91: =IF(E91<>"",D91*E91,"") | G91: 15000 | H91: =IF(G91<>"",D91*G91,"") -> 225000 | I91: 17500 | J91: =IF(I91<>"",D91*I91,"") -> 262500 | K91: =IF(J91<>"",IF(H91<>"",J91-H91,IF(F91<>"",J91-F91,"")),"") -> 37500 | L91: =IF(K91<>"",IF(H91<>"",IF(H91<>0,K91/H91,""),IF(F91<>"",IF(F91<>0,K91/F91,""),"")),"") -> 0.16666667
A92: 2 | B92: Cup Sambal 25 ml | C92: Pcs | D92: 700 | G92: 225 | H92: =IF(G92<>"",D92*G92,"") -> 157500 | I92: 250 | J92: =IF(I92<>"",D92*I92,"") -> 175000 | K92: =IF(J92<>"",IF(H92<>"",J92-H92,IF(F92<>"",J92-F92,"")),"") -> 17500 | L92: =IF(K92<>"",IF(H92<>"",IF(H92<>0,K92/H92,""),IF(F92<>"",IF(F92<>0,K92/F92,""),"")),"") -> 0.11111111
A93: 3 | B93: Thinwall 200 Ml | C93: Pcs | D93: 1225 | G93: 640 | H93: =IF(G93<>"",D93*G93,"") -> 784000 | I93: 750 | J93: =IF(I93<>"",D93*I93,"") -> 918750 | K93: =IF(J93<>"",IF(H93<>"",J93-H93,IF(F93<>"",J93-F93,"")),"") -> 134750 | L93: =IF(K93<>"",IF(H93<>"",IF(H93<>0,K93/H93,""),IF(F93<>"",IF(F93<>0,K93/F93,""),"")),"") -> 0.171875
A94: 4 | B94: Goodday | C94: Dus | D94: 1 | G94: 205000 | H94: =IF(G94<>"",D94*G94,"") -> 205000 | I94: 210000 | J94: =IF(I94<>"",D94*I94,"") -> 210000 | K94: =IF(J94<>"",IF(H94<>"",J94-H94,IF(F94<>"",J94-F94,"")),"") -> 5000 | L94: =IF(K94<>"",IF(H94<>"",IF(H94<>0,K94/H94,""),IF(F94<>"",IF(F94<>0,K94/F94,""),"")),"") -> 0.024390244
A95: 5 | B95: Plastik Es Ukuran 12x25 cm isi 100 | C95: Pack | D95: 15 | F95: =IF(E95<>"",D95*E95,"") | G95: 15000 | H95: =IF(G95<>"",D95*G95,"") -> 225000 | I95: 17500 | J95: =IF(I95<>"",D95*I95,"") -> 262500 | K95: =IF(J95<>"",IF(H95<>"",J95-H95,IF(F95<>"",J95-F95,"")),"") -> 37500 | L95: =IF(K95<>"",IF(H95<>"",IF(H95<>0,K95/H95,""),IF(F95<>"",IF(F95<>0,K95/F95,""),"")),"") -> 0.16666667
A96: 09 June SUBTOTAL | F96: =SUMIF(F91:F95,"<>",F91:F95) -> 0 | H96: =SUMIF(H91:H95,"<>",H91:H95) -> 1596500 | J96: =SUMIF(J91:J95,"<>",J91:J95) -> 1828750 | K96: =IF(J96<>"",IF(H96<>"",J96-H96,IF(F96<>"",J96-F96,"")),"") -> 232250 | L96: =IF(K96<>"",IF(H96<>"",IF(H96<>0,K96/H96,""),IF(F96<>"",IF(F96<>0,K96/F96,""),"")),"") -> 0.14547448
A98: 📅 Wednesday, 10 June 2026
A99: No | B99: Nama Barang | C99: Satuan | D99: Qty | E99: 📊 ESTIMASI | G99: 🧾 REALISASI BELI | I99: 💰 PENJUALAN | K99: 📈 MARGIN | M99: Keterangan
A100: No | B100: Nama Barang | C100: Satuan | D100: Qty | E100: Est. Harga Beli (Rp) | F100: Total Estimasi (Rp) | G100: Harga Beli Nota (Rp) | H100: Total Beli Nota (Rp) | I100: Harga Jual (Rp) | J100: Total Jual (Rp) | K100: Margin (Rp) | L100: Margin (%) | M100: Keterangan
A101: 1 | B101: Soklin Lantai Sereh | C101: Drigen | D101: 2 | F101: =IF(E101<>"",D101*E101,"") | G101: 51000 | H101: =IF(G101<>"",D101*G101,"") -> 102000 | I101: 80000 | J101: =IF(I101<>"",D101*I101,"") -> 160000 | K101: =IF(J101<>"",IF(H101<>"",J101-H101,IF(F101<>"",J101-F101,"")),"") -> 58000 | L101: =IF(K101<>"",IF(H101<>"",IF(H101<>0,K101/H101,""),IF(F101<>"",IF(F101<>0,K101/F101,""),"")),"") -> 0.56862745
A102: 2 | B102: Kertas | C102: Rim | D102: 2 | F102: =IF(E102<>"",D102*E102,"") | G102: 42000 | H102: =IF(G102<>"",D102*G102,"") -> 84000 | I102: 50000 | J102: =IF(I102<>"",D102*I102,"") -> 100000 | K102: =IF(J102<>"",IF(H102<>"",J102-H102,IF(F102<>"",J102-F102,"")),"") -> 16000 | L102: =IF(K102<>"",IF(H102<>"",IF(H102<>0,K102/H102,""),IF(F102<>"",IF(F102<>0,K102/F102,""),"")),"") -> 0.19047619
A103: 3 | B103: Tisu Toilet | C103: Roll | D103: 10 | F103: =IF(E103<>"",D103*E103,"") | G103: 16000 | H103: =IF(G103<>"",D103*G103,"") -> 160000 | I103: 20000 | J103: =IF(I103<>"",D103*I103,"") -> 200000 | K103: =IF(J103<>"",IF(H103<>"",J103-H103,IF(F103<>"",J103-F103,"")),"") -> 40000 | L103: =IF(K103<>"",IF(H103<>"",IF(H103<>0,K103/H103,""),IF(F103<>"",IF(F103<>0,K103/F103,""),"")),"") -> 0.25
A104: 4 | B104: Tisu Wajah | C104: Pcs | D104: 18 | F104: =IF(E104<>"",D104*E104,"") | G104: 10000 | H104: =IF(G104<>"",D104*G104,"") -> 180000 | I104: 14000 | J104: =IF(I104<>"",D104*I104,"") -> 252000 | K104: =IF(J104<>"",IF(H104<>"",J104-H104,IF(F104<>"",J104-F104,"")),"") -> 72000 | L104: =IF(K104<>"",IF(H104<>"",IF(H104<>0,K104/H104,""),IF(F104<>"",IF(F104<>0,K104/F104,""),"")),"") -> 0.4
A105: 5 | B105: Tolak Angin Cair | C105: Dus | D105: 5 | F105: =IF(E105<>"",D105*E105,"") | G105: 46000 | H105: =IF(G105<>"",D105*G105,"") -> 230000 | I105: 55000 | J105: =IF(I105<>"",D105*I105,"") -> 275000 | K105: =IF(J105<>"",IF(H105<>"",J105-H105,IF(F105<>"",J105-F105,"")),"") -> 45000 | L105: =IF(K105<>"",IF(H105<>"",IF(H105<>0,K105/H105,""),IF(F105<>"",IF(F105<>0,K105/F105,""),"")),"") -> 0.19565217
A106: 6 | B106: Hansaplas | C106: Dus | D106: 1 | F106: =IF(E106<>"",D106*E106,"") | G106: 35000 | H106: =IF(G106<>"",D106*G106,"") -> 35000 | I106: 54000 | J106: =IF(I106<>"",D106*I106,"") -> 54000 | K106: =IF(J106<>"",IF(H106<>"",J106-H106,IF(F106<>"",J106-F106,"")),"") -> 19000 | L106: =IF(K106<>"",IF(H106<>"",IF(H106<>0,K106/H106,""),IF(F106<>"",IF(F106<>0,K106/F106,""),"")),"") -> 0.54285714
A107: 7 | B107: Minyak Kayu Putih Besar | C107: Pcs | D107: 1 | F107: =IF(E107<>"",D107*E107,"") | G107: 72000 | H107: =IF(G107<>"",D107*G107,"") -> 72000 | I107: 85000 | J107: =IF(I107<>"",D107*I107,"") -> 85000 | K107: =IF(J107<>"",IF(H107<>"",J107-H107,IF(F107<>"",J107-F107,"")),"") -> 13000 | L107: =IF(K107<>"",IF(H107<>"",IF(H107<>0,K107/H107,""),IF(F107<>"",IF(F107<>0,K107/F107,""),"")),"") -> 0.18055556
A108: 8 | B108: Koyo Cabe | C108: Pack | D108: 1 | F108: =IF(E108<>"",D108*E108,"") | G108: 220000 | H108: =IF(G108<>"",D108*G108,"") -> 220000 | I108: 250000 | J108: =IF(I108<>"",D108*I108,"") -> 250000 | K108: =IF(J108<>"",IF(H108<>"",J108-H108,IF(F108<>"",J108-F108,"")),"") -> 30000 | L108: =IF(K108<>"",IF(H108<>"",IF(H108<>0,K108/H108,""),IF(F108<>"",IF(F108<>0,K108/F108,""),"")),"") -> 0.13636364
A109: 9 | B109: Salonpas | C109: Pack | D109: 1 | F109: =IF(E109<>"",D109*E109,"") | G109: 86000 | H109: =IF(G109<>"",D109*G109,"") -> 86000 | I109: 100000 | J109: =IF(I109<>"",D109*I109,"") -> 100000 | K109: =IF(J109<>"",IF(H109<>"",J109-H109,IF(F109<>"",J109-F109,"")),"") -> 14000 | L109: =IF(K109<>"",IF(H109<>"",IF(H109<>0,K109/H109,""),IF(F109<>"",IF(F109<>0,K109/F109,""),"")),"") -> 0.1627907
A110: 10 | B110: Spons Cuci | C110: Pcs | D110: 10 | F110: =IF(E110<>"",D110*E110,"") | G110: 60000 | H110: =IF(G110<>"",D110*G110,"") -> 600000 | I110: 75000 | J110: =IF(I110<>"",D110*I110,"") -> 750000 | K110: =IF(J110<>"",IF(H110<>"",J110-H110,IF(F110<>"",J110-F110,"")),"") -> 150000 | L110: =IF(K110<>"",IF(H110<>"",IF(H110<>0,K110/H110,""),IF(F110<>"",IF(F110<>0,K110/F110,""),"")),"") -> 0.25
A111: 11 | B111: Energen | C111: Dus | D111: 1 | F111: =IF(E111<>"",D111*E111,"") | G111: 320000 | H111: =IF(G111<>"",D111*G111,"") -> 320000 | I111: 350000 | J111: =IF(I111<>"",D111*I111,"") -> 350000 | K111: =IF(J111<>"",IF(H111<>"",J111-H111,IF(F111<>"",J111-F111,"")),"") -> 30000 | L111: =IF(K111<>"",IF(H111<>"",IF(H111<>0,K111/H111,""),IF(F111<>"",IF(F111<>0,K111/F111,""),"")),"") -> 0.09375
...

Sheet Invoice Wer
A1: 🧾 DRAFT INVOICE — WERKUDARA
A2: Periode: 24–29 Mei 2026 | 🟢 Hijau = linked Daftar Harga | 🔵 Biru = input manual (isi setelah nota datang)
A3: Kolom G (Harga Beli Nota) dikosongkan — isi saat barang tiba. Margin: pakai Nota jika ada, fallback ke Estimasi.
A4: 📅 Sunday, 24 May 2026
A5: No | B5: Nama Barang | C5: Satuan | D5: Qty | E5: 📊 ESTIMASI | G5: 🧾 REALISASI BELI | I5: 💰 PENJUALAN | K5: 📈 MARGIN | M5: Keterangan
A6: No | B6: Nama Barang | C6: Satuan | D6: Qty | E6: Est. Harga Beli (Rp) | F6: Total Estimasi (Rp) | G6: Harga Beli Nota (Rp) | H6: Total Beli Nota (Rp) | I6: Harga Jual (Rp) | J6: Total Jual (Rp) | K6: Margin (Rp) | L6: Margin (%) | M6: Keterangan
A7: 1 | B7: Ayam Fillet | C7: Kg | D7: 117.4 | E7: ='Daftar Harga'!D8 -> 48000 | F7: =IF(E7<>"",D7*E7,"") -> 5635200 | G7: 46500 | H7: =IF(G7<>"",D7*G7,"") -> 5459100 | I7: 52500 | J7: =IF(I7<>"",D7*I7,"") -> 6163500 | K7: =IF(J7<>"",IF(H7<>"",J7-H7,IF(F7<>"",J7-F7,"")),"") -> 704400 | L7: =IF(K7<>"",IF(H7<>"",IF(H7<>0,K7/H7,""),IF(F7<>"",IF(F7<>0,K7/F7,""),"")),"") -> 0.12903226
A8: 2 | B8: Beras | C8: Kg | D8: 150 | E8: ='Daftar Harga'!D17 -> 15500 | F8: =IF(E8<>"",D8*E8,"") -> 2325000 | G8: 14500 | H8: =IF(G8<>"",D8*G8,"") -> 2175000 | I8: ='Daftar Harga'!E17 -> 15500 | J8: =IF(I8<>"",D8*I8,"") -> 2325000 | K8: =IF(J8<>"",IF(H8<>"",J8-H8,IF(F8<>"",J8-F8,"")),"") -> 150000 | L8: =IF(K8<>"",IF(H8<>"",IF(H8<>0,K8/H8,""),IF(F8<>"",IF(F8<>0,K8/F8,""),"")),"") -> 0.068965517
A9: 3 | B9: Gula merah | C9: Kg | D9: 2 | E9: ='Daftar Harga'!D35 -> 17000 | F9: =IF(E9<>"",D9*E9,"") -> 34000 | G9: 16000 | H9: =IF(G9<>"",D9*G9,"") -> 32000 | I9: 22000 | J9: =IF(I9<>"",D9*I9,"") -> 44000 | K9: =IF(J9<>"",IF(H9<>"",J9-H9,IF(F9<>"",J9-F9,"")),"") -> 12000 | L9: =IF(K9<>"",IF(H9<>"",IF(H9<>0,K9/H9,""),IF(F9<>"",IF(F9<>0,K9/F9,""),"")),"") -> 0.375
A10: 4 | B10: Kacang tanah giling | C10: Kg | D10: 22 | E10: ='Daftar Harga'!D47 -> 35000 | F10: =IF(E10<>"",D10*E10,"") -> 770000 | G10: 55000 | H10: =IF(G10<>"",D10*G10,"") -> 1210000 | I10: 60000 | J10: =IF(I10<>"",D10*I10,"") -> 1320000 | K10: =IF(J10<>"",IF(H10<>"",J10-H10,IF(F10<>"",J10-F10,"")),"") -> 110000 | L10: =IF(K10<>"",IF(H10<>"",IF(H10<>0,K10/H10,""),IF(F10<>"",IF(F10<>0,K10/F10,""),"")),"") -> 0.090909091
A11: 5 | B11: Kecap manis | C11: Dirigen | D11: 2 | E11: ='Daftar Harga'!D50 -> 190000 | F11: =IF(E11<>"",D11*E11,"") -> 380000 | G11: 190000 | H11: =IF(G11<>"",D11*G11,"") -> 380000 | I11: 210000 | J11: =IF(I11<>"",D11*I11,"") -> 420000 | K11: =IF(J11<>"",IF(H11<>"",J11-H11,IF(F11<>"",J11-F11,"")),"") -> 40000 | L11: =IF(K11<>"",IF(H11<>"",IF(H11<>0,K11/H11,""),IF(F11<>"",IF(F11<>0,K11/F11,""),"")),"") -> 0.10526316
A12: 6 | B12: Pisang | C12: Pcs | D12: 2225 | E12: ='Daftar Harga'!D71 -> 1900 | F12: =IF(E12<>"",D12*E12,"") -> 4227500 | G12: 1800 | H12: =IF(G12<>"",D12*G12,"") -> 4005000 | I12: 2000 | J12: =IF(I12<>"",D12*I12,"") -> 4450000 | K12: =IF(J12<>"",IF(H12<>"",J12-H12,IF(F12<>"",J12-F12,"")),"") -> 445000 | L12: =IF(K12<>"",IF(H12<>"",IF(H12<>0,K12/H12,""),IF(F12<>"",IF(F12<>0,K12/F12,""),"")),"") -> 0.11111111
A13: 7 | B13: Tahu Coklat | C13: Pcs | D13: 2225 | E13: ='Daftar Harga'!D90 -> 650 | F13: =IF(E13<>"",D13*E13,"") -> 1446250 | G13: 560 | H13: =IF(G13<>"",D13*G13,"") -> 1246000 | I13: 700 | J13: =IF(I13<>"",D13*I13,"") -> 1557500 | K13: =IF(J13<>"",IF(H13<>"",J13-H13,IF(F13<>"",J13-F13,"")),"") -> 311500 | L13: =IF(K13<>"",IF(H13<>"",IF(H13<>0,K13/H13,""),IF(F13<>"",IF(F13<>0,K13/F13,""),"")),"") -> 0.25
A14: 8 | B14: Timun | C14: Kg | D14: 75 | E14: ='Daftar Harga'!D99 -> 8000 | F14: =IF(E14<>"",D14*E14,"") -> 600000 | G14: 8000 | H14: =IF(G14<>"",D14*G14,"") -> 600000 | I14: 12000 | J14: =IF(I14<>"",D14*I14,"") -> 900000 | K14: =IF(J14<>"",IF(H14<>"",J14-H14,IF(F14<>"",J14-F14,"")),"") -> 300000 | L14: =IF(K14<>"",IF(H14<>"",IF(H14<>0,K14/H14,""),IF(F14<>"",IF(F14<>0,K14/F14,""),"")),"") -> 0.5
A15: 9 | B15: Wortel | C15: Kg | D15: 37 | E15: ='Daftar Harga'!D101 -> 9000 | F15: =IF(E15<>"",D15*E15,"") -> 333000 | G15: 12000 | H15: =IF(G15<>"",D15*G15,"") -> 444000 | I15: ='Daftar Harga'!E101 -> 14000 | J15: =IF(I15<>"",D15*I15,"") -> 518000 | K15: =IF(J15<>"",IF(H15<>"",J15-H15,IF(F15<>"",J15-F15,"")),"") -> 74000 | L15: =IF(K15<>"",IF(H15<>"",IF(H15<>0,K15/H15,""),IF(F15<>"",IF(F15<>0,K15/F15,""),"")),"") -> 0.16666667
A16: SUBTOTAL 24 May 2026 | F16: =SUMIF(F7:F15,"<>",F7:F15) -> 15750950 | H16: =SUMIF(H7:H15,"<>",H7:H15) -> 15551100 | J16: =SUMIF(J7:J15,"<>",J7:J15) -> 17698000 | K16: =IF(J16<>"",IF(H16<>"",J16-H16,IF(F16<>"",J16-F16,"")),"") -> 2146900 | L16: =IF(K16<>"",IF(H16<>"",IF(H16<>0,K16/H16,""),IF(F16<>"",IF(F16<>0,K16/F16,""),"")),"") -> 0.13805454
A18: 📅 Monday, 25 May 2026
A19: No | B19: Nama Barang | C19: Satuan | D19: Qty | E19: 📊 ESTIMASI | G19: 🧾 REALISASI BELI | I19: 💰 PENJUALAN | K19: 📈 MARGIN | M19: Keterangan
A20: No | B20: Nama Barang | C20: Satuan | D20: Qty | E20: Est. Harga Beli (Rp) | F20: Total Estimasi (Rp) | G20: Harga Beli Nota (Rp) | H20: Total Beli Nota (Rp) | I20: Harga Jual (Rp) | J20: Total Jual (Rp) | K20: Margin (Rp) | L20: Margin (%) | M20: Keterangan
A21: 1 | B21: Bawang Bombay | C21: Kg | D21: 5 | E21: ='Daftar Harga'!D12 -> 30000 | F21: =IF(E21<>"",D21*E21,"") -> 150000 | G21: 19000 | H21: =IF(G21<>"",D21*G21,"") -> 95000 | I21: 35000 | J21: =IF(I21<>"",D21*I21,"") -> 175000 | K21: =IF(J21<>"",IF(H21<>"",J21-H21,IF(F21<>"",J21-F21,"")),"") -> 80000 | L21: =IF(K21<>"",IF(H21<>"",IF(H21<>0,K21/H21,""),IF(F21<>"",IF(F21<>0,K21/F21,""),"")),"") -> 0.84210526
A22: 2 | B22: Bawang merah | C22: Kg | D22: 1 | E22: ='Daftar Harga'!D13 -> 28000 | F22: =IF(E22<>"",D22*E22,"") -> 28000 | G22: 36000 | H22: =IF(G22<>"",D22*G22,"") -> 36000 | I22: 38000 | J22: =IF(I22<>"",D22*I22,"") -> 38000 | K22: =IF(J22<>"",IF(H22<>"",J22-H22,IF(F22<>"",J22-F22,"")),"") -> 2000 | L22: =IF(K22<>"",IF(H22<>"",IF(H22<>0,K22/H22,""),IF(F22<>"",IF(F22<>0,K22/F22,""),"")),"") -> 0.055555556
A23: 3 | B23: Bawang putih | C23: Kg | D23: 1 | E23: ='Daftar Harga'!D15 -> 33000 | F23: =IF(E23<>"",D23*E23,"") -> 33000 | G23: 30000 | H23: =IF(G23<>"",D23*G23,"") -> 30000 | I23: 40000 | J23: =IF(I23<>"",D23*I23,"") -> 40000 | K23: =IF(J23<>"",IF(H23<>"",J23-H23,IF(F23<>"",J23-F23,"")),"") -> 10000 | L23: =IF(K23<>"",IF(H23<>"",IF(H23<>0,K23/H23,""),IF(F23<>"",IF(F23<>0,K23/F23,""),"")),"") -> 0.33333333
A24: 4 | B24: Beras | C24: Kg | D24: 100 | E24: ='Daftar Harga'!D17 -> 15500 | F24: =IF(E24<>"",D24*E24,"") -> 1550000 | G24: 14500 | H24: =IF(G24<>"",D24*G24,"") -> 1450000 | I24: 15500 | J24: =IF(I24<>"",D24*I24,"") -> 1550000 | K24: =IF(J24<>"",IF(H24<>"",J24-H24,IF(F24<>"",J24-F24,"")),"") -> 100000 | L24: =IF(K24<>"",IF(H24<>"",IF(H24<>0,K24/H24,""),IF(F24<>"",IF(F24<>0,K24/F24,""),"")),"") -> 0.068965517
A25: 5 | B25: Daun Salam | C25: Kg | D25: 0.3 | E25: ='Daftar Harga'!D32 -> 21600 | F25: =IF(E25<>"",D25*E25,"") -> 6480 | G25: 28000 | H25: =IF(G25<>"",D25*G25,"") -> 8400 | I25: 30000 | J25: =IF(I25<>"",D25*I25,"") -> 9000 | K25: =IF(J25<>"",IF(H25<>"",J25-H25,IF(F25<>"",J25-F25,"")),"") -> 600 | L25: =IF(K25<>"",IF(H25<>"",IF(H25<>0,K25/H25,""),IF(F25<>"",IF(F25<>0,K25/F25,""),"")),"") -> 0.071428571
A26: 6 | B26: Jagung pipil | C26: Kg | D26: 33 | E26: ='Daftar Harga'!D38 -> 24000 | F26: =IF(E26<>"",D26*E26,"") -> 792000 | G26: 23000 | H26: =IF(G26<>"",D26*G26,"") -> 759000 | I26: 27000 | J26: =IF(I26<>"",D26*I26,"") -> 891000 | K26: =IF(J26<>"",IF(H26<>"",J26-H26,IF(F26<>"",J26-F26,"")),"") -> 132000 | L26: =IF(K26<>"",IF(H26<>"",IF(H26<>0,K26/H26,""),IF(F26<>"",IF(F26<>0,K26/F26,""),"")),"") -> 0.17391304
A27: 7 | B27: Jeruk Super | C27: Kg | D27: 183.4 | E27: ='Daftar Harga'!D42 -> 27500 | F27: =IF(E27<>"",D27*E27,"") -> 5043500 | G27: 25000 | H27: =IF(G27<>"",D27*G27,"") -> 4585000 | I27: 27500 | J27: =IF(I27<>"",D27*I27,"") -> 5043500 | K27: =IF(J27<>"",IF(H27<>"",J27-H27,IF(F27<>"",J27-F27,"")),"") -> 458500 | L27: =IF(K27<>"",IF(H27<>"",IF(H27<>0,K27/H27,""),IF(F27<>"",IF(F27<>0,K27/F27,""),"")),"") -> 0.1
A28: 8 | B28: Labu Siam | C28: Kg | D28: 65 | E28: ='Daftar Harga'!D61 -> 9000 | F28: =IF(E28<>"",D28*E28,"") -> 585000 | G28: 9000 | H28: =IF(G28<>"",D28*G28,"") -> 585000 | I28: 14000 | J28: =IF(I28<>"",D28*I28,"") -> 910000 | K28: =IF(J28<>"",IF(H28<>"",J28-H28,IF(F28<>"",J28-F28,"")),"") -> 325000 | L28: =IF(K28<>"",IF(H28<>"",IF(H28<>0,K28/H28,""),IF(F28<>"",IF(F28<>0,K28/F28,""),"")),"") -> 0.55555556
A29: 9 | B29: Lada putih bubuk | C29: Kg | D29: 1 | E29: ='Daftar Harga'!D64 -> 140000 | F29: =IF(E29<>"",D29*E29,"") -> 140000 | G29: 140000 | H29: =IF(G29<>"",D29*G29,"") -> 140000 | I29: 180000 | J29: =IF(I29<>"",D29*I29,"") -> 180000 | K29: =IF(J29<>"",IF(H29<>"",J29-H29,IF(F29<>"",J29-F29,"")),"") -> 40000 | L29: =IF(K29<>"",IF(H29<>"",IF(H29<>0,K29/H29,""),IF(F29<>"",IF(F29<>0,K29/F29,""),"")),"") -> 0.28571429
A30: 10 | B30: Minyak | C30: Liter | D30: 10 | E30: ='Daftar Harga'!D69 -> 205000 | F30: =IF(E30<>"",D30*E30,"") -> 2050000 | G30: 22000 | H30: =IF(G30<>"",D30*G30,"") -> 220000 | I30: 23000 | J30: =IF(I30<>"",D30*I30,"") -> 230000 | K30: =IF(J30<>"",IF(H30<>"",J30-H30,IF(F30<>"",J30-F30,"")),"") -> 10000 | L30: =IF(K30<>"",IF(H30<>"",IF(H30<>0,K30/H30,""),IF(F30<>"",IF(F30<>0,K30/F30,""),"")),"") -> 0.045454545
A31: 11 | B31: Saus BBQ | C31: Kg | D31: 5 | E31: ='Daftar Harga'!D75 | F31: =IF(E31<>"",D31*E31,"") | G31: 35000 | H31: =IF(G31<>"",D31*G31,"") -> 175000 | I31: 40000 | J31: =IF(I31<>"",D31*I31,"") -> 200000 | K31: =IF(J31<>"",IF(H31<>"",J31-H31,IF(F31<>"",J31-F31,"")),"") -> 25000 | L31: =IF(K31<>"",IF(H31<>"",IF(H31<>0,K31/H31,""),IF(F31<>"",IF(F31<>0,K31/F31,""),"")),"") -> 0.14285714
A32: 12 | B32: Sereh | C32: Kg | D32: 0.4 | E32: ='Daftar Harga'!D86 -> 12000 | F32: =IF(E32<>"",D32*E32,"") -> 4800 | G32: 11000 | H32: =IF(G32<>"",D32*G32,"") -> 4400 | I32: 14000 | J32: =IF(I32<>"",D32*I32,"") -> 5600 | K32: =IF(J32<>"",IF(H32<>"",J32-H32,IF(F32<>"",J32-F32,"")),"") -> 1200 | L32: =IF(K32<>"",IF(H32<>"",IF(H32<>0,K32/H32,""),IF(F32<>"",IF(F32<>0,K32/F32,""),"")),"") -> 0.27272727
A33: 13 | B33: Telur Ayam | C33: Kg | D33: 126.7 | E33: ='Daftar Harga'!D92 -> 28000 | F33: =IF(E33<>"",D33*E33,"") -> 3547600 | G33: 25500 | H33: =IF(G33<>"",D33*G33,"") -> 3230850 | I33: 28000 | J33: =IF(I33<>"",D33*I33,"") -> 3547600 | K33: =IF(J33<>"",IF(H33<>"",J33-H33,IF(F33<>"",J33-F33,"")),"") -> 316750 | L33: =IF(K33<>"",IF(H33<>"",IF(H33<>0,K33/H33,""),IF(F33<>"",IF(F33<>0,K33/F33,""),"")),"") -> 0.098039216
A34: 14 | B34: Tempe | C34: Papan | D34: 75 | E34: ='Daftar Harga'!D93 -> 12000 | F34: =IF(E34<>"",D34*E34,"") -> 900000 | G34: 12000 | H34: =IF(G34<>"",D34*G34,"") -> 900000 | I34: 14000 | J34: =IF(I34<>"",D34*I34,"") -> 1050000 | K34: =IF(J34<>"",IF(H34<>"",J34-H34,IF(F34<>"",J34-F34,"")),"") -> 150000 | L34: =IF(K34<>"",IF(H34<>"",IF(H34<>0,K34/H34,""),IF(F34<>"",IF(F34<>0,K34/F34,""),"")),"") -> 0.16666667
A35: 15 | B35: Gula Pasir (Tambahan) | C35: Kg | D35: 2 | G35: 17500 | H35: =IF(G35<>"",D35*G35,"") -> 35000 | I35: 17500 | J35: =IF(I35<>"",D35*I35,"") -> 35000 | K35: =IF(J35<>"",IF(H35<>"",J35-H35,IF(F35<>"",J35-F35,"")),"") -> 0 | L35: =IF(K35<>"",IF(H35<>"",IF(H35<>0,K35/H35,""),IF(F35<>"",IF(F35<>0,K35/F35,""),"")),"") -> 0
A36: 16 | B36: Gula Pasir (Tambahan) | C36: kg | D36: 2 | G36: 17500 | H36: =IF(G36<>"",D36*G36,"") -> 35000 | I36: 17500 | J36: =IF(I36<>"",D36*I36,"") -> 35000 | K36: =IF(J36<>"",IF(H36<>"",J36-H36,IF(F36<>"",J36-F36,"")),"") -> 0 | L36: =IF(K36<>"",IF(H36<>"",IF(H36<>0,K36/H36,""),IF(F36<>"",IF(F36<>0,K36/F36,""),"")),"") -> 0
A37: 17 | B37: Gula Pasir (Tambahan) | C37: kg | D37: 2 | G37: 17500 | H37: =IF(G37<>"",D37*G37,"") -> 35000 | I37: 17500 | J37: =IF(I37<>"",D37*I37,"") -> 35000 | K37: =IF(J37<>"",IF(H37<>"",J37-H37,IF(F37<>"",J37-F37,"")),"") -> 0 | L37: =IF(K37<>"",IF(H37<>"",IF(H37<>0,K37/H37,""),IF(F37<>"",IF(F37<>0,K37/F37,""),"")),"") -> 0
A38: SUBTOTAL 25 May 2026 | F38: =SUMIF(F21:F37,"<>",F21:F37) -> 14830380 | H38: =SUMIF(H21:H37,"<>",H21:H37) -> 12323650 | J38: =SUMIF(J21:J37,"<>",J21:J37) -> 13974700 | K38: =IF(J38<>"",IF(H38<>"",J38-H38,IF(F38<>"",J38-F38,"")),"") -> 1651050 | L38: =IF(K38<>"",IF(H38<>"",IF(H38<>0,K38/H38,""),IF(F38<>"",IF(F38<>0,K38/F38,""),"")),"") -> 0.13397411
A40: 📅 Thursday, 28 May 2026
A41: No | B41: Nama Barang | C41: Satuan | D41: Qty | E41: 📊 ESTIMASI | G41: 🧾 REALISASI BELI | I41: 💰 PENJUALAN | K41: 📈 MARGIN | M41: Keterangan
A42: No | B42: Nama Barang | C42: Satuan | D42: Qty | E42: Est. Harga Beli (Rp) | F42: Total Estimasi (Rp) | G42: Harga Beli Nota (Rp) | H42: Total Beli Nota (Rp) | I42: Harga Jual (Rp) | J42: Total Jual (Rp) | K42: Margin (Rp) | L42: Margin (%) | M42: Keterangan
A43: 1 | B43: Beras | C43: Kg | D43: 100 | F43: =IF(E43<>"",D43*E43,"") | G43: 14500 | H43: =IF(G43<>"",D43*G43,"") -> 1450000 | I43: 15500 | J43: =IF(I43<>"",D43*I43,"") -> 1550000 | K43: =IF(J43<>"",IF(H43<>"",J43-H43,IF(F43<>"",J43-F43,"")),"") -> 100000 | L43: =IF(K43<>"",IF(H43<>"",IF(H43<>0,K43/H43,""),IF(F43<>"",IF(F43<>0,K43/F43,""),"")),"") -> 0.068965517
A44: 2 | B44: Ayam Potong | C44: Kg | D44: 308 | F44: =IF(E44<>"",D44*E44,"") | G44: 35000 | H44: =IF(G44<>"",D44*G44,"") -> 10780000 | I44: 38000 | J44: =IF(I44<>"",D44*I44,"") -> 11704000 | K44: =IF(J44<>"",IF(H44<>"",J44-H44,IF(F44<>"",J44-F44,"")),"") -> 924000 | L44: =IF(K44<>"",IF(H44<>"",IF(H44<>0,K44/H44,""),IF(F44<>"",IF(F44<>0,K44/F44,""),"")),"") -> 0.085714286
A45: 3 | B45: Tahu Coklat | C45: Kg | D45: 4265 | F45: =IF(E45<>"",D45*E45,"") | G45: 560 | H45: =IF(G45<>"",D45*G45,"") -> 2388400 | I45: 700 | J45: =IF(I45<>"",D45*I45,"") -> 2985500 | K45: =IF(J45<>"",IF(H45<>"",J45-H45,IF(F45<>"",J45-F45,"")),"") -> 597100 | L45: =IF(K45<>"",IF(H45<>"",IF(H45<>0,K45/H45,""),IF(F45<>"",IF(F45<>0,K45/F45,""),"")),"") -> 0.25
A46: 4 | B46: Kol | C46: Kg | D46: 37 | F46: =IF(E46<>"",D46*E46,"") | G46: 10000 | H46: =IF(G46<>"",D46*G46,"") -> 370000 | I46: 12000 | J46: =IF(I46<>"",D46*I46,"") -> 444000 | K46: =IF(J46<>"",IF(H46<>"",J46-H46,IF(F46<>"",J46-F46,"")),"") -> 74000 | L46: =IF(K46<>"",IF(H46<>"",IF(H46<>0,K46/H46,""),IF(F46<>"",IF(F46<>0,K46/F46,""),"")),"") -> 0.2
A47: 5 | B47: Wortel | C47: Kg | D47: 29 | F47: =IF(E47<>"",D47*E47,"") | G47: 10000 | H47: =IF(G47<>"",D47*G47,"") -> 290000 | I47: 12000 | J47: =IF(I47<>"",D47*I47,"") -> 348000 | K47: =IF(J47<>"",IF(H47<>"",J47-H47,IF(F47<>"",J47-F47,"")),"") -> 58000 | L47: =IF(K47<>"",IF(H47<>"",IF(H47<>0,K47/H47,""),IF(F47<>"",IF(F47<>0,K47/F47,""),"")),"") -> 0.2
A48: 6 | B48: Pisang Ambon | C48: Kg | D48: 2960 | F48: =IF(E48<>"",D48*E48,"") | G48: 1800 | H48: =IF(G48<>"",D48*G48,"") -> 5328000 | I48: 2000 | J48: =IF(I48<>"",D48*I48,"") -> 5920000 | K48: =IF(J48<>"",IF(H48<>"",J48-H48,IF(F48<>"",J48-F48,"")),"") -> 592000 | L48: =IF(K48<>"",IF(H48<>"",IF(H48<>0,K48/H48,""),IF(F48<>"",IF(F48<>0,K48/F48,""),"")),"") -> 0.11111111
A49: 7 | B49: Mentega | C49: Dirigen | D49: 2 | F49: =IF(E49<>"",D49*E49,"") | G49: 25000 | H49: =IF(G49<>"",D49*G49,"") -> 50000 | I49: 27000 | J49: =IF(I49<>"",D49*I49,"") -> 54000 | K49: =IF(J49<>"",IF(H49<>"",J49-H49,IF(F49<>"",J49-F49,"")),"") -> 4000 | L49: =IF(K49<>"",IF(H49<>"",IF(H49<>0,K49/H49,""),IF(F49<>"",IF(F49<>0,K49/F49,""),"")),"") -> 0.08
A50: 8 | B50: Bawang Bombay | C50: Kg | D50: 3 | F50: =IF(E50<>"",D50*E50,"") | G50: 19000 | H50: =IF(G50<>"",D50*G50,"") -> 57000 | I50: 35000 | J50: =IF(I50<>"",D50*I50,"") -> 105000 | K50: =IF(J50<>"",IF(H50<>"",J50-H50,IF(F50<>"",J50-F50,"")),"") -> 48000 | L50: =IF(K50<>"",IF(H50<>"",IF(H50<>0,K50/H50,""),IF(F50<>"",IF(F50<>0,K50/F50,""),"")),"") -> 0.84210526
A51: 9 | B51: Garam | C51: Kg | D51: 1 | F51: =IF(E51<>"",D51*E51,"") | G51: 7000 | H51: =IF(G51<>"",D51*G51,"") -> 7000 | I51: 10000 | J51: =IF(I51<>"",D51*I51,"") -> 10000 | K51: =IF(J51<>"",IF(H51<>"",J51-H51,IF(F51<>"",J51-F51,"")),"") -> 3000 | L51: =IF(K51<>"",IF(H51<>"",IF(H51<>0,K51/H51,""),IF(F51<>"",IF(F51<>0,K51/F51,""),"")),"") -> 0.42857143
A52: 10 | B52: Bawang Putih Kupas | C52: Kg | D52: 1.5 | F52: =IF(E52<>"",D52*E52,"") | G52: 30000 | H52: =IF(G52<>"",D52*G52,"") -> 45000 | I52: 40000 | J52: =IF(I52<>"",D52*I52,"") -> 60000 | K52: =IF(J52<>"",IF(H52<>"",J52-H52,IF(F52<>"",J52-F52,"")),"") -> 15000 | L52: =IF(K52<>"",IF(H52<>"",IF(H52<>0,K52/H52,""),IF(F52<>"",IF(F52<>0,K52/F52,""),"")),"") -> 0.33333333
A53: 11 | B53: Mayonaise Mc Lewis Biru | C53: Liter | D53: 9 | F53: =IF(E53<>"",D53*E53,"") | G53: 23500 | H53: =IF(G53<>"",D53*G53,"") -> 211500 | I53: 26000 | J53: =IF(I53<>"",D53*I53,"") -> 234000 | K53: =IF(J53<>"",IF(H53<>"",J53-H53,IF(F53<>"",J53-F53,"")),"") -> 22500 | L53: =IF(K53<>"",IF(H53<>"",IF(H53<>0,K53/H53,""),IF(F53<>"",IF(F53<>0,K53/F53,""),"")),"") -> 0.10638298
A54: 12 | B54: Bawang Merah Kupas | C54: Pcs | D54: 1 | F54: =IF(E54<>"",D54*E54,"") | G54: 40000 | H54: =IF(G54<>"",D54*G54,"") -> 40000 | I54: 45000 | J54: =IF(I54<>"",D54*I54,"") -> 45000 | K54: =IF(J54<>"",IF(H54<>"",J54-H54,IF(F54<>"",J54-F54,"")),"") -> 5000 | L54: =IF(K54<>"",IF(H54<>"",IF(H54<>0,K54/H54,""),IF(F54<>"",IF(F54<>0,K54/F54,""),"")),"") -> 0.125
... A56: 14 | B56: Gula Pasir | C56: Pcs | D56: 1 | F56: =IF(E56<>"",D56*E56,"") | G56: 18500 | H56: =IF(G56<>"",D56*G56,"") -> 18500 | I56: 20000 | J56: =IF(I56<>"",D56*I56,"") -> 20000 | K56: =IF(J56<>"",IF(H56<>"",J56-H56,IF(F56<>"",J56-F56,"")),"") -> 1500 | L56: =IF(K56<>"",IF(H56<>"",IF(H56<>0,K56/H56,""),IF(F56<>"",IF(F56<>0,K56/F56,""),"")),"") -> 0.081081081
A57: SUBTOTAL 28 May 2026 | F57: =SUMIF(F43:F56,"<>",F43:F56) -> 0 | H57: =SUMIF(H43:H56,"<>",H43:H56) -> 21125400 | J57: =SUMIF(J43:J56,"<>",J43:J56) -> 23594500 | K57: =IF(J57<>"",IF(H57<>"",J57-H57,IF(F57<>"",J57-F57,"")),"") -> 2469100 | L57: =IF(K57<>"",IF(H57<>"",IF(H57<>0,K57/H57,""),IF(F57<>"",IF(F57<>0,K57/F57,""),"")),"") -> 0.11687826
A59: 📅 Friday, 29 May 2026
